Workbook
Name CM: #REF!
Name CMAC: [1]CM!#REF!
Name CMAC: [2]CM!#REF!
Name CR: #REF!
Name CRAC: [1]CR!#REF!
Name CRAC: [2]CR!#REF!
Name CREDEP: #REF!
Name d: #REF!
Name DATA11: '[3]BASE DATA'!$A$1:$B$111
Name DATA11: '[4]BASE DATA'!$A$1:$B$111
Name DATA12: '[3]BASE DATA'!$A$2:$B$112
Name DATA12: '[4]BASE DATA'!$A$2:$B$112
Name DATA13: '[3]BASE DATA'!$A$2:$B$113
Name DATA13: '[4]BASE DATA'!$A$2:$B$113
Name DATA14: '[3]BASE DATA'!$A$1:$B$114
Name DATA14: '[4]BASE DATA'!$A$1:$B$114
Name DATA4: '[3]BASE DATA'!$A$2:$B$85
Name DATA4: '[4]BASE DATA'!$A$2:$B$85
Name DATA5: '[3]BASE DATA'!$A$1:$B$87
Name DATA5: '[4]BASE DATA'!$A$1:$B$87
Name DATA6: '[3]BASE DATA'!$A$1:$B$88
Name DATA6: '[4]BASE DATA'!$A$1:$B$88
Name DATA7: '[3]BASE DATA'!$A$2:$B$89
Name DATA7: '[4]BASE DATA'!$A$2:$B$89
Name DATA8: '[3]BASE DATA'!$A$1:$B$90
Name DATA8: '[4]BASE DATA'!$A$1:$B$90
Name DATA9: '[3]BASE DATA'!$A$1:$B$91
Name DATA9: '[4]BASE DATA'!$A$1:$B$91
Name DEPDEP: #REF!
Name EDP: [1]ED!#REF!
Name EDP: [2]ED!#REF!
Name EDPYME: #REF!
Name EstatalAgregado: #REF!
Name EstatalPorTipo: #REF!
Name FECHA: '[5]GRUPOS POR TIPO'!$D$3:$IV$3
Name FECHA: '[6]GRUPOS POR TIPO'!$D$3:$IV$3
Name GAdmin: #REF!
Name GAdmin: #REF!
Name Indic.Propuestos: #REF!
Name INDICE: #REF!
Name IngresF: #REF!
Name IngresF: #REF!
Name MFinanc: #REF!
Name MFinanc: #REF!
Name PrivadoAgregado: #REF!
Name PrivadoPorTipos: #REF!
Name SIFAgregado: #REF!
Name SIFporTipo: '[7]SIST FIN TOTAL POR TIPO'!$3:$8
Name Utilid: #REF!
Name Utilid: #REF!

Sheet Definic tipos cred SBS
A2: CLASIFICACIÓN DE CRÉDITOS
A4: La Resolución SBS N° 2368-2023, que modifica el "Reglamento para la Evaluación y Clasificación del Deudor y la Exigencia de Provisiones" (Resolución SBS N° 11356-2008), establece nuevos criterios para la tipificación de créditos los cuales entraron en vigor en octubre de 2024, estableciéndose las siguientes definiciones:
A6: Corporativos
A7: Créditos corporativos del sector real: Créditos otorgados a personas o entes jurídicos con ventas o ingresos anuales mayores a S/ 200 millones en los dos últimos periodos, declarados a la Autoridad Tributaria o de acuerdo a los estados financieros anuales auditados más recientes. Adicionalmente, se consideran como créditos corporativos a los créditos soberanos, créditos concedidos a bancos multilaterales de desarrollo, a entidades del sector público, a intermediarios de valores, a empresas del sistema financiero, a empresas del sistema de seguros, a los patrimonios autónomos de seguro de crédito, a fondos de garantía constituidos conforme a Ley y a otros fondos de garantía
A9: Créditos a Grandes empresas
A10: Créditos otorgados a personas o entes jurídicos con ventas o ingresos anuales mayores a S/ 20 millones en los dos últimos períodos, declarados a la Autoridad Tributaria.
A12: Créditos a Medianas empresas
A13: Créditos otorgados a personas o entes jurídicos que no cumplen con las condiciones para ser tipificados como corporativos o grandes empresas y que hayan registrado ventas o ingresos anuales de actividades ordinarias en el último período declarado a la Autoridad Tributaria mayores a S/ 5 millones y no cumplen con las características para ser clasificados como corporativos o grandes empresas.
A15: Créditos a Pequeñas empresas
A16: Créditos destinados a financiar actividades de producción, comercialización, prestación de servicios u otras actividades empresariales, otorgados a personas jurídicas o personas naturales que hayan registrado un nivel de ventas o ingresos anuales de actividades ordinarias en el último período no mayor a S/ 5 millones y siempre que su nivel de endeudamiento total en el sistema financiero sea mayor a S/ 20 mil en al menos uno de los últimos 6 meses, o siempre que el nuevo crédito desembolsado sea mayor a dicho monto. En el caso de persona natural, el nivel de endeudamiento total en el sistema financiero antes mencionado no incluye los créditos hipotecarios para vivienda.
A18: Créditos a Microempresas
A19: Créditos destinados a financiar actividades de producción, comercialización, prestación de servicios u otras actividades empresariales, otorgados a personas jurídicas o personas naturales que hayan registrado un nivel de ventas o ingresos anuales en el último período no mayor a S/ 5 millones, y siempre que su nivel de endeudamiento total en el sistema financiero sea no mayor a S/ 20 mil en los últimos 6 meses, y que el nuevo crédito desembolsado sea no mayor a S/ 20 mil. En el caso de persona natural, el nivel de endeudamiento total en el sistema financiero antes mencionado no incluye los créditos hipotecarios para vivienda.
... A25: Créditos otorgados a personas naturales para la adquisición, construcción, refacción, remodelación, ampliación, mejoramiento y subdivisión de vivienda propia, siempre que tales créditos se otorguen amparados con hipotecas debidamente inscritas; sea que estos créditos se otorguen por el sistema convencional de préstamo hipotecario, de letras hipotecarias o por cualquier otro sistema de similares características.

Sheet BaseIBK
A1: Departamento | B1: Provincia | C1: Distrito | D1: Ubigeo | E1: Poblacion | F1: Nro_mypes | G1: ventas_mypes_totales | H1: ventas_mypes_promedio | I1: Corp_Banca_Multiple | J1: Corp_Empresas_Financieras | K1: Corp_Cajas_Municipales | L1: Corp_Cajas_Rurales_Ah_y_Cred | M1: Corp_Empresas_Creditos | N1: Corp_Total | O1: GE_Banca_Multiple | P1: GE_Empresas_Financieras | Q1: GE_Cajas_Municipales | R1: GE_Cajas_Rurales_Ah_y_Cred | S1: GE_Empresas_Creditos | T1: GE_Total | U1: ME_Banca_Multiple | V1: ME_Empresas_Financieras | W1: ME_Cajas_Municipales | X1: ME_Cajas_Rurales_Ah_y_Cred | Y1: ME_Empresas_Creditos | Z1: ME_Total | AA1: PE_Banca_Multiple | AB1: PE_Empresas_Financieras | AC1: PE_Cajas_Municipales | AD1: PE_Cajas_Rurales_Ah_y_Cred | AE1: PE_Empresas_Creditos | AF1: PE_Total | AG1: MI_Banca_Multiple | AH1: MI_Empresas_Financieras | AI1: MI_Cajas_Municipales | AJ1: MI_Cajas_Rurales_Ah_y_Cred | AK1: MI_Empresas_Creditos | AL1: MI_Total | AM1: Con_Banca_Multiple | AN1: Con_Empresas_Financieras | AO1: Con_Cajas_Municipales | AP1: Con_Cajas_Rurales_Ah_y_Cred | AQ1: Con_Empresas_Creditos | AR1: Con_Total | AS1: Hi_Banca_Multiple | AT1: Hi_Empresas_Financieras | AU1: Hi_Cajas_Municipales | AV1: Hi_Cajas_Rurales_Ah_y_Cred | AW1: Hi_Empresas_Creditos | AX1: Hi_Total | AY1: CD_Total | AZ1: Mas100milhab | BA1: n_rt | BB1: venta_mean_rt | BC1: venta_sum_rt | BD1: plin_mean_rt | BE1: izipay_mean_rt | BF1: n_univ | BG1: plin_mean_univ | BH1: izipay_mean_univ
A2: AMAZONAS | B2: CHACHAPOYAS | C2: CHACHAPOYAS | D2: 010101 | E2: 41335 | F2: 299 | G2: 268.7399 | H2: 0.8987958 | I2: 0.01 | J2: 0 | K2: 0 | L2: 0 | M2: 0 | N2: 0.01 | O2: 0 | P2: 0 | Q2: 111.3 | R2: 0 | S2: 0 | T2: 111.3 | U2: 568.84 | V2: 0 | W2: 3756.42 | X2: 0 | Y2: 0 | Z2: 4325.26 | AA2: 100470.98 | AB2: 36731.51 | AC2: 114461.2 | AD2: 5389.1 | AE2: 0 | AF2: 257052.79 | AG2: 9009.28 | AH2: 9546 | AI2: 15790.21 | AJ2: 1719.29 | AK2: 0 | AL2: 36064.78 | AM2: 6828.51 | AN2: 10346.22 | AO2: 51571.89 | AP2: 714.37 | AQ2: 0 | AR2: 69460.99 | AS2: 5608.56 | AT2: 0 | AU2: 6468.75 | AV2: 0 | AW2: 0 | AX2: 12077.31 | AY2: 379092.44 | AZ2: 0 | BA2: 22 | BB2: 34183.793 | BC2: 752043.45 | BD2: 34.090909 | BE2: 1546.709 | BF2: 737 | BG2: 1286.6637 | BH2: 1968.134
A3: AMAZONAS | B3: CHACHAPOYAS | C3: ASUNCION | D3: 010102 | E3: 271 | F3: . | G3: . | H3: . | I3: 0 | J3: 0 | K3: 0 | L3: 0 | M3: 0 | N3: 0 | O3: 0 | P3: 0 | Q3: 0 | R3: 0 | S3: 0 | T3: 0 | U3: 0 | V3: 0 | W3: 0 | X3: 0 | Y3: 0 | Z3: 0 | AA3: 0 | AB3: 0 | AC3: 0 | AD3: 0 | AE3: 0 | AF3: 0 | AG3: 0 | AH3: 0 | AI3: 0 | AJ3: 0 | AK3: 0 | AL3: 0 | AM3: 0 | AN3: 0 | AO3: 0 | AP3: 0 | AQ3: 0 | AR3: 0 | AS3: 0 | AT3: 0 | AU3: 0 | AV3: 0 | AW3: 0 | AX3: 0 | AY3: 0 | AZ3: 0 | BA3: 0 | BB3: 0 | BC3: 0 | BD3: 0 | BE3: 0 | BF3: 1 | BG3: 0 | BH3: 0
A4: AMAZONAS | B4: CHACHAPOYAS | C4: BALSAS | D4: 010103 | E4: 1137 | F4: . | G4: . | H4: . | I4: 0 | J4: 0 | K4: 0 | L4: 0 | M4: 0 | N4: 0 | O4: 0 | P4: 0 | Q4: 0 | R4: 0 | S4: 0 | T4: 0 | U4: 0 | V4: 0 | W4: 0 | X4: 0 | Y4: 0 | Z4: 0 | AA4: 0 | AB4: 0 | AC4: 0 | AD4: 0 | AE4: 0 | AF4: 0 | AG4: 0 | AH4: 0 | AI4: 0 | AJ4: 0 | AK4: 0 | AL4: 0 | AM4: 0 | AN4: 0 | AO4: 0 | AP4: 0 | AQ4: 0 | AR4: 0 | AS4: 0 | AT4: 0 | AU4: 0 | AV4: 0 | AW4: 0 | AX4: 0 | AY4: 0 | AZ4: 0 | BA4: 0 | BB4: 0 | BC4: 0 | BD4: 0 | BE4: 0 | BF4: 7 | BG4: 0 | BH4: 0
A5: AMAZONAS | B5: CHACHAPOYAS | C5: CHETO | D5: 010104 | E5: 713 | F5: 1 | G5: 0.205 | H5: 0.205 | I5: 0 | J5: 0 | K5: 0 | L5: 0 | M5: 0 | N5: 0 | O5: 0 | P5: 0 | Q5: 0 | R5: 0 | S5: 0 | T5: 0 | U5: 0 | V5: 0 | W5: 0 | X5: 0 | Y5: 0 | Z5: 0 | AA5: 0 | AB5: 0 | AC5: 0 | AD5: 0 | AE5: 0 | AF5: 0 | AG5: 0 | AH5: 0 | AI5: 0 | AJ5: 0 | AK5: 0 | AL5: 0 | AM5: 0 | AN5: 0 | AO5: 0 | AP5: 0 | AQ5: 0 | AR5: 0 | AS5: 0 | AT5: 0 | AU5: 0 | AV5: 0 | AW5: 0 | AX5: 0 | AY5: 0 | AZ5: 0 | BA5: 0 | BB5: 0 | BC5: 0 | BD5: 0 | BE5: 0 | BF5: 5 | BG5: 0 | BH5: 0
A6: AMAZONAS | B6: CHACHAPOYAS | C6: CHILIQUIN | D6: 010105 | E6: 561 | F6: . | G6: . | H6: . | I6: 0 | J6: 0 | K6: 0 | L6: 0 | M6: 0 | N6: 0 | O6: 0 | P6: 0 | Q6: 0 | R6: 0 | S6: 0 | T6: 0 | U6: 0 | V6: 0 | W6: 0 | X6: 0 | Y6: 0 | Z6: 0 | AA6: 0 | AB6: 0 | AC6: 0 | AD6: 0 | AE6: 0 | AF6: 0 | AG6: 0 | AH6: 0 | AI6: 0 | AJ6: 0 | AK6: 0 | AL6: 0 | AM6: 0 | AN6: 0 | AO6: 0 | AP6: 0 | AQ6: 0 | AR6: 0 | AS6: 0 | AT6: 0 | AU6: 0 | AV6: 0 | AW6: 0 | AX6: 0 | AY6: 0 | AZ6: 0 | BA6: 0 | BB6: 0 | BC6: 0 | BD6: 0 | BE6: 0 | BF6: 2 | BG6: 0 | BH6: 0
A7: AMAZONAS | B7: CHACHAPOYAS | C7: CHUQUIBAMBA | D7: 010106 | E7: 1884 | F7: . | G7: . | H7: . | I7: 0 | J7: 0 | K7: 0 | L7: 0 | M7: 0 | N7: 0 | O7: 0 | P7: 0 | Q7: 0 | R7: 0 | S7: 0 | T7: 0 | U7: 0 | V7: 0 | W7: 0 | X7: 0 | Y7: 0 | Z7: 0 | AA7: 0 | AB7: 0 | AC7: 0 | AD7: 0 | AE7: 0 | AF7: 0 | AG7: 0 | AH7: 0 | AI7: 0 | AJ7: 0 | AK7: 0 | AL7: 0 | AM7: 0 | AN7: 0 | AO7: 0 | AP7: 0 | AQ7: 0 | AR7: 0 | AS7: 0 | AT7: 0 | AU7: 0 | AV7: 0 | AW7: 0 | AX7: 0 | AY7: 0 | AZ7: 0 | BA7: 0 | BB7: 0 | BC7: 0 | BD7: 0 | BE7: 0 | BF7: 1 | BG7: 0 | BH7: 0
A8: AMAZONAS | B8: CHACHAPOYAS | C8: GRANADA | D8: 010107 | E8: 549 | F8: . | G8: . | H8: . | I8: 0 | J8: 0 | K8: 0 | L8: 0 | M8: 0 | N8: 0 | O8: 0 | P8: 0 | Q8: 0 | R8: 0 | S8: 0 | T8: 0 | U8: 0 | V8: 0 | W8: 0 | X8: 0 | Y8: 0 | Z8: 0 | AA8: 0 | AB8: 0 | AC8: 0 | AD8: 0 | AE8: 0 | AF8: 0 | AG8: 0 | AH8: 0 | AI8: 0 | AJ8: 0 | AK8: 0 | AL8: 0 | AM8: 0 | AN8: 0 | AO8: 0 | AP8: 0 | AQ8: 0 | AR8: 0 | AS8: 0 | AT8: 0 | AU8: 0 | AV8: 0 | AW8: 0 | AX8: 0 | AY8: 0 | AZ8: 0 | BA8: 0 | BB8: 0 | BC8: 0 | BD8: 0 | BE8: 0 | BF8: 1 | BG8: 0 | BH8: 0
A9: AMAZONAS | B9: CHACHAPOYAS | C9: HUANCAS | D9: 010108 | E9: 1526 | F9: . | G9: . | H9: . | I9: 0 | J9: 0 | K9: 0 | L9: 0 | M9: 0 | N9: 0 | O9: 0 | P9: 0 | Q9: 0 | R9: 0 | S9: 0 | T9: 0 | U9: 0 | V9: 0 | W9: 0 | X9: 0 | Y9: 0 | Z9: 0 | AA9: 0 | AB9: 0 | AC9: 0 | AD9: 0 | AE9: 0 | AF9: 0 | AG9: 0 | AH9: 0 | AI9: 0 | AJ9: 0 | AK9: 0 | AL9: 0 | AM9: 0 | AN9: 0 | AO9: 0 | AP9: 0 | AQ9: 0 | AR9: 0 | AS9: 0 | AT9: 0 | AU9: 0 | AV9: 0 | AW9: 0 | AX9: 0 | AY9: 0 | AZ9: 0 | BA9: 0 | BB9: 0 | BC9: 0 | BD9: 0 | BE9: 0 | BF9: 3 | BG9: 0 | BH9: 0
A10: AMAZONAS | B10: CHACHAPOYAS | C10: LA JALCA | D10: 010109 | E10: 3418 | F10: 3 | G10: 0.904 | H10: 0.3013333 | I10: 0 | J10: 0 | K10: 0 | L10: 0 | M10: 0 | N10: 0 | O10: 0 | P10: 0 | Q10: 0 | R10: 0 | S10: 0 | T10: 0 | U10: 0 | V10: 0 | W10: 0 | X10: 0 | Y10: 0 | Z10: 0 | AA10: 0 | AB10: 0 | AC10: 0 | AD10: 0 | AE10: 0 | AF10: 0 | AG10: 0 | AH10: 0 | AI10: 0 | AJ10: 0 | AK10: 0 | AL10: 0 | AM10: 0 | AN10: 0 | AO10: 0 | AP10: 0 | AQ10: 0 | AR10: 0 | AS10: 0 | AT10: 0 | AU10: 0 | AV10: 0 | AW10: 0 | AX10: 0 | AY10: 0 | AZ10: 0 | BA10: 1 | BB10: 191781.83 | BC10: 191781.83 | BD10: 0 | BE10: 0 | BF10: 33 | BG10: 693.78485 | BH10: 0
A11: AMAZONAS | B11: CHACHAPOYAS | C11: LEIMEBAMBA | D11: 010110 | E11: 3738 | F11: 3 | G11: 1.596 | H11: 0.532 | I11: 0 | J11: 0 | K11: 0 | L11: 0 | M11: 0 | N11: 0 | O11: 0 | P11: 0 | Q11: 0 | R11: 0 | S11: 0 | T11: 0 | U11: 0 | V11: 0 | W11: 0 | X11: 0 | Y11: 0 | Z11: 0 | AA11: 0 | AB11: 0 | AC11: 0 | AD11: 0 | AE11: 0 | AF11: 0 | AG11: 0 | AH11: 0 | AI11: 0 | AJ11: 0 | AK11: 0 | AL11: 0 | AM11: 0 | AN11: 0 | AO11: 0 | AP11: 0 | AQ11: 0 | AR11: 0 | AS11: 0 | AT11: 0 | AU11: 0 | AV11: 0 | AW11: 0 | AX11: 0 | AY11: 0 | AZ11: 0 | BA11: 0 | BB11: 0 | BC11: 0 | BD11: 0 | BE11: 0 | BF11: 14 | BG11: 0 | BH11: 0
A12: AMAZONAS | B12: CHACHAPOYAS | C12: LEVANTO | D12: 010111 | E12: 774 | F12: . | G12: . | H12: . | I12: 0 | J12: 0 | K12: 0 | L12: 0 | M12: 0 | N12: 0 | O12: 0 | P12: 0 | Q12: 0 | R12: 0 | S12: 0 | T12: 0 | U12: 0 | V12: 0 | W12: 0 | X12: 0 | Y12: 0 | Z12: 0 | AA12: 0 | AB12: 0 | AC12: 0 | AD12: 0 | AE12: 0 | AF12: 0 | AG12: 0 | AH12: 0 | AI12: 0 | AJ12: 0 | AK12: 0 | AL12: 0 | AM12: 0 | AN12: 0 | AO12: 0 | AP12: 0 | AQ12: 0 | AR12: 0 | AS12: 0 | AT12: 0 | AU12: 0 | AV12: 0 | AW12: 0 | AX12: 0 | AY12: 0 | AZ12: 0 | BA12: 0 | BB12: 0 | BC12: 0 | BD12: 0 | BE12: 0 | BF12: 2 | BG12: 0 | BH12: 0
A13: AMAZONAS | B13: CHACHAPOYAS | C13: MAGDALENA | D13: 010112 | E13: 900 | F13: . | G13: . | H13: . | I13: 0 | J13: 0 | K13: 0 | L13: 0 | M13: 0 | N13: 0 | O13: 0 | P13: 0 | Q13: 0 | R13: 0 | S13: 0 | T13: 0 | U13: 0 | V13: 0 | W13: 0 | X13: 0 | Y13: 0 | Z13: 0 | AA13: 0 | AB13: 0 | AC13: 0 | AD13: 0 | AE13: 0 | AF13: 0 | AG13: 0 | AH13: 0 | AI13: 0 | AJ13: 0 | AK13: 0 | AL13: 0 | AM13: 0 | AN13: 0 | AO13: 0 | AP13: 0 | AQ13: 0 | AR13: 0 | AS13: 0 | AT13: 0 | AU13: 0 | AV13: 0 | AW13: 0 | AX13: 0 | AY13: 0 | AZ13: 0 | BA13: 0 | BB13: 0 | BC13: 0 | BD13: 0 | BE13: 0 | BF13: 4 | BG13: 0 | BH13: 0
A14: AMAZONAS | B14: CHACHAPOYAS | C14: MARISCAL CASTILLA | D14: 010113 | E14: 1631 | F14: 4 | G14: 2.956087 | H14: 0.7390218 | I14: 0 | J14: 0 | K14: 0 | L14: 0 | M14: 0 | N14: 0 | O14: 0 | P14: 0 | Q14: 0 | R14: 0 | S14: 0 | T14: 0 | U14: 0 | V14: 0 | W14: 0 | X14: 0 | Y14: 0 | Z14: 0 | AA14: 0 | AB14: 0 | AC14: 0 | AD14: 0 | AE14: 0 | AF14: 0 | AG14: 0 | AH14: 0 | AI14: 0 | AJ14: 0 | AK14: 0 | AL14: 0 | AM14: 0 | AN14: 0 | AO14: 0 | AP14: 0 | AQ14: 0 | AR14: 0 | AS14: 0 | AT14: 0 | AU14: 0 | AV14: 0 | AW14: 0 | AX14: 0 | AY14: 0 | AZ14: 0 | BA14: 0 | BB14: 0 | BC14: 0 | BD14: 0 | BE14: 0 | BF14: 1 | BG14: 0 | BH14: 0
A15: AMAZONAS | B15: CHACHAPOYAS | C15: MOLINOPAMPA | D15: 010114 | E15: 2201 | F15: 3 | G15: 0.70128 | H15: 0.23376 | I15: 0 | J15: 0 | K15: 0 | L15: 0 | M15: 0 | N15: 0 | O15: 0 | P15: 0 | Q15: 0 | R15: 0 | S15: 0 | T15: 0 | U15: 0 | V15: 0 | W15: 0 | X15: 0 | Y15: 0 | Z15: 0 | AA15: 0 | AB15: 0 | AC15: 0 | AD15: 0 | AE15: 0 | AF15: 0 | AG15: 0 | AH15: 0 | AI15: 0 | AJ15: 0 | AK15: 0 | AL15: 0 | AM15: 0 | AN15: 0 | AO15: 0 | AP15: 0 | AQ15: 0 | AR15: 0 | AS15: 0 | AT15: 0 | AU15: 0 | AV15: 0 | AW15: 0 | AX15: 0 | AY15: 0 | AZ15: 0 | BA15: 0 | BB15: 0 | BC15: 0 | BD15: 0 | BE15: 0 | BF15: 10 | BG15: 0 | BH15: 0
A16: AMAZONAS | B16: CHACHAPOYAS | C16: MONTEVIDEO | D16: 010115 | E16: 459 | F16: . | G16: . | H16: . | I16: 0 | J16: 0 | K16: 0 | L16: 0 | M16: 0 | N16: 0 | O16: 0 | P16: 0 | Q16: 0 | R16: 0 | S16: 0 | T16: 0 | U16: 0 | V16: 0 | W16: 0 | X16: 0 | Y16: 0 | Z16: 0 | AA16: 0 | AB16: 0 | AC16: 0 | AD16: 0 | AE16: 0 | AF16: 0 | AG16: 0 | AH16: 0 | AI16: 0 | AJ16: 0 | AK16: 0 | AL16: 0 | AM16: 0 | AN16: 0 | AO16: 0 | AP16: 0 | AQ16: 0 | AR16: 0 | AS16: 0 | AT16: 0 | AU16: 0 | AV16: 0 | AW16: 0 | AX16: 0 | AY16: 0 | AZ16: 0 | BA16: 0 | BB16: 0 | BC16: 0 | BD16: 0 | BE16: 0 | BF16: 1 | BG16: 0 | BH16: 0
A17: AMAZONAS | B17: CHACHAPOYAS | C17: OLLEROS | D17: 010116 | E17: 446 | F17: 1 | G17: 0.324 | H17: 0.324 | I17: 0 | J17: 0 | K17: 0 | L17: 0 | M17: 0 | N17: 0 | O17: 0 | P17: 0 | Q17: 0 | R17: 0 | S17: 0 | T17: 0 | U17: 0 | V17: 0 | W17: 0 | X17: 0 | Y17: 0 | Z17: 0 | AA17: 0 | AB17: 0 | AC17: 0 | AD17: 0 | AE17: 0 | AF17: 0 | AG17: 0 | AH17: 0 | AI17: 0 | AJ17: 0 | AK17: 0 | AL17: 0 | AM17: 0 | AN17: 0 | AO17: 0 | AP17: 0 | AQ17: 0 | AR17: 0 | AS17: 0 | AT17: 0 | AU17: 0 | AV17: 0 | AW17: 0 | AX17: 0 | AY17: 0 | AZ17: 0 | BA17: 0 | BB17: 0 | BC17: 0 | BD17: 0 | BE17: 0 | BF17: 1 | BG17: 0 | BH17: 0
A18: AMAZONAS | B18: CHACHAPOYAS | C18: QUINJALCA | D18: 010117 | E18: 763 | F18: . | G18: . | H18: . | I18: 0 | J18: 0 | K18: 0 | L18: 0 | M18: 0 | N18: 0 | O18: 0 | P18: 0 | Q18: 0 | R18: 0 | S18: 0 | T18: 0 | U18: 0 | V18: 0 | W18: 0 | X18: 0 | Y18: 0 | Z18: 0 | AA18: 0 | AB18: 0 | AC18: 0 | AD18: 0 | AE18: 0 | AF18: 0 | AG18: 0 | AH18: 0 | AI18: 0 | AJ18: 0 | AK18: 0 | AL18: 0 | AM18: 0 | AN18: 0 | AO18: 0 | AP18: 0 | AQ18: 0 | AR18: 0 | AS18: 0 | AT18: 0 | AU18: 0 | AV18: 0 | AW18: 0 | AX18: 0 | AY18: 0 | AZ18: 0 | BA18: 0 | BB18: 0 | BC18: 0 | BD18: 0 | BE18: 0 | BF18: 1 | BG18: 0 | BH18: 0
A19: AMAZONAS | B19: CHACHAPOYAS | C19: SAN FRANCISCO DE DAGUAS | D19: 010118 | E19: 332 | F19: . | G19: . | H19: . | I19: 0 | J19: 0 | K19: 0 | L19: 0 | M19: 0 | N19: 0 | O19: 0 | P19: 0 | Q19: 0 | R19: 0 | S19: 0 | T19: 0 | U19: 0 | V19: 0 | W19: 0 | X19: 0 | Y19: 0 | Z19: 0 | AA19: 0 | AB19: 0 | AC19: 0 | AD19: 0 | AE19: 0 | AF19: 0 | AG19: 0 | AH19: 0 | AI19: 0 | AJ19: 0 | AK19: 0 | AL19: 0 | AM19: 0 | AN19: 0 | AO19: 0 | AP19: 0 | AQ19: 0 | AR19: 0 | AS19: 0 | AT19: 0 | AU19: 0 | AV19: 0 | AW19: 0 | AX19: 0 | AY19: 0 | AZ19: 0 | BA19: 0 | BB19: 0 | BC19: 0 | BD19: 0 | BE19: 0 | BF19: 1 | BG19: 0 | BH19: 0
A20: AMAZONAS | B20: CHACHAPOYAS | C20: SAN ISIDRO DE MAINO | D20: 010119 | E20: 570 | F20: . | G20: . | H20: . | I20: 0 | J20: 0 | K20: 0 | L20: 0 | M20: 0 | N20: 0 | O20: 0 | P20: 0 | Q20: 0 | R20: 0 | S20: 0 | T20: 0 | U20: 0 | V20: 0 | W20: 0 | X20: 0 | Y20: 0 | Z20: 0 | AA20: 0 | AB20: 0 | AC20: 0 | AD20: 0 | AE20: 0 | AF20: 0 | AG20: 0 | AH20: 0 | AI20: 0 | AJ20: 0 | AK20: 0 | AL20: 0 | AM20: 0 | AN20: 0 | AO20: 0 | AP20: 0 | AQ20: 0 | AR20: 0 | AS20: 0 | AT20: 0 | AU20: 0 | AV20: 0 | AW20: 0 | AX20: 0 | AY20: 0 | AZ20: 0 | BA20: 0 | BB20: 0 | BC20: 0 | BD20: 0 | BE20: 0 | BF20: 2 | BG20: 0 | BH20: 0
A21: AMAZONAS | B21: CHACHAPOYAS | C21: SOLOCO | D21: 010120 | E21: 1224 | F21: . | G21: . | H21: . | I21: 0 | J21: 0 | K21: 0 | L21: 0 | M21: 0 | N21: 0 | O21: 0 | P21: 0 | Q21: 0 | R21: 0 | S21: 0 | T21: 0 | U21: 0 | V21: 0 | W21: 0 | X21: 0 | Y21: 0 | Z21: 0 | AA21: 0 | AB21: 0 | AC21: 0 | AD21: 0 | AE21: 0 | AF21: 0 | AG21: 0 | AH21: 0 | AI21: 0 | AJ21: 0 | AK21: 0 | AL21: 0 | AM21: 0 | AN21: 0 | AO21: 0 | AP21: 0 | AQ21: 0 | AR21: 0 | AS21: 0 | AT21: 0 | AU21: 0 | AV21: 0 | AW21: 0 | AX21: 0 | AY21: 0 | AZ21: 0 | BA21: 0 | BB21: 0 | BC21: 0 | BD21: 0 | BE21: 0 | BF21: 1 | BG21: 0 | BH21: 0
A22: AMAZONAS | B22: CHACHAPOYAS | C22: SONCHE | D22: 010121 | E22: 286 | F22: . | G22: . | H22: . | I22: 0 | J22: 0 | K22: 0 | L22: 0 | M22: 0 | N22: 0 | O22: 0 | P22: 0 | Q22: 0 | R22: 0 | S22: 0 | T22: 0 | U22: 0 | V22: 0 | W22: 0 | X22: 0 | Y22: 0 | Z22: 0 | AA22: 0 | AB22: 0 | AC22: 0 | AD22: 0 | AE22: 0 | AF22: 0 | AG22: 0 | AH22: 0 | AI22: 0 | AJ22: 0 | AK22: 0 | AL22: 0 | AM22: 0 | AN22: 0 | AO22: 0 | AP22: 0 | AQ22: 0 | AR22: 0 | AS22: 0 | AT22: 0 | AU22: 0 | AV22: 0 | AW22: 0 | AX22: 0 | AY22: 0 | AZ22: 0 | BA22: . | BB22: . | BC22: . | BD22: . | BE22: . | BF22: . | BG22: . | BH22: .
A23: AMAZONAS | B23: BAGUA | C23: BAGUA | D23: 010201 | E23: 30790 | F23: 133 | G23: 125.9749 | H23: 0.94718 | I23: 0 | J23: 0 | K23: 0 | L23: 0 | M23: 0 | N23: 0 | O23: 0 | P23: 0 | Q23: 272.39 | R23: 0 | S23: 0 | T23: 272.39 | U23: 0 | V23: 0 | W23: 1362.79 | X23: 0 | Y23: 0 | Z23: 1362.79 | AA23: 38337.75 | AB23: 0 | AC23: 42795.73 | AD23: 0 | AE23: 1505.09 | AF23: 82638.57 | AG23: 6765.89 | AH23: 0 | AI23: 4024.05 | AJ23: 0 | AK23: 1538.99 | AL23: 12328.93 | AM23: 2883.06 | AN23: 0 | AO23: 12404.9 | AP23: 0 | AQ23: 417.21 | AR23: 15705.17 | AS23: 1998.77 | AT23: 0 | AU23: 6584.03 | AV23: 0 | AW23: 0 | AX23: 8582.8 | AY23: 120890.65 | AZ23: 0 | BA23: 10 | BB23: 49268.931 | BC23: 492689.3 | BD23: 0 | BE23: 2.99 | BF23: 308 | BG23: 1718.149 | BH23: 169.035
A24: AMAZONAS | B24: BAGUA | C24: ARAMANGO | D24: 010202 | E24: 9613 | F24: . | G24: . | H24: . | I24: 0 | J24: 0 | K24: 0 | L24: 0 | M24: 0 | N24: 0 | O24: 0 | P24: 0 | Q24: 0 | R24: 0 | S24: 0 | T24: 0 | U24: 0 | V24: 0 | W24: 0 | X24: 0 | Y24: 0 | Z24: 0 | AA24: 0 | AB24: 0 | AC24: 0 | AD24: 0 | AE24: 0 | AF24: 0 | AG24: 0 | AH24: 0 | AI24: 0 | AJ24: 0 | AK24: 0 | AL24: 0 | AM24: 0 | AN24: 0 | AO24: 0 | AP24: 0 | AQ24: 0 | AR24: 0 | AS24: 0 | AT24: 0 | AU24: 0 | AV24: 0 | AW24: 0 | AX24: 0 | AY24: 0 | AZ24: 0 | BA24: 0 | BB24: 0 | BC24: 0 | BD24: 0 | BE24: 0 | BF24: 28 | BG24: 0 | BH24: 0
A25: AMAZONAS | B25: BAGUA | C25: COPALLIN | D25: 010203 | E25: 4213 | F25: 2 | G25: 0.68 | H25: 0.34 | I25: 0 | J25: 0 | K25: 0 | L25: 0 | M25: 0 | N25: 0 | O25: 0 | P25: 0 | Q25: 0 | R25: 0 | S25: 0 | T25: 0 | U25: 0 | V25: 0 | W25: 0 | X25: 0 | Y25: 0 | Z25: 0 | AA25: 0 | AB25: 0 | AC25: 0 | AD25: 0 | AE25: 0 | AF25: 0 | AG25: 0 | AH25: 0 | AI25: 0 | AJ25: 0 | AK25: 0 | AL25: 0 | AM25: 0 | AN25: 0 | AO25: 0 | AP25: 0 | AQ25: 0 | AR25: 0 | AS25: 0 | AT25: 0 | AU25: 0 | AV25: 0 | AW25: 0 | AX25: 0 | AY25: 0 | AZ25: 0 | BA25: 0 | BB25: 0 | BC25: 0 | BD25: 0 | BE25: 0 | BF25: 8 | BG25: 378.625 | BH25: 0
A26: AMAZONAS | B26: BAGUA | C26: EL PARCO | D26: 010204 | E26: 1251 | F26: . | G26: . | H26: . | I26: 0 | J26: 0 | K26: 0 | L26: 0 | M26: 0 | N26: 0 | O26: 0 | P26: 0 | Q26: 0 | R26: 0 | S26: 0 | T26: 0 | U26: 0 | V26: 0 | W26: 0 | X26: 0 | Y26: 0 | Z26: 0 | AA26: 0 | AB26: 0 | AC26: 0 | AD26: 0 | AE26: 0 | AF26: 0 | AG26: 0 | AH26: 0 | AI26: 0 | AJ26: 0 | AK26: 0 | AL26: 0 | AM26: 0 | AN26: 0 | AO26: 0 | AP26: 0 | AQ26: 0 | AR26: 0 | AS26: 0 | AT26: 0 | AU26: 0 | AV26: 0 | AW26: 0 | AX26: 0 | AY26: 0 | AZ26: 0 | BA26: 0 | BB26: 0 | BC26: 0 | BD26: 0 | BE26: 0 | BF26: 2 | BG26: 0 | BH26: 0
A27: AMAZONAS | B27: BAGUA | C27: IMAZA | D27: 010205 | E27: 34240 | F27: 18 | G27: 10.41557 | H27: 0.578643 | I27: 0 | J27: 0 | K27: 0 | L27: 0 | M27: 0 | N27: 0 | O27: 0 | P27: 0 | Q27: 0 | R27: 0 | S27: 0 | T27: 0 | U27: 0 | V27: 0 | W27: 0 | X27: 0 | Y27: 0 | Z27: 0 | AA27: 0 | AB27: 0 | AC27: 0 | AD27: 0 | AE27: 0 | AF27: 0 | AG27: 0 | AH27: 0 | AI27: 0 | AJ27: 0 | AK27: 0 | AL27: 0 | AM27: 0 | AN27: 0 | AO27: 0 | AP27: 0 | AQ27: 0 | AR27: 0 | AS27: 0 | AT27: 0 | AU27: 0 | AV27: 0 | AW27: 0 | AX27: 0 | AY27: 0 | AZ27: 0 | BA27: 3 | BB27: 173559.76 | BC27: 520679.28 | BD27: 0 | BE27: 0 | BF27: 75 | BG27: 608.07467 | BH27: 0
A28: AMAZONAS | B28: BAGUA | C28: LA PECA | D28: 010206 | E28: 6226 | F28: 5 | G28: 2.024038 | H28: 0.4048076 | I28: 0 | J28: 0 | K28: 0 | L28: 0 | M28: 0 | N28: 0 | O28: 0 | P28: 0 | Q28: 0 | R28: 0 | S28: 0 | T28: 0 | U28: 0 | V28: 0 | W28: 0 | X28: 0 | Y28: 0 | Z28: 0 | AA28: 0 | AB28: 0 | AC28: 35421.71 | AD28: 0 | AE28: 0 | AF28: 35421.71 | AG28: 0 | AH28: 0 | AI28: 5652.14 | AJ28: 0 | AK28: 0 | AL28: 5652.14 | AM28: 0 | AN28: 0 | AO28: 12334.81 | AP28: 0 | AQ28: 0 | AR28: 12334.81 | AS28: 0 | AT28: 0 | AU28: 1271.95 | AV28: 0 | AW28: 0 | AX28: 1271.95 | AY28: 54680.61 | AZ28: 0 | BA28: 1 | BB28: 8894.167 | BC28: 8894.167 | BD28: 2873 | BE28: 0 | BF28: 44 | BG28: 10.072727 | BH28: 0
A29: AMAZONAS | B29: BONGARA | C29: JUMBILLA | D29: 010301 | E29: 1232 | F29: 2 | G29: 0.5465 | H29: 0.27325 | I29: 0 | J29: 0 | K29: 0 | L29: 0 | M29: 0 | N29: 0 | O29: 0 | P29: 0 | Q29: 0 | R29: 0 | S29: 0 | T29: 0 | U29: 0 | V29: 0 | W29: 0 | X29: 0 | Y29: 0 | Z29: 0 | AA29: 0 | AB29: 0 | AC29: 0 | AD29: 0 | AE29: 0 | AF29: 0 | AG29: 0 | AH29: 0 | AI29: 0 | AJ29: 0 | AK29: 0 | AL29: 0 | AM29: 0 | AN29: 0 | AO29: 0 | AP29: 0 | AQ29: 0 | AR29: 0 | AS29: 0 | AT29: 0 | AU29: 0 | AV29: 0 | AW29: 0 | AX29: 0 | AY29: 0 | AZ29: 0 | BA29: 0 | BB29: 0 | BC29: 0 | BD29: 0 | BE29: 0 | BF29: 8 | BG29: 0 | BH29: 0
A30: AMAZONAS | B30: BONGARA | C30: CHISQUILLA | D30: 010302 | E30: 308 | F30: . | G30: . | H30: . | I30: 0 | J30: 0 | K30: 0 | L30: 0 | M30: 0 | N30: 0 | O30: 0 | P30: 0 | Q30: 0 | R30: 0 | S30: 0 | T30: 0 | U30: 0 | V30: 0 | W30: 0 | X30: 0 | Y30: 0 | Z30: 0 | AA30: 0 | AB30: 0 | AC30: 0 | AD30: 0 | AE30: 0 | AF30: 0 | AG30: 0 | AH30: 0 | AI30: 0 | AJ30: 0 | AK30: 0 | AL30: 0 | AM30: 0 | AN30: 0 | AO30: 0 | AP30: 0 | AQ30: 0 | AR30: 0 | AS30: 0 | AT30: 0 | AU30: 0 | AV30: 0 | AW30: 0 | AX30: 0 | AY30: 0 | AZ30: 0 | BA30: . | BB30: . | BC30: . | BD30: . | BE30: . | BF30: . | BG30: . | BH30: .
A31: AMAZONAS | B31: BONGARA | C31: CHURUJA | D31: 010303 | E31: 292 | F31: . | G31: . | H31: . | I31: 0 | J31: 0 | K31: 0 | L31: 0 | M31: 0 | N31: 0 | O31: 0 | P31: 0 | Q31: 0 | R31: 0 | S31: 0 | T31: 0 | U31: 0 | V31: 0 | W31: 0 | X31: 0 | Y31: 0 | Z31: 0 | AA31: 0 | AB31: 0 | AC31: 0 | AD31: 0 | AE31: 0 | AF31: 0 | AG31: 0 | AH31: 0 | AI31: 0 | AJ31: 0 | AK31: 0 | AL31: 0 | AM31: 0 | AN31: 0 | AO31: 0 | AP31: 0 | AQ31: 0 | AR31: 0 | AS31: 0 | AT31: 0 | AU31: 0 | AV31: 0 | AW31: 0 | AX31: 0 | AY31: 0 | AZ31: 0 | BA31: 0 | BB31: 0 | BC31: 0 | BD31: 0 | BE31: 0 | BF31: 1 | BG31: 0 | BH31: 0
A32: AMAZONAS | B32: BONGARA | C32: COROSHA | D32: 010304 | E32: 849 | F32: . | G32: . | H32: . | I32: 0 | J32: 0 | K32: 0 | L32: 0 | M32: 0 | N32: 0 | O32: 0 | P32: 0 | Q32: 0 | R32: 0 | S32: 0 | T32: 0 | U32: 0 | V32: 0 | W32: 0 | X32: 0 | Y32: 0 | Z32: 0 | AA32: 0 | AB32: 0 | AC32: 0 | AD32: 0 | AE32: 0 | AF32: 0 | AG32: 0 | AH32: 0 | AI32: 0 | AJ32: 0 | AK32: 0 | AL32: 0 | AM32: 0 | AN32: 0 | AO32: 0 | AP32: 0 | AQ32: 0 | AR32: 0 | AS32: 0 | AT32: 0 | AU32: 0 | AV32: 0 | AW32: 0 | AX32: 0 | AY32: 0 | AZ32: 0 | BA32: . | BB32: . | BC32: . | BD32: . | BE32: . | BF32: . | BG32: . | BH32: .
A33: AMAZONAS | B33: BONGARA | C33: CUISPES | D33: 010305 | E33: 638 | F33: . | G33: . | H33: . | I33: 0 | J33: 0 | K33: 0 | L33: 0 | M33: 0 | N33: 0 | O33: 0 | P33: 0 | Q33: 0 | R33: 0 | S33: 0 | T33: 0 | U33: 0 | V33: 0 | W33: 0 | X33: 0 | Y33: 0 | Z33: 0 | AA33: 0 | AB33: 0 | AC33: 0 | AD33: 0 | AE33: 0 | AF33: 0 | AG33: 0 | AH33: 0 | AI33: 0 | AJ33: 0 | AK33: 0 | AL33: 0 | AM33: 0 | AN33: 0 | AO33: 0 | AP33: 0 | AQ33: 0 | AR33: 0 | AS33: 0 | AT33: 0 | AU33: 0 | AV33: 0 | AW33: 0 | AX33: 0 | AY33: 0 | AZ33: 0 | BA33: . | BB33: . | BC33: . | BD33: . | BE33: . | BF33: . | BG33: . | BH33: .
A34: AMAZONAS | B34: BONGARA | C34: FLORIDA | D34: 010306 | E34: 6283 | F34: 13 | G34: 8.247031 | H34: 0.634387 | I34: 0 | J34: 0 | K34: 0 | L34: 0 | M34: 0 | N34: 0 | O34: 0 | P34: 0 | Q34: 0 | R34: 0 | S34: 0 | T34: 0 | U34: 0 | V34: 0 | W34: 0 | X34: 0 | Y34: 0 | Z34: 0 | AA34: 0 | AB34: 0 | AC34: 4664.31 | AD34: 0 | AE34: 0 | AF34: 4664.31 | AG34: 0 | AH34: 0 | AI34: 755.13 | AJ34: 0 | AK34: 0 | AL34: 755.13 | AM34: 0 | AN34: 0 | AO34: 798.2 | AP34: 0 | AQ34: 0 | AR34: 798.2 | AS34: 0 | AT34: 0 | AU34: 778.74 | AV34: 0 | AW34: 0 | AX34: 778.74 | AY34: 6996.38 | AZ34: 0 | BA34: 0 | BB34: 0 | BC34: 0 | BD34: 0 | BE34: 0 | BF34: 41 | BG34: 1723.0634 | BH34: 920.1
A35: AMAZONAS | B35: BONGARA | C35: JAZAN | D35: 010307 | E35: 7588 | F35: 52 | G35: 32.85964 | H35: 0.631916 | I35: 0 | J35: 0 | K35: 0 | L35: 0 | M35: 0 | N35: 0 | O35: 0 | P35: 0 | Q35: 0 | R35: 0 | S35: 0 | T35: 0 | U35: 0 | V35: 0 | W35: 0 | X35: 0 | Y35: 0 | Z35: 0 | AA35: 15420.09 | AB35: 0 | AC35: 25007.7 | AD35: 0 | AE35: 0 | AF35: 40427.79 | AG35: 3181.38 | AH35: 0 | AI35: 3548.74 | AJ35: 0 | AK35: 0 | AL35: 6730.12 | AM35: 166.2 | AN35: 0 | AO35: 3236.57 | AP35: 0 | AQ35: 0 | AR35: 3402.77 | AS35: 1058.44 | AT35: 0 | AU35: 1164.89 | AV35: 0 | AW35: 0 | AX35: 2223.33 | AY35: 52784.01 | AZ35: 0 | BA35: 5 | BB35: 12832.9 | BC35: 64164.5 | BD35: 0 | BE35: 55.933 | BF35: 99 | BG35: 1213.9783 | BH35: 825.876
A36: AMAZONAS | B36: BONGARA | C36: RECTA | D36: 010308 | E36: 208 | F36: . | G36: . | H36: . | I36: 0 | J36: 0 | K36: 0 | L36: 0 | M36: 0 | N36: 0 | O36: 0 | P36: 0 | Q36: 0 | R36: 0 | S36: 0 | T36: 0 | U36: 0 | V36: 0 | W36: 0 | X36: 0 | Y36: 0 | Z36: 0 | AA36: 0 | AB36: 0 | AC36: 0 | AD36: 0 | AE36: 0 | AF36: 0 | AG36: 0 | AH36: 0 | AI36: 0 | AJ36: 0 | AK36: 0 | AL36: 0 | AM36: 0 | AN36: 0 | AO36: 0 | AP36: 0 | AQ36: 0 | AR36: 0 | AS36: 0 | AT36: 0 | AU36: 0 | AV36: 0 | AW36: 0 | AX36: 0 | AY36: 0 | AZ36: 0 | BA36: . | BB36: . | BC36: . | BD36: . | BE36: . | BF36: . | BG36: . | BH36: .
A37: AMAZONAS | B37: BONGARA | C37: SAN CARLOS | D37: 010309 | E37: 606 | F37: . | G37: . | H37: . | I37: 0 | J37: 0 | K37: 0 | L37: 0 | M37: 0 | N37: 0 | O37: 0 | P37: 0 | Q37: 0 | R37: 0 | S37: 0 | T37: 0 | U37: 0 | V37: 0 | W37: 0 | X37: 0 | Y37: 0 | Z37: 0 | AA37: 0 | AB37: 0 | AC37: 0 | AD37: 0 | AE37: 0 | AF37: 0 | AG37: 0 | AH37: 0 | AI37: 0 | AJ37: 0 | AK37: 0 | AL37: 0 | AM37: 0 | AN37: 0 | AO37: 0 | AP37: 0 | AQ37: 0 | AR37: 0 | AS37: 0 | AT37: 0 | AU37: 0 | AV37: 0 | AW37: 0 | AX37: 0 | AY37: 0 | AZ37: 0 | BA37: . | BB37: . | BC37: . | BD37: . | BE37: . | BF37: . | BG37: . | BH37: .
A38: AMAZONAS | B38: BONGARA | C38: SHIPASBAMBA | D38: 010310 | E38: 1748 | F38: . | G38: . | H38: . | I38: 0 | J38: 0 | K38: 0 | L38: 0 | M38: 0 | N38: 0 | O38: 0 | P38: 0 | Q38: 0 | R38: 0 | S38: 0 | T38: 0 | U38: 0 | V38: 0 | W38: 0 | X38: 0 | Y38: 0 | Z38: 0 | AA38: 0 | AB38: 0 | AC38: 0 | AD38: 0 | AE38: 0 | AF38: 0 | AG38: 0 | AH38: 0 | AI38: 0 | AJ38: 0 | AK38: 0 | AL38: 0 | AM38: 0 | AN38: 0 | AO38: 0 | AP38: 0 | AQ38: 0 | AR38: 0 | AS38: 0 | AT38: 0 | AU38: 0 | AV38: 0 | AW38: 0 | AX38: 0 | AY38: 0 | AZ38: 0 | BA38: 0 | BB38: 0 | BC38: 0 | BD38: 0 | BE38: 0 | BF38: 6 | BG38: 27661.58 | BH38: 0
A39: AMAZONAS | B39: BONGARA | C39: VALERA | D39: 010311 | E39: 715 | F39: 1 | G39: 0.70735 | H39: 0.70735 | I39: 0 | J39: 0 | K39: 0 | L39: 0 | M39: 0 | N39: 0 | O39: 0 | P39: 0 | Q39: 0 | R39: 0 | S39: 0 | T39: 0 | U39: 0 | V39: 0 | W39: 0 | X39: 0 | Y39: 0 | Z39: 0 | AA39: 0 | AB39: 0 | AC39: 0 | AD39: 0 | AE39: 0 | AF39: 0 | AG39: 0 | AH39: 0 | AI39: 0 | AJ39: 0 | AK39: 0 | AL39: 0 | AM39: 0 | AN39: 0 | AO39: 0 | AP39: 0 | AQ39: 0 | AR39: 0 | AS39: 0 | AT39: 0 | AU39: 0 | AV39: 0 | AW39: 0 | AX39: 0 | AY39: 0 | AZ39: 0 | BA39: 0 | BB39: 0 | BC39: 0 | BD39: 0 | BE39: 0 | BF39: 6 | BG39: 0 | BH39: 0
A40: AMAZONAS | B40: BONGARA | C40: YAMBRASBAMBA | D40: 010312 | E40: 5513 | F40: . | G40: . | H40: . | I40: 0 | J40: 0 | K40: 0 | L40: 0 | M40: 0 | N40: 0 | O40: 0 | P40: 0 | Q40: 0 | R40: 0 | S40: 0 | T40: 0 | U40: 0 | V40: 0 | W40: 0 | X40: 0 | Y40: 0 | Z40: 0 | AA40: 0 | AB40: 0 | AC40: 0 | AD40: 0 | AE40: 0 | AF40: 0 | AG40: 0 | AH40: 0 | AI40: 0 | AJ40: 0 | AK40: 0 | AL40: 0 | AM40: 0 | AN40: 0 | AO40: 0 | AP40: 0 | AQ40: 0 | AR40: 0 | AS40: 0 | AT40: 0 | AU40: 0 | AV40: 0 | AW40: 0 | AX40: 0 | AY40: 0 | AZ40: 0 | BA40: 0 | BB40: 0 | BC40: 0 | BD40: 0 | BE40: 0 | BF40: 33 | BG40: 12.272727 | BH40: 0
A41: AMAZONAS | B41: CONDORCANQUI | C41: NIEVA | D41: 010401 | E41: 19600 | F41: 25 | G41: 12.75134 | H41: 0.5100535 | I41: 0 | J41: 0 | K41: 0 | L41: 0 | M41: 0 | N41: 0 | O41: 0 | P41: 0 | Q41: 0 | R41: 0 | S41: 0 | T41: 0 | U41: 0 | V41: 0 | W41: 133.26 | X41: 0 | Y41: 0 | Z41: 133.26 | AA41: 0 | AB41: 0 | AC41: 10312.67 | AD41: 0 | AE41: 0 | AF41: 10312.67 | AG41: 0 | AH41: 0 | AI41: 1542.36 | AJ41: 0 | AK41: 0 | AL41: 1542.36 | AM41: 0 | AN41: 0 | AO41: 653.21 | AP41: 0 | AQ41: 0 | AR41: 653.21 | AS41: 0 | AT41: 0 | AU41: 146.47 | AV41: 0 | AW41: 0 | AX41: 146.47 | AY41: 12787.97 | AZ41: 0 | BA41: 1 | BB41: 22523.667 | BC41: 22523.667 | BD41: 18549 | BE41: 0 | BF41: 80 | BG41: 4234.7005 | BH41: 0
A42: AMAZONAS | B42: CONDORCANQUI | C42: EL CENEPA | D42: 010402 | E42: 13578 | F42: 3 | G42: 0.873 | H42: 0.291 | I42: 0 | J42: 0 | K42: 0 | L42: 0 | M42: 0 | N42: 0 | O42: 0 | P42: 0 | Q42: 0 | R42: 0 | S42: 0 | T42: 0 | U42: 0 | V42: 0 | W42: 0 | X42: 0 | Y42: 0 | Z42: 0 | AA42: 0 | AB42: 0 | AC42: 0 | AD42: 0 | AE42: 0 | AF42: 0 | AG42: 0 | AH42: 0 | AI42: 0 | AJ42: 0 | AK42: 0 | AL42: 0 | AM42: 0 | AN42: 0 | AO42: 0 | AP42: 0 | AQ42: 0 | AR42: 0 | AS42: 0 | AT42: 0 | AU42: 0 | AV42: 0 | AW42: 0 | AX42: 0 | AY42: 0 | AZ42: 0 | BA42: 0 | BB42: 0 | BC42: 0 | BD42: 0 | BE42: 0 | BF42: 3 | BG42: 0 | BH42: 0
A43: AMAZONAS | B43: CONDORCANQUI | C43: RIO SANTIAGO | D43: 010403 | E43: 19233 | F43: 8 | G43: 3.008 | H43: 0.376 | I43: 0 | J43: 0 | K43: 0 | L43: 0 | M43: 0 | N43: 0 | O43: 0 | P43: 0 | Q43: 0 | R43: 0 | S43: 0 | T43: 0 | U43: 0 | V43: 0 | W43: 0 | X43: 0 | Y43: 0 | Z43: 0 | AA43: 0 | AB43: 0 | AC43: 0 | AD43: 0 | AE43: 0 | AF43: 0 | AG43: 0 | AH43: 0 | AI43: 0 | AJ43: 0 | AK43: 0 | AL43: 0 | AM43: 0 | AN43: 0 | AO43: 0 | AP43: 0 | AQ43: 0 | AR43: 0 | AS43: 0 | AT43: 0 | AU43: 0 | AV43: 0 | AW43: 0 | AX43: 0 | AY43: 0 | AZ43: 0 | BA43: 0 | BB43: 0 | BC43: 0 | BD43: 0 | BE43: 0 | BF43: 9 | BG43: 0 | BH43: 0
A44: AMAZONAS | B44: LUYA | C44: LAMUD | D44: 010501 | E44: 2305 | F44: 7 | G44: 1.6926 | H44: 0.2418 | I44: 0 | J44: 0 | K44: 0 | L44: 0 | M44: 0 | N44: 0 | O44: 0 | P44: 0 | Q44: 0 | R44: 0 | S44: 0 | T44: 0 | U44: 0 | V44: 0 | W44: 0 | X44: 0 | Y44: 0 | Z44: 0 | AA44: 0 | AB44: 0 | AC44: 0 | AD44: 0 | AE44: 0 | AF44: 0 | AG44: 0 | AH44: 0 | AI44: 0 | AJ44: 0 | AK44: 0 | AL44: 0 | AM44: 0 | AN44: 0 | AO44: 0 | AP44: 0 | AQ44: 0 | AR44: 0 | AS44: 0 | AT44: 0 | AU44: 0 | AV44: 0 | AW44: 0 | AX44: 0 | AY44: 0 | AZ44: 0 | BA44: 0 | BB44: 0 | BC44: 0 | BD44: 0 | BE44: 0 | BF44: 14 | BG44: 2880.4729 | BH44: 0
A45: AMAZONAS | B45: LUYA | C45: CAMPORREDONDO | D45: 010502 | E45: 7729 | F45: 5 | G45: 1.57 | H45: 0.314 | I45: 0 | J45: 0 | K45: 0 | L45: 0 | M45: 0 | N45: 0 | O45: 0 | P45: 0 | Q45: 0 | R45: 0 | S45: 0 | T45: 0 | U45: 0 | V45: 0 | W45: 0 | X45: 0 | Y45: 0 | Z45: 0 | AA45: 0 | AB45: 0 | AC45: 0 | AD45: 0 | AE45: 0 | AF45: 0 | AG45: 0 | AH45: 0 | AI45: 0 | AJ45: 0 | AK45: 0 | AL45: 0 | AM45: 0 | AN45: 0 | AO45: 0 | AP45: 0 | AQ45: 0 | AR45: 0 | AS45: 0 | AT45: 0 | AU45: 0 | AV45: 0 | AW45: 0 | AX45: 0 | AY45: 0 | AZ45: 0 | BA45: 0 | BB45: 0 | BC45: 0 | BD45: 0 | BE45: 0 | BF45: 6 | BG45: 0 | BH45: 0
A46: AMAZONAS | B46: LUYA | C46: COCABAMBA | D46: 010503 | E46: 1913 | F46: . | G46: . | H46: . | I46: 0 | J46: 0 | K46: 0 | L46: 0 | M46: 0 | N46: 0 | O46: 0 | P46: 0 | Q46: 0 | R46: 0 | S46: 0 | T46: 0 | U46: 0 | V46: 0 | W46: 0 | X46: 0 | Y46: 0 | Z46: 0 | AA46: 0 | AB46: 0 | AC46: 0 | AD46: 0 | AE46: 0 | AF46: 0 | AG46: 0 | AH46: 0 | AI46: 0 | AJ46: 0 | AK46: 0 | AL46: 0 | AM46: 0 | AN46: 0 | AO46: 0 | AP46: 0 | AQ46: 0 | AR46: 0 | AS46: 0 | AT46: 0 | AU46: 0 | AV46: 0 | AW46: 0 | AX46: 0 | AY46: 0 | AZ46: 0 | BA46: 0 | BB46: 0 | BC46: 0 | BD46: 0 | BE46: 0 | BF46: 1 | BG46: 0 | BH46: 0
A47: AMAZONAS | B47: LUYA | C47: COLCAMAR | D47: 010504 | E47: 1739 | F47: . | G47: . | H47: . | I47: 0 | J47: 0 | K47: 0 | L47: 0 | M47: 0 | N47: 0 | O47: 0 | P47: 0 | Q47: 0 | R47: 0 | S47: 0 | T47: 0 | U47: 0 | V47: 0 | W47: 0 | X47: 0 | Y47: 0 | Z47: 0 | AA47: 0 | AB47: 0 | AC47: 0 | AD47: 0 | AE47: 0 | AF47: 0 | AG47: 0 | AH47: 0 | AI47: 0 | AJ47: 0 | AK47: 0 | AL47: 0 | AM47: 0 | AN47: 0 | AO47: 0 | AP47: 0 | AQ47: 0 | AR47: 0 | AS47: 0 | AT47: 0 | AU47: 0 | AV47: 0 | AW47: 0 | AX47: 0 | AY47: 0 | AZ47: 0 | BA47: 0 | BB47: 0 | BC47: 0 | BD47: 0 | BE47: 0 | BF47: 4 | BG47: 0 | BH47: 0
A48: AMAZONAS | B48: LUYA | C48: CONILA | D48: 010505 | E48: 1819 | F48: . | G48: . | H48: . | I48: 0 | J48: 0 | K48: 0 | L48: 0 | M48: 0 | N48: 0 | O48: 0 | P48: 0 | Q48: 0 | R48: 0 | S48: 0 | T48: 0 | U48: 0 | V48: 0 | W48: 0 | X48: 0 | Y48: 0 | Z48: 0 | AA48: 0 | AB48: 0 | AC48: 0 | AD48: 0 | AE48: 0 | AF48: 0 | AG48: 0 | AH48: 0 | AI48: 0 | AJ48: 0 | AK48: 0 | AL48: 0 | AM48: 0 | AN48: 0 | AO48: 0 | AP48: 0 | AQ48: 0 | AR48: 0 | AS48: 0 | AT48: 0 | AU48: 0 | AV48: 0 | AW48: 0 | AX48: 0 | AY48: 0 | AZ48: 0 | BA48: 0 | BB48: 0 | BC48: 0 | BD48: 0 | BE48: 0 | BF48: 4 | BG48: 34.75 | BH48: 0
A49: AMAZONAS | B49: LUYA | C49: INGUILPATA | D49: 010506 | E49: 417 | F49: . | G49: . | H49: . | I49: 0 | J49: 0 | K49: 0 | L49: 0 | M49: 0 | N49: 0 | O49: 0 | P49: 0 | Q49: 0 | R49: 0 | S49: 0 | T49: 0 | U49: 0 | V49: 0 | W49: 0 | X49: 0 | Y49: 0 | Z49: 0 | AA49: 0 | AB49: 0 | AC49: 0 | AD49: 0 | AE49: 0 | AF49: 0 | AG49: 0 | AH49: 0 | AI49: 0 | AJ49: 0 | AK49: 0 | AL49: 0 | AM49: 0 | AN49: 0 | AO49: 0 | AP49: 0 | AQ49: 0 | AR49: 0 | AS49: 0 | AT49: 0 | AU49: 0 | AV49: 0 | AW49: 0 | AX49: 0 | AY49: 0 | AZ49: 0 | BA49: . | BB49: . | BC49: . | BD49: . | BE49: . | BF49: . | BG49: . | BH49: .
A50: AMAZONAS | B50: LUYA | C50: LONGUITA | D50: 010507 | E50: 833 | F50: 1 | G50: 0.43 | H50: 0.43 | I50: 0 | J50: 0 | K50: 0 | L50: 0 | M50: 0 | N50: 0 | O50: 0 | P50: 0 | Q50: 0 | R50: 0 | S50: 0 | T50: 0 | U50: 0 | V50: 0 | W50: 0 | X50: 0 | Y50: 0 | Z50: 0 | AA50: 0 | AB50: 0 | AC50: 0 | AD50: 0 | AE50: 0 | AF50: 0 | AG50: 0 | AH50: 0 | AI50: 0 | AJ50: 0 | AK50: 0 | AL50: 0 | AM50: 0 | AN50: 0 | AO50: 0 | AP50: 0 | AQ50: 0 | AR50: 0 | AS50: 0 | AT50: 0 | AU50: 0 | AV50: 0 | AW50: 0 | AX50: 0 | AY50: 0 | AZ50: 0 | BA50: 0 | BB50: 0 | BC50: 0 | BD50: 0 | BE50: 0 | BF50: 3 | BG50: 0 | BH50: 0
A51: AMAZONAS | B51: LUYA | C51: LONYA CHICO | D51: 010508 | E51: 775 | F51: . | G51: . | H51: . | I51: 0 | J51: 0 | K51: 0 | L51: 0 | M51: 0 | N51: 0 | O51: 0 | P51: 0 | Q51: 0 | R51: 0 | S51: 0 | T51: 0 | U51: 0 | V51: 0 | W51: 0 | X51: 0 | Y51: 0 | Z51: 0 | AA51: 0 | AB51: 0 | AC51: 0 | AD51: 0 | AE51: 0 | AF51: 0 | AG51: 0 | AH51: 0 | AI51: 0 | AJ51: 0 | AK51: 0 | AL51: 0 | AM51: 0 | AN51: 0 | AO51: 0 | AP51: 0 | AQ51: 0 | AR51: 0 | AS51: 0 | AT51: 0 | AU51: 0 | AV51: 0 | AW51: 0 | AX51: 0 | AY51: 0 | AZ51: 0 | BA51: . | BB51: . | BC51: . | BD51: . | BE51: . | BF51: . | BG51: . | BH51: .
A52: AMAZONAS | B52: LUYA | C52: LUYA | D52: 010509 | E52: 3957 | F52: 11 | G52: 5.578585 | H52: 0.5071441 | I52: 0 | J52: 0 | K52: 0 | L52: 0 | M52: 0 | N52: 0 | O52: 0 | P52: 0 | Q52: 0 | R52: 0 | S52: 0 | T52: 0 | U52: 0 | V52: 0 | W52: 0 | X52: 0 | Y52: 0 | Z52: 0 | AA52: 0 | AB52: 0 | AC52: 0 | AD52: 0 | AE52: 0 | AF52: 0 | AG52: 0 | AH52: 0 | AI52: 0 | AJ52: 0 | AK52: 0 | AL52: 0 | AM52: 0 | AN52: 0 | AO52: 0 | AP52: 0 | AQ52: 0 | AR52: 0 | AS52: 0 | AT52: 0 | AU52: 0 | AV52: 0 | AW52: 0 | AX52: 0 | AY52: 0 | AZ52: 0 | BA52: 0 | BB52: 0 | BC52: 0 | BD52: 0 | BE52: 0 | BF52: 42 | BG52: 1101.906 | BH52: 0
A53: AMAZONAS | B53: LUYA | C53: LUYA VIEJO | D53: 010510 | E53: 388 | F53: . | G53: . | H53: . | I53: 0 | J53: 0 | K53: 0 | L53: 0 | M53: 0 | N53: 0 | O53: 0 | P53: 0 | Q53: 0 | R53: 0 | S53: 0 | T53: 0 | U53: 0 | V53: 0 | W53: 0 | X53: 0 | Y53: 0 | Z53: 0 | AA53: 0 | AB53: 0 | AC53: 0 | AD53: 0 | AE53: 0 | AF53: 0 | AG53: 0 | AH53: 0 | AI53: 0 | AJ53: 0 | AK53: 0 | AL53: 0 | AM53: 0 | AN53: 0 | AO53: 0 | AP53: 0 | AQ53: 0 | AR53: 0 | AS53: 0 | AT53: 0 | AU53: 0 | AV53: 0 | AW53: 0 | AX53: 0 | AY53: 0 | AZ53: 0 | BA53: . | BB53: . | BC53: . | BD53: . | BE53: . | BF53: . | BG53: . | BH53: .
A54: AMAZONAS | B54: LUYA | C54: MARIA | D54: 010511 | E54: 724 | F54: . | G54: . | H54: . | I54: 0 | J54: 0 | K54: 0 | L54: 0 | M54: 0 | N54: 0 | O54: 0 | P54: 0 | Q54: 0 | R54: 0 | S54: 0 | T54: 0 | U54: 0 | V54: 0 | W54: 0 | X54: 0 | Y54: 0 | Z54: 0 | AA54: 0 | AB54: 0 | AC54: 0 | AD54: 0 | AE54: 0 | AF54: 0 | AG54: 0 | AH54: 0 | AI54: 0 | AJ54: 0 | AK54: 0 | AL54: 0 | AM54: 0 | AN54: 0 | AO54: 0 | AP54: 0 | AQ54: 0 | AR54: 0 | AS54: 0 | AT54: 0 | AU54: 0 | AV54: 0 | AW54: 0 | AX54: 0 | AY54: 0 | AZ54: 0 | BA54: 0 | BB54: 0 | BC54: 0 | BD54: 0 | BE54: 0 | BF54: 3 | BG54: 0 | BH54: 0
A55: AMAZONAS | B55: LUYA | C55: OCALLI | D55: 010512 | E55: 3966 | F55: 2 | G55: 0.718 | H55: 0.359 | I55: 0 | J55: 0 | K55: 0 | L55: 0 | M55: 0 | N55: 0 | O55: 0 | P55: 0 | Q55: 0 | R55: 0 | S55: 0 | T55: 0 | U55: 0 | V55: 0 | W55: 0 | X55: 0 | Y55: 0 | Z55: 0 | AA55: 0 | AB55: 0 | AC55: 0 | AD55: 0 | AE55: 0 | AF55: 0 | AG55: 0 | AH55: 0 | AI55: 0 | AJ55: 0 | AK55: 0 | AL55: 0 | AM55: 0 | AN55: 0 | AO55: 0 | AP55: 0 | AQ55: 0 | AR55: 0 | AS55: 0 | AT55: 0 | AU55: 0 | AV55: 0 | AW55: 0 | AX55: 0 | AY55: 0 | AZ55: 0 | BA55: 0 | BB55: 0 | BC55: 0 | BD55: 0 | BE55: 0 | BF55: 14 | BG55: 341.42857 | BH55: 0
A56: AMAZONAS | B56: LUYA | C56: OCUMAL | D56: 010513 | E56: 3554 | F56: . | G56: . | H56: . | I56: 0 | J56: 0 | K56: 0 | L56: 0 | M56: 0 | N56: 0 | O56: 0 | P56: 0 | Q56: 0 | R56: 0 | S56: 0 | T56: 0 | U56: 0 | V56: 0 | W56: 0 | X56: 0 | Y56: 0 | Z56: 0 | AA56: 0 | AB56: 0 | AC56: 0 | AD56: 0 | AE56: 0 | AF56: 0 | AG56: 0 | AH56: 0 | AI56: 0 | AJ56: 0 | AK56: 0 | AL56: 0 | AM56: 0 | AN56: 0 | AO56: 0 | AP56: 0 | AQ56: 0 | AR56: 0 | AS56: 0 | AT56: 0 | AU56: 0 | AV56: 0 | AW56: 0 | AX56: 0 | AY56: 0 | AZ56: 0 | BA56: 0 | BB56: 0 | BC56: 0 | BD56: 0 | BE56: 0 | BF56: 3 | BG56: 0 | BH56: 0
A57: AMAZONAS | B57: LUYA | C57: PISUQUIA | D57: 010514 | E57: 4784 | F57: . | G57: . | H57: . | I57: 0 | J57: 0 | K57: 0 | L57: 0 | M57: 0 | N57: 0 | O57: 0 | P57: 0 | Q57: 0 | R57: 0 | S57: 0 | T57: 0 | U57: 0 | V57: 0 | W57: 0 | X57: 0 | Y57: 0 | Z57: 0 | AA57: 0 | AB57: 0 | AC57: 0 | AD57: 0 | AE57: 0 | AF57: 0 | AG57: 0 | AH57: 0 | AI57: 0 | AJ57: 0 | AK57: 0 | AL57: 0 | AM57: 0 | AN57: 0 | AO57: 0 | AP57: 0 | AQ57: 0 | AR57: 0 | AS57: 0 | AT57: 0 | AU57: 0 | AV57: 0 | AW57: 0 | AX57: 0 | AY57: 0 | AZ57: 0 | BA57: 0 | BB57: 0 | BC57: 0 | BD57: 0 | BE57: 0 | BF57: 2 | BG57: 0 | BH57: 0
A58: AMAZONAS | B58: LUYA | C58: PROVIDENCIA | D58: 010515 | E58: 1320 | F58: . | G58: . | H58: . | I58: 0 | J58: 0 | K58: 0 | L58: 0 | M58: 0 | N58: 0 | O58: 0 | P58: 0 | Q58: 0 | R58: 0 | S58: 0 | T58: 0 | U58: 0 | V58: 0 | W58: 0 | X58: 0 | Y58: 0 | Z58: 0 | AA58: 0 | AB58: 0 | AC58: 0 | AD58: 0 | AE58: 0 | AF58: 0 | AG58: 0 | AH58: 0 | AI58: 0 | AJ58: 0 | AK58: 0 | AL58: 0 | AM58: 0 | AN58: 0 | AO58: 0 | AP58: 0 | AQ58: 0 | AR58: 0 | AS58: 0 | AT58: 0 | AU58: 0 | AV58: 0 | AW58: 0 | AX58: 0 | AY58: 0 | AZ58: 0 | BA58: . | BB58: . | BC58: . | BD58: . | BE58: . | BF58: . | BG58: . | BH58: .
A59: AMAZONAS | B59: LUYA | C59: SAN CRISTOBAL | D59: 010516 | E59: 490 | F59: . | G59: . | H59: . | I59: 0 | J59: 0 | K59: 0 | L59: 0 | M59: 0 | N59: 0 | O59: 0 | P59: 0 | Q59: 0 | R59: 0 | S59: 0 | T59: 0 | U59: 0 | V59: 0 | W59: 0 | X59: 0 | Y59: 0 | Z59: 0 | AA59: 0 | AB59: 0 | AC59: 0 | AD59: 0 | AE59: 0 | AF59: 0 | AG59: 0 | AH59: 0 | AI59: 0 | AJ59: 0 | AK59: 0 | AL59: 0 | AM59: 0 | AN59: 0 | AO59: 0 | AP59: 0 | AQ59: 0 | AR59: 0 | AS59: 0 | AT59: 0 | AU59: 0 | AV59: 0 | AW59: 0 | AX59: 0 | AY59: 0 | AZ59: 0 | BA59: . | BB59: . | BC59: . | BD59: . | BE59: . | BF59: . | BG59: . | BH59: .
A60: AMAZONAS | B60: LUYA | C60: SAN FRANCISCO DEL YESO | D60: 010517 | E60: 688 | F60: . | G60: . | H60: . | I60: 0 | J60: 0 | K60: 0 | L60: 0 | M60: 0 | N60: 0 | O60: 0 | P60: 0 | Q60: 0 | R60: 0 | S60: 0 | T60: 0 | U60: 0 | V60: 0 | W60: 0 | X60: 0 | Y60: 0 | Z60: 0 | AA60: 0 | AB60: 0 | AC60: 0 | AD60: 0 | AE60: 0 | AF60: 0 | AG60: 0 | AH60: 0 | AI60: 0 | AJ60: 0 | AK60: 0 | AL60: 0 | AM60: 0 | AN60: 0 | AO60: 0 | AP60: 0 | AQ60: 0 | AR60: 0 | AS60: 0 | AT60: 0 | AU60: 0 | AV60: 0 | AW60: 0 | AX60: 0 | AY60: 0 | AZ60: 0 | BA60: . | BB60: . | BC60: . | BD60: . | BE60: . | BF60: . | BG60: . | BH60: .
A61: AMAZONAS | B61: LUYA | C61: SAN JERONIMO | D61: 010518 | E61: 524 | F61: . | G61: . | H61: . | I61: 0 | J61: 0 | K61: 0 | L61: 0 | M61: 0 | N61: 0 | O61: 0 | P61: 0 | Q61: 0 | R61: 0 | S61: 0 | T61: 0 | U61: 0 | V61: 0 | W61: 0 | X61: 0 | Y61: 0 | Z61: 0 | AA61: 0 | AB61: 0 | AC61: 0 | AD61: 0 | AE61: 0 | AF61: 0 | AG61: 0 | AH61: 0 | AI61: 0 | AJ61: 0 | AK61: 0 | AL61: 0 | AM61: 0 | AN61: 0 | AO61: 0 | AP61: 0 | AQ61: 0 | AR61: 0 | AS61: 0 | AT61: 0 | AU61: 0 | AV61: 0 | AW61: 0 | AX61: 0 | AY61: 0 | AZ61: 0 | BA61: 0 | BB61: 0 | BC61: 0 | BD61: 0 | BE61: 0 | BF61: 1 | BG61: 0 | BH61: 0
A62: AMAZONAS | B62: LUYA | C62: SAN JUAN DE LOPECANCHA | D62: 010519 | E62: 388 | F62: . | G62: . | H62: . | I62: 0 | J62: 0 | K62: 0 | L62: 0 | M62: 0 | N62: 0 | O62: 0 | P62: 0 | Q62: 0 | R62: 0 | S62: 0 | T62: 0 | U62: 0 | V62: 0 | W62: 0 | X62: 0 | Y62: 0 | Z62: 0 | AA62: 0 | AB62: 0 | AC62: 0 | AD62: 0 | AE62: 0 | AF62: 0 | AG62: 0 | AH62: 0 | AI62: 0 | AJ62: 0 | AK62: 0 | AL62: 0 | AM62: 0 | AN62: 0 | AO62: 0 | AP62: 0 | AQ62: 0 | AR62: 0 | AS62: 0 | AT62: 0 | AU62: 0 | AV62: 0 | AW62: 0 | AX62: 0 | AY62: 0 | AZ62: 0 | BA62: . | BB62: . | BC62: . | BD62: . | BE62: . | BF62: . | BG62: . | BH62: .
A63: AMAZONAS | B63: LUYA | C63: SANTA CATALINA | D63: 010520 | E63: 2222 | F63: . | G63: . | H63: . | I63: 0 | J63: 0 | K63: 0 | L63: 0 | M63: 0 | N63: 0 | O63: 0 | P63: 0 | Q63: 0 | R63: 0 | S63: 0 | T63: 0 | U63: 0 | V63: 0 | W63: 0 | X63: 0 | Y63: 0 | Z63: 0 | AA63: 0 | AB63: 0 | AC63: 0 | AD63: 0 | AE63: 0 | AF63: 0 | AG63: 0 | AH63: 0 | AI63: 0 | AJ63: 0 | AK63: 0 | AL63: 0 | AM63: 0 | AN63: 0 | AO63: 0 | AP63: 0 | AQ63: 0 | AR63: 0 | AS63: 0 | AT63: 0 | AU63: 0 | AV63: 0 | AW63: 0 | AX63: 0 | AY63: 0 | AZ63: 0 | BA63: 0 | BB63: 0 | BC63: 0 | BD63: 0 | BE63: 0 | BF63: 4 | BG63: 0 | BH63: 0
A64: AMAZONAS | B64: LUYA | C64: SANTO TOMAS | D64: 010521 | E64: 2793 | F64: . | G64: . | H64: . | I64: 0 | J64: 0 | K64: 0 | L64: 0 | M64: 0 | N64: 0 | O64: 0 | P64: 0 | Q64: 0 | R64: 0 | S64: 0 | T64: 0 | U64: 0 | V64: 0 | W64: 0 | X64: 0 | Y64: 0 | Z64: 0 | AA64: 0 | AB64: 0 | AC64: 0 | AD64: 0 | AE64: 0 | AF64: 0 | AG64: 0 | AH64: 0 | AI64: 0 | AJ64: 0 | AK64: 0 | AL64: 0 | AM64: 0 | AN64: 0 | AO64: 0 | AP64: 0 | AQ64: 0 | AR64: 0 | AS64: 0 | AT64: 0 | AU64: 0 | AV64: 0 | AW64: 0 | AX64: 0 | AY64: 0 | AZ64: 0 | BA64: 0 | BB64: 0 | BC64: 0 | BD64: 0 | BE64: 0 | BF64: 2 | BG64: 0 | BH64: 0
A65: AMAZONAS | B65: LUYA | C65: TINGO | D65: 010522 | E65: 1388 | F65: 2 | G65: 1.38 | H65: 0.6900001 | I65: 0 | J65: 0 | K65: 0 | L65: 0 | M65: 0 | N65: 0 | O65: 0 | P65: 0 | Q65: 0 | R65: 0 | S65: 0 | T65: 0 | U65: 0 | V65: 0 | W65: 0 | X65: 0 | Y65: 0 | Z65: 0 | AA65: 0 | AB65: 0 | AC65: 0 | AD65: 0 | AE65: 0 | AF65: 0 | AG65: 0 | AH65: 0 | AI65: 0 | AJ65: 0 | AK65: 0 | AL65: 0 | AM65: 0 | AN65: 0 | AO65: 0 | AP65: 0 | AQ65: 0 | AR65: 0 | AS65: 0 | AT65: 0 | AU65: 0 | AV65: 0 | AW65: 0 | AX65: 0 | AY65: 0 | AZ65: 0 | BA65: 0 | BB65: 0 | BC65: 0 | BD65: 0 | BE65: 0 | BF65: 15 | BG65: 0 | BH65: 2829.978
A66: AMAZONAS | B66: LUYA | C66: TRITA | D66: 010523 | E66: 1463 | F66: . | G66: . | H66: . | I66: 0 | J66: 0 | K66: 0 | L66: 0 | M66: 0 | N66: 0 | O66: 0 | P66: 0 | Q66: 0 | R66: 0 | S66: 0 | T66: 0 | U66: 0 | V66: 0 | W66: 0 | X66: 0 | Y66: 0 | Z66: 0 | AA66: 0 | AB66: 0 | AC66: 0 | AD66: 0 | AE66: 0 | AF66: 0 | AG66: 0 | AH66: 0 | AI66: 0 | AJ66: 0 | AK66: 0 | AL66: 0 | AM66: 0 | AN66: 0 | AO66: 0 | AP66: 0 | AQ66: 0 | AR66: 0 | AS66: 0 | AT66: 0 | AU66: 0 | AV66: 0 | AW66: 0 | AX66: 0 | AY66: 0 | AZ66: 0 | BA66: 0 | BB66: 0 | BC66: 0 | BD66: 0 | BE66: 0 | BF66: 2 | BG66: 0 | BH66: 0
A67: AMAZONAS | B67: RODRIGUEZ DE MENDOZA | C67: SAN NICOLAS | D67: 010601 | E67: 6660 | F67: 61 | G67: 59.55164 | H67: 0.9762564 | I67: 0 | J67: 0 | K67: 0 | L67: 0 | M67: 0 | N67: 0 | O67: 0 | P67: 0 | Q67: 0 | R67: 0 | S67: 0 | T67: 0 | U67: 0 | V67: 0 | W67: 283.04 | X67: 0 | Y67: 0 | Z67: 283.04 | AA67: 0 | AB67: 0 | AC67: 26163.7 | AD67: 9147.66 | AE67: 0 | AF67: 35311.36 | AG67: 0 | AH67: 0 | AI67: 5759.02 | AJ67: 1943.48 | AK67: 0 | AL67: 7702.5 | AM67: 0 | AN67: 0 | AO67: 6073.18 | AP67: 436.27 | AQ67: 0 | AR67: 6509.45 | AS67: 0 | AT67: 0 | AU67: 3880.94 | AV67: 0 | AW67: 0 | AX67: 3880.94 | AY67: 53687.29 | AZ67: 0 | BA67: 7 | BB67: 28500.357 | BC67: 199502.5 | BD67: 9618.4286 | BE67: 1673.254 | BF67: 146 | BG67: 420.88507 | BH67: 41.935
A68: AMAZONAS | B68: RODRIGUEZ DE MENDOZA | C68: CHIRIMOTO | D68: 010602 | E68: 2996 | F68: . | G68: . | H68: . | I68: 0 | J68: 0 | K68: 0 | L68: 0 | M68: 0 | N68: 0 | O68: 0 | P68: 0 | Q68: 0 | R68: 0 | S68: 0 | T68: 0 | U68: 0 | V68: 0 | W68: 0 | X68: 0 | Y68: 0 | Z68: 0 | AA68: 0 | AB68: 0 | AC68: 0 | AD68: 0 | AE68: 0 | AF68: 0 | AG68: 0 | AH68: 0 | AI68: 0 | AJ68: 0 | AK68: 0 | AL68: 0 | AM68: 0 | AN68: 0 | AO68: 0 | AP68: 0 | AQ68: 0 | AR68: 0 | AS68: 0 | AT68: 0 | AU68: 0 | AV68: 0 | AW68: 0 | AX68: 0 | AY68: 0 | AZ68: 0 | BA68: 1 | BB68: 30264 | BC68: 30264 | BD68: 0 | BE68: 5767.779 | BF68: 4 | BG68: 0 | BH68: 1489.525
A69: AMAZONAS | B69: RODRIGUEZ DE MENDOZA | C69: COCHAMAL | D69: 010603 | E69: 645 | F69: 1 | G69: 0.72 | H69: 0.72 | I69: 0 | J69: 0 | K69: 0 | L69: 0 | M69: 0 | N69: 0 | O69: 0 | P69: 0 | Q69: 0 | R69: 0 | S69: 0 | T69: 0 | U69: 0 | V69: 0 | W69: 0 | X69: 0 | Y69: 0 | Z69: 0 | AA69: 0 | AB69: 0 | AC69: 0 | AD69: 0 | AE69: 0 | AF69: 0 | AG69: 0 | AH69: 0 | AI69: 0 | AJ69: 0 | AK69: 0 | AL69: 0 | AM69: 0 | AN69: 0 | AO69: 0 | AP69: 0 | AQ69: 0 | AR69: 0 | AS69: 0 | AT69: 0 | AU69: 0 | AV69: 0 | AW69: 0 | AX69: 0 | AY69: 0 | AZ69: 0 | BA69: 0 | BB69: 0 | BC69: 0 | BD69: 0 | BE69: 0 | BF69: 3 | BG69: 0 | BH69: 0
A70: AMAZONAS | B70: RODRIGUEZ DE MENDOZA | C70: HUAMBO | D70: 010604 | E70: 2363 | F70: 5 | G70: 4.5105 | H70: 0.9021 | I70: 0 | J70: 0 | K70: 0 | L70: 0 | M70: 0 | N70: 0 | O70: 0 | P70: 0 | Q70: 0 | R70: 0 | S70: 0 | T70: 0 | U70: 0 | V70: 0 | W70: 0 | X70: 0 | Y70: 0 | Z70: 0 | AA70: 0 | AB70: 0 | AC70: 0 | AD70: 0 | AE70: 0 | AF70: 0 | AG70: 0 | AH70: 0 | AI70: 0 | AJ70: 0 | AK70: 0 | AL70: 0 | AM70: 0 | AN70: 0 | AO70: 0 | AP70: 0 | AQ70: 0 | AR70: 0 | AS70: 0 | AT70: 0 | AU70: 0 | AV70: 0 | AW70: 0 | AX70: 0 | AY70: 0 | AZ70: 0 | BA70: 1 | BB70: 4906.75 | BC70: 4906.75 | BD70: 0 | BE70: 2910.6 | BF70: 11 | BG70: 403.46454 | BH70: 0
A71: AMAZONAS | B71: RODRIGUEZ DE MENDOZA | C71: LIMABAMBA | D71: 010605 | E71: 2242 | F71: . | G71: . | H71: . | I71: 0 | J71: 0 | K71: 0 | L71: 0 | M71: 0 | N71: 0 | O71: 0 | P71: 0 | Q71: 0 | R71: 0 | S71: 0 | T71: 0 | U71: 0 | V71: 0 | W71: 0 | X71: 0 | Y71: 0 | Z71: 0 | AA71: 0 | AB71: 0 | AC71: 0 | AD71: 0 | AE71: 0 | AF71: 0 | AG71: 0 | AH71: 0 | AI71: 0 | AJ71: 0 | AK71: 0 | AL71: 0 | AM71: 0 | AN71: 0 | AO71: 0 | AP71: 0 | AQ71: 0 | AR71: 0 | AS71: 0 | AT71: 0 | AU71: 0 | AV71: 0 | AW71: 0 | AX71: 0 | AY71: 0 | AZ71: 0 | BA71: 0 | BB71: 0 | BC71: 0 | BD71: 0 | BE71: 0 | BF71: 4 | BG71: 0 | BH71: 0
A72: AMAZONAS | B72: RODRIGUEZ DE MENDOZA | C72: LONGAR | D72: 010606 | E72: 1567 | F72: . | G72: . | H72: . | I72: 0 | J72: 0 | K72: 0 | L72: 0 | M72: 0 | N72: 0 | O72: 0 | P72: 0 | Q72: 0 | R72: 0 | S72: 0 | T72: 0 | U72: 0 | V72: 0 | W72: 0 | X72: 0 | Y72: 0 | Z72: 0 | AA72: 0 | AB72: 0 | AC72: 0 | AD72: 0 | AE72: 0 | AF72: 0 | AG72: 0 | AH72: 0 | AI72: 0 | AJ72: 0 | AK72: 0 | AL72: 0 | AM72: 0 | AN72: 0 | AO72: 0 | AP72: 0 | AQ72: 0 | AR72: 0 | AS72: 0 | AT72: 0 | AU72: 0 | AV72: 0 | AW72: 0 | AX72: 0 | AY72: 0 | AZ72: 0 | BA72: 0 | BB72: 0 | BC72: 0 | BD72: 0 | BE72: 0 | BF72: 9 | BG72: 0 | BH72: 0
A73: AMAZONAS | B73: RODRIGUEZ DE MENDOZA | C73: MARISCAL BENAVIDES | D73: 010607 | E73: 1477 | F73: 3 | G73: 3.911118 | H73: 1.303706 | I73: 0 | J73: 0 | K73: 0 | L73: 0 | M73: 0 | N73: 0 | O73: 0 | P73: 0 | Q73: 0 | R73: 0 | S73: 0 | T73: 0 | U73: 0 | V73: 0 | W73: 0 | X73: 0 | Y73: 0 | Z73: 0 | AA73: 0 | AB73: 0 | AC73: 0 | AD73: 0 | AE73: 0 | AF73: 0 | AG73: 0 | AH73: 0 | AI73: 0 | AJ73: 0 | AK73: 0 | AL73: 0 | AM73: 0 | AN73: 0 | AO73: 0 | AP73: 0 | AQ73: 0 | AR73: 0 | AS73: 0 | AT73: 0 | AU73: 0 | AV73: 0 | AW73: 0 | AX73: 0 | AY73: 0 | AZ73: 0 | BA73: 0 | BB73: 0 | BC73: 0 | BD73: 0 | BE73: 0 | BF73: 8 | BG73: 0 | BH73: 0
A74: AMAZONAS | B74: RODRIGUEZ DE MENDOZA | C74: MILPUC | D74: 010608 | E74: 393 | F74: . | G74: . | H74: . | I74: 0 | J74: 0 | K74: 0 | L74: 0 | M74: 0 | N74: 0 | O74: 0 | P74: 0 | Q74: 0 | R74: 0 | S74: 0 | T74: 0 | U74: 0 | V74: 0 | W74: 0 | X74: 0 | Y74: 0 | Z74: 0 | AA74: 0 | AB74: 0 | AC74: 0 | AD74: 0 | AE74: 0 | AF74: 0 | AG74: 0 | AH74: 0 | AI74: 0 | AJ74: 0 | AK74: 0 | AL74: 0 | AM74: 0 | AN74: 0 | AO74: 0 | AP74: 0 | AQ74: 0 | AR74: 0 | AS74: 0 | AT74: 0 | AU74: 0 | AV74: 0 | AW74: 0 | AX74: 0 | AY74: 0 | AZ74: 0 | BA74: 0 | BB74: 0 | BC74: 0 | BD74: 0 | BE74: 0 | BF74: 1 | BG74: 0 | BH74: 0
A75: AMAZONAS | B75: RODRIGUEZ DE MENDOZA | C75: OMIA | D75: 010609 | E75: 10328 | F75: 1 | G75: 2.3 | H75: 2.3 | I75: 0 | J75: 0 | K75: 0 | L75: 0 | M75: 0 | N75: 0 | O75: 0 | P75: 0 | Q75: 0 | R75: 0 | S75: 0 | T75: 0 | U75: 0 | V75: 0 | W75: 0 | X75: 0 | Y75: 0 | Z75: 0 | AA75: 0 | AB75: 0 | AC75: 0 | AD75: 0 | AE75: 0 | AF75: 0 | AG75: 0 | AH75: 0 | AI75: 0 | AJ75: 0 | AK75: 0 | AL75: 0 | AM75: 0 | AN75: 0 | AO75: 0 | AP75: 0 | AQ75: 0 | AR75: 0 | AS75: 0 | AT75: 0 | AU75: 0 | AV75: 0 | AW75: 0 | AX75: 0 | AY75: 0 | AZ75: 0 | BA75: 0 | BB75: 0 | BC75: 0 | BD75: 0 | BE75: 0 | BF75: 26 | BG75: 0 | BH75: 0
A76: AMAZONAS | B76: RODRIGUEZ DE MENDOZA | C76: SANTA ROSA | D76: 010610 | E76: 524 | F76: 1 | G76: 0.216 | H76: 0.216 | I76: 0 | J76: 0 | K76: 0 | L76: 0 | M76: 0 | N76: 0 | O76: 0 | P76: 0 | Q76: 0 | R76: 0 | S76: 0 | T76: 0 | U76: 0 | V76: 0 | W76: 0 | X76: 0 | Y76: 0 | Z76: 0 | AA76: 0 | AB76: 0 | AC76: 0 | AD76: 0 | AE76: 0 | AF76: 0 | AG76: 0 | AH76: 0 | AI76: 0 | AJ76: 0 | AK76: 0 | AL76: 0 | AM76: 0 | AN76: 0 | AO76: 0 | AP76: 0 | AQ76: 0 | AR76: 0 | AS76: 0 | AT76: 0 | AU76: 0 | AV76: 0 | AW76: 0 | AX76: 0 | AY76: 0 | AZ76: 0 | BA76: 0 | BB76: 0 | BC76: 0 | BD76: 0 | BE76: 0 | BF76: 1 | BG76: 0 | BH76: 0
A77: AMAZONAS | B77: RODRIGUEZ DE MENDOZA | C77: TOTORA | D77: 010611 | E77: 284 | F77: . | G77: . | H77: . | I77: 0 | J77: 0 | K77: 0 | L77: 0 | M77: 0 | N77: 0 | O77: 0 | P77: 0 | Q77: 0 | R77: 0 | S77: 0 | T77: 0 | U77: 0 | V77: 0 | W77: 0 | X77: 0 | Y77: 0 | Z77: 0 | AA77: 0 | AB77: 0 | AC77: 0 | AD77: 0 | AE77: 0 | AF77: 0 | AG77: 0 | AH77: 0 | AI77: 0 | AJ77: 0 | AK77: 0 | AL77: 0 | AM77: 0 | AN77: 0 | AO77: 0 | AP77: 0 | AQ77: 0 | AR77: 0 | AS77: 0 | AT77: 0 | AU77: 0 | AV77: 0 | AW77: 0 | AX77: 0 | AY77: 0 | AZ77: 0 | BA77: . | BB77: . | BC77: . | BD77: . | BE77: . | BF77: . | BG77: . | BH77: .
A78: AMAZONAS | B78: RODRIGUEZ DE MENDOZA | C78: VISTA ALEGRE | D78: 010612 | E78: 4955 | F78: . | G78: . | H78: . | I78: 0 | J78: 0 | K78: 0 | L78: 0 | M78: 0 | N78: 0 | O78: 0 | P78: 0 | Q78: 0 | R78: 0 | S78: 0 | T78: 0 | U78: 0 | V78: 0 | W78: 0 | X78: 0 | Y78: 0 | Z78: 0 | AA78: 0 | AB78: 0 | AC78: 0 | AD78: 0 | AE78: 0 | AF78: 0 | AG78: 0 | AH78: 0 | AI78: 0 | AJ78: 0 | AK78: 0 | AL78: 0 | AM78: 0 | AN78: 0 | AO78: 0 | AP78: 0 | AQ78: 0 | AR78: 0 | AS78: 0 | AT78: 0 | AU78: 0 | AV78: 0 | AW78: 0 | AX78: 0 | AY78: 0 | AZ78: 0 | BA78: . | BB78: . | BC78: . | BD78: . | BE78: . | BF78: . | BG78: . | BH78: .
A79: AMAZONAS | B79: UTCUBAMBA | C79: BAGUA GRANDE | D79: 010701 | E79: 59952 | F79: 240 | G79: 263.6656 | H79: 1.098607 | I79: 0 | J79: 0 | K79: 0 | L79: 0 | M79: 0 | N79: 0 | O79: 0 | P79: 0 | Q79: 0 | R79: 0 | S79: 0 | T79: 0 | U79: 11604.2 | V79: 0 | W79: 279.88 | X79: 0 | Y79: 0 | Z79: 11884.08 | AA79: 138056.37 | AB79: 0 | AC79: 85082.48 | AD79: 0 | AE79: 0 | AF79: 223138.85 | AG79: 16739.59 | AH79: 0 | AI79: 14887.55 | AJ79: 0 | AK79: 0 | AL79: 31627.14 | AM79: 70342.01 | AN79: 0 | AO79: 19544.06 | AP79: 0 | AQ79: 0 | AR79: 89886.07 | AS79: 11531.84 | AT79: 0 | AU79: 12296.65 | AV79: 0 | AW79: 0 | AX79: 23828.49 | AY79: 380364.63 | AZ79: 0 | BA79: 26 | BB79: 40232.507 | BC79: 1046045.2 | BD79: 2234.7673 | BE79: 1331.336 | BF79: 498 | BG79: 1778.6603 | BH79: 969.235
A80: AMAZONAS | B80: UTCUBAMBA | C80: CAJARURO | D80: 010702 | E80: 23221 | F80: 14 | G80: 16.4172 | H80: 1.172657 | I80: 0 | J80: 0 | K80: 0 | L80: 0 | M80: 0 | N80: 0 | O80: 0 | P80: 0 | Q80: 0 | R80: 0 | S80: 0 | T80: 0 | U80: 0 | V80: 0 | W80: 0 | X80: 0 | Y80: 0 | Z80: 0 | AA80: 0 | AB80: 0 | AC80: 0 | AD80: 0 | AE80: 0 | AF80: 0 | AG80: 0 | AH80: 0 | AI80: 0 | AJ80: 0 | AK80: 0 | AL80: 0 | AM80: 0 | AN80: 0 | AO80: 0 | AP80: 0 | AQ80: 0 | AR80: 0 | AS80: 0 | AT80: 0 | AU80: 0 | AV80: 0 | AW80: 0 | AX80: 0 | AY80: 0 | AZ80: 0 | BA80: 0 | BB80: 0 | BC80: 0 | BD80: 0 | BE80: 0 | BF80: 23 | BG80: 0 | BH80: 0
A81: AMAZONAS | B81: UTCUBAMBA | C81: CUMBA | D81: 010703 | E81: 8449 | F81: 2 | G81: 0.540001 | H81: 0.2700005 | I81: 0 | J81: 0 | K81: 0 | L81: 0 | M81: 0 | N81: 0 | O81: 0 | P81: 0 | Q81: 0 | R81: 0 | S81: 0 | T81: 0 | U81: 0 | V81: 0 | W81: 0 | X81: 0 | Y81: 0 | Z81: 0 | AA81: 0 | AB81: 0 | AC81: 0 | AD81: 0 | AE81: 0 | AF81: 0 | AG81: 0 | AH81: 0 | AI81: 0 | AJ81: 0 | AK81: 0 | AL81: 0 | AM81: 0 | AN81: 0 | AO81: 0 | AP81: 0 | AQ81: 0 | AR81: 0 | AS81: 0 | AT81: 0 | AU81: 0 | AV81: 0 | AW81: 0 | AX81: 0 | AY81: 0 | AZ81: 0 | BA81: 0 | BB81: 0 | BC81: 0 | BD81: 0 | BE81: 0 | BF81: 11 | BG81: 0 | BH81: 0
A82: AMAZONAS | B82: UTCUBAMBA | C82: EL MILAGRO | D82: 010704 | E82: 6576 | F82: 1 | G82: 0.43 | H82: 0.43 | I82: 0 | J82: 0 | K82: 0 | L82: 0 | M82: 0 | N82: 0 | O82: 0 | P82: 0 | Q82: 0 | R82: 0 | S82: 0 | T82: 0 | U82: 0 | V82: 0 | W82: 0 | X82: 0 | Y82: 0 | Z82: 0 | AA82: 0 | AB82: 0 | AC82: 0 | AD82: 0 | AE82: 0 | AF82: 0 | AG82: 0 | AH82: 0 | AI82: 0 | AJ82: 0 | AK82: 0 | AL82: 0 | AM82: 0 | AN82: 0 | AO82: 0 | AP82: 0 | AQ82: 0 | AR82: 0 | AS82: 0 | AT82: 0 | AU82: 0 | AV82: 0 | AW82: 0 | AX82: 0 | AY82: 0 | AZ82: 0 | BA82: 1 | BB82: 259242.88 | BC82: 259242.88 | BD82: 0 | BE82: 0 | BF82: 6 | BG82: 0 | BH82: 0
A83: AMAZONAS | B83: UTCUBAMBA | C83: JAMALCA | D83: 010705 | E83: 6934 | F83: 1 | G83: 4.749246 | H83: 4.749246 | I83: 0 | J83: 0 | K83: 0 | L83: 0 | M83: 0 | N83: 0 | O83: 0 | P83: 0 | Q83: 0 | R83: 0 | S83: 0 | T83: 0 | U83: 0 | V83: 0 | W83: 0 | X83: 0 | Y83: 0 | Z83: 0 | AA83: 0 | AB83: 0 | AC83: 0 | AD83: 0 | AE83: 0 | AF83: 0 | AG83: 0 | AH83: 0 | AI83: 0 | AJ83: 0 | AK83: 0 | AL83: 0 | AM83: 0 | AN83: 0 | AO83: 0 | AP83: 0 | AQ83: 0 | AR83: 0 | AS83: 0 | AT83: 0 | AU83: 0 | AV83: 0 | AW83: 0 | AX83: 0 | AY83: 0 | AZ83: 0 | BA83: 1 | BB83: 32957.5 | BC83: 32957.5 | BD83: 0 | BE83: 0 | BF83: 7 | BG83: 112.93143 | BH83: 0
A84: AMAZONAS | B84: UTCUBAMBA | C84: LONYA GRANDE | D84: 010706 | E84: 11681 | F84: 16 | G84: 20.70432 | H84: 1.29402 | I84: 0 | J84: 0 | K84: 0 | L84: 0 | M84: 0 | N84: 0 | O84: 0 | P84: 0 | Q84: 0 | R84: 0 | S84: 0 | T84: 0 | U84: 0 | V84: 0 | W84: 0 | X84: 0 | Y84: 0 | Z84: 0 | AA84: 0 | AB84: 0 | AC84: 12935.92 | AD84: 0 | AE84: 0 | AF84: 12935.92 | AG84: 0 | AH84: 0 | AI84: 4565.84 | AJ84: 0 | AK84: 0 | AL84: 4565.84 | AM84: 0 | AN84: 0 | AO84: 2178.69 | AP84: 0 | AQ84: 0 | AR84: 2178.69 | AS84: 0 | AT84: 0 | AU84: 103.57 | AV84: 0 | AW84: 0 | AX84: 103.57 | AY84: 19784.02 | AZ84: 0 | BA84: 1 | BB84: 10688.167 | BC84: 10688.167 | BD84: 0 | BE84: 0 | BF84: 50 | BG84: 0 | BH84: 93.295
A85: AMAZONAS | B85: UTCUBAMBA | C85: YAMON | D85: 010707 | E85: 3255 | F85: 1 | G85: 1 | H85: 1 | I85: 0 | J85: 0 | K85: 0 | L85: 0 | M85: 0 | N85: 0 | O85: 0 | P85: 0 | Q85: 0 | R85: 0 | S85: 0 | T85: 0 | U85: 0 | V85: 0 | W85: 0 | X85: 0 | Y85: 0 | Z85: 0 | AA85: 0 | AB85: 0 | AC85: 0 | AD85: 0 | AE85: 0 | AF85: 0 | AG85: 0 | AH85: 0 | AI85: 0 | AJ85: 0 | AK85: 0 | AL85: 0 | AM85: 0 | AN85: 0 | AO85: 0 | AP85: 0 | AQ85: 0 | AR85: 0 | AS85: 0 | AT85: 0 | AU85: 0 | AV85: 0 | AW85: 0 | AX85: 0 | AY85: 0 | AZ85: 0 | BA85: 0 | BB85: 0 | BC85: 0 | BD85: 0 | BE85: 0 | BF85: 5 | BG85: 0 | BH85: 0
A86: ÁNCASH | B86: HUARAZ | C86: HUARAZ | D86: 020101 | E86: 70876 | F86: 417 | G86: 412.9984 | H86: 0.990404 | I86: 38.55 | J86: 0 | K86: 0 | L86: 0 | M86: 0 | N86: 38.55 | O86: 23389.63 | P86: 0 | Q86: 0 | R86: 0 | S86: 0 | T86: 23389.63 | U86: 119961.28 | V86: 0 | W86: 927.82 | X86: 0 | Y86: 0 | Z86: 120889.1 | AA86: 449922.55 | AB86: 13884.77 | AC86: 136894.43 | AD86: 0 | AE86: 0 | AF86: 600701.75 | AG86: 38167.01 | AH86: 2234.48 | AI86: 23768.1 | AJ86: 0 | AK86: 0 | AL86: 64169.59 | AM86: 550903.61 | AN86: 10325.5 | AO86: 29047.61 | AP86: 0 | AQ86: 0 | AR86: 590276.72 | AS86: 109123.28 | AT86: 0 | AU86: 2349.05 | AV86: 0 | AW86: 0 | AX86: 111472.33 | AY86: 1510937.7 | AZ86: 1 | BA86: 175 | BB86: 48737.66 | BC86: 8529090.5 | BD86: 7047.7467 | BE86: 1489.242 | BF86: 1180 | BG86: 4896.2173 | BH86: 1023.253
A87: ÁNCASH | B87: HUARAZ | C87: COCHABAMBA | D87: 020102 | E87: 1648 | F87: . | G87: . | H87: . | I87: 0 | J87: 0 | K87: 0 | L87: 0 | M87: 0 | N87: 0 | O87: 0 | P87: 0 | Q87: 0 | R87: 0 | S87: 0 | T87: 0 | U87: 0 | V87: 0 | W87: 0 | X87: 0 | Y87: 0 | Z87: 0 | AA87: 0 | AB87: 0 | AC87: 0 | AD87: 0 | AE87: 0 | AF87: 0 | AG87: 0 | AH87: 0 | AI87: 0 | AJ87: 0 | AK87: 0 | AL87: 0 | AM87: 0 | AN87: 0 | AO87: 0 | AP87: 0 | AQ87: 0 | AR87: 0 | AS87: 0 | AT87: 0 | AU87: 0 | AV87: 0 | AW87: 0 | AX87: 0 | AY87: 0 | AZ87: 0 | BA87: 0 | BB87: 0 | BC87: 0 | BD87: 0 | BE87: 0 | BF87: 1 | BG87: 0 | BH87: 0
A88: ÁNCASH | B88: HUARAZ | C88: COLCABAMBA | D88: 020103 | E88: 239 | F88: . | G88: . | H88: . | I88: 0 | J88: 0 | K88: 0 | L88: 0 | M88: 0 | N88: 0 | O88: 0 | P88: 0 | Q88: 0 | R88: 0 | S88: 0 | T88: 0 | U88: 0 | V88: 0 | W88: 0 | X88: 0 | Y88: 0 | Z88: 0 | AA88: 0 | AB88: 0 | AC88: 0 | AD88: 0 | AE88: 0 | AF88: 0 | AG88: 0 | AH88: 0 | AI88: 0 | AJ88: 0 | AK88: 0 | AL88: 0 | AM88: 0 | AN88: 0 | AO88: 0 | AP88: 0 | AQ88: 0 | AR88: 0 | AS88: 0 | AT88: 0 | AU88: 0 | AV88: 0 | AW88: 0 | AX88: 0 | AY88: 0 | AZ88: 0 | BA88: . | BB88: . | BC88: . | BD88: . | BE88: . | BF88: . | BG88: . | BH88: .
A89: ÁNCASH | B89: HUARAZ | C89: HUANCHAY | D89: 020104 | E89: 1580 | F89: . | G89: . | H89: . | I89: 0 | J89: 0 | K89: 0 | L89: 0 | M89: 0 | N89: 0 | O89: 0 | P89: 0 | Q89: 0 | R89: 0 | S89: 0 | T89: 0 | U89: 0 | V89: 0 | W89: 0 | X89: 0 | Y89: 0 | Z89: 0 | AA89: 0 | AB89: 0 | AC89: 0 | AD89: 0 | AE89: 0 | AF89: 0 | AG89: 0 | AH89: 0 | AI89: 0 | AJ89: 0 | AK89: 0 | AL89: 0 | AM89: 0 | AN89: 0 | AO89: 0 | AP89: 0 | AQ89: 0 | AR89: 0 | AS89: 0 | AT89: 0 | AU89: 0 | AV89: 0 | AW89: 0 | AX89: 0 | AY89: 0 | AZ89: 0 | BA89: . | BB89: . | BC89: . | BD89: . | BE89: . | BF89: . | BG89: . | BH89: .
A90: ÁNCASH | B90: HUARAZ | C90: INDEPENDENCIA | D90: 020105 | E90: 93922 | F90: 123 | G90: 140.7189 | H90: 1.144056 | I90: 0 | J90: 0 | K90: 0 | L90: 0 | M90: 0 | N90: 0 | O90: 0 | P90: 0 | Q90: 0 | R90: 0 | S90: 0 | T90: 0 | U90: 0 | V90: 0 | W90: 0 | X90: 0 | Y90: 0 | Z90: 0 | AA90: 0 | AB90: 210.67 | AC90: 0 | AD90: 0 | AE90: 0 | AF90: 210.67 | AG90: 0 | AH90: 745.7 | AI90: 0 | AJ90: 0 | AK90: 0 | AL90: 745.7 | AM90: 0 | AN90: 523.86 | AO90: 0 | AP90: 0 | AQ90: 0 | AR90: 523.86 | AS90: 0 | AT90: 0 | AU90: 0 | AV90: 0 | AW90: 0 | AX90: 0 | AY90: 1480.23 | AZ90: 1 | BA90: 99 | BB90: 47460.116 | BC90: 4698551.5 | BD90: 17861.748 | BE90: 2824.045 | BF90: 661 | BG90: 5614.5333 | BH90: 880.795
A91: ÁNCASH | B91: HUARAZ | C91: JANGAS | D91: 020106 | E91: 5344 | F91: 5 | G91: 8.427819 | H91: 1.685564 | I91: 0 | J91: 0 | K91: 0 | L91: 0 | M91: 0 | N91: 0 | O91: 0 | P91: 0 | Q91: 0 | R91: 0 | S91: 0 | T91: 0 | U91: 0 | V91: 0 | W91: 0 | X91: 0 | Y91: 0 | Z91: 0 | AA91: 0 | AB91: 0 | AC91: 0 | AD91: 0 | AE91: 0 | AF91: 0 | AG91: 0 | AH91: 0 | AI91: 0 | AJ91: 0 | AK91: 0 | AL91: 0 | AM91: 0 | AN91: 0 | AO91: 0 | AP91: 0 | AQ91: 0 | AR91: 0 | AS91: 0 | AT91: 0 | AU91: 0 | AV91: 0 | AW91: 0 | AX91: 0 | AY91: 0 | AZ91: 0 | BA91: 2 | BB91: 70243.583 | BC91: 140487.17 | BD91: 0 | BE91: 0 | BF91: 25 | BG91: 212.4 | BH91: 10.2
A92: ÁNCASH | B92: HUARAZ | C92: LA LIBERTAD | D92: 020107 | E92: 1084 | F92: . | G92: . | H92: . | I92: 0 | J92: 0 | K92: 0 | L92: 0 | M92: 0 | N92: 0 | O92: 0 | P92: 0 | Q92: 0 | R92: 0 | S92: 0 | T92: 0 | U92: 0 | V92: 0 | W92: 0 | X92: 0 | Y92: 0 | Z92: 0 | AA92: 0 | AB92: 0 | AC92: 0 | AD92: 0 | AE92: 0 | AF92: 0 | AG92: 0 | AH92: 0 | AI92: 0 | AJ92: 0 | AK92: 0 | AL92: 0 | AM92: 0 | AN92: 0 | AO92: 0 | AP92: 0 | AQ92: 0 | AR92: 0 | AS92: 0 | AT92: 0 | AU92: 0 | AV92: 0 | AW92: 0 | AX92: 0 | AY92: 0 | AZ92: 0 | BA92: 0 | BB92: 0 | BC92: 0 | BD92: 0 | BE92: 0 | BF92: 1 | BG92: 0 | BH92: 0
A93: ÁNCASH | B93: HUARAZ | C93: OLLEROS | D93: 020108 | E93: 2487 | F93: . | G93: . | H93: . | I93: 0 | J93: 0 | K93: 0 | L93: 0 | M93: 0 | N93: 0 | O93: 0 | P93: 0 | Q93: 0 | R93: 0 | S93: 0 | T93: 0 | U93: 0 | V93: 0 | W93: 0 | X93: 0 | Y93: 0 | Z93: 0 | AA93: 0 | AB93: 0 | AC93: 0 | AD93: 0 | AE93: 0 | AF93: 0 | AG93: 0 | AH93: 0 | AI93: 0 | AJ93: 0 | AK93: 0 | AL93: 0 | AM93: 0 | AN93: 0 | AO93: 0 | AP93: 0 | AQ93: 0 | AR93: 0 | AS93: 0 | AT93: 0 | AU93: 0 | AV93: 0 | AW93: 0 | AX93: 0 | AY93: 0 | AZ93: 0 | BA93: 0 | BB93: 0 | BC93: 0 | BD93: 0 | BE93: 0 | BF93: 2 | BG93: 0 | BH93: 0
A94: ÁNCASH | B94: HUARAZ | C94: PAMPAS GRANDE | D94: 020109 | E94: 956 | F94: . | G94: . | H94: . | I94: 0 | J94: 0 | K94: 0 | L94: 0 | M94: 0 | N94: 0 | O94: 0 | P94: 0 | Q94: 0 | R94: 0 | S94: 0 | T94: 0 | U94: 0 | V94: 0 | W94: 0 | X94: 0 | Y94: 0 | Z94: 0 | AA94: 0 | AB94: 0 | AC94: 0 | AD94: 0 | AE94: 0 | AF94: 0 | AG94: 0 | AH94: 0 | AI94: 0 | AJ94: 0 | AK94: 0 | AL94: 0 | AM94: 0 | AN94: 0 | AO94: 0 | AP94: 0 | AQ94: 0 | AR94: 0 | AS94: 0 | AT94: 0 | AU94: 0 | AV94: 0 | AW94: 0 | AX94: 0 | AY94: 0 | AZ94: 0 | BA94: . | BB94: . | BC94: . | BD94: . | BE94: . | BF94: . | BG94: . | BH94: .
A95: ÁNCASH | B95: HUARAZ | C95: PARIACOTO | D95: 020110 | E95: 5391 | F95: 1 | G95: 0.6 | H95: 0.6 | I95: 0 | J95: 0 | K95: 0 | L95: 0 | M95: 0 | N95: 0 | O95: 0 | P95: 0 | Q95: 0 | R95: 0 | S95: 0 | T95: 0 | U95: 0 | V95: 0 | W95: 0 | X95: 0 | Y95: 0 | Z95: 0 | AA95: 0 | AB95: 0 | AC95: 0 | AD95: 0 | AE95: 0 | AF95: 0 | AG95: 0 | AH95: 0 | AI95: 0 | AJ95: 0 | AK95: 0 | AL95: 0 | AM95: 0 | AN95: 0 | AO95: 0 | AP95: 0 | AQ95: 0 | AR95: 0 | AS95: 0 | AT95: 0 | AU95: 0 | AV95: 0 | AW95: 0 | AX95: 0 | AY95: 0 | AZ95: 0 | BA95: 0 | BB95: 0 | BC95: 0 | BD95: 0 | BE95: 0 | BF95: 9 | BG95: 2583.7222 | BH95: 0
A96: ÁNCASH | B96: HUARAZ | C96: PIRA | D96: 020111 | E96: 3428 | F96: 2 | G96: 2.406369 | H96: 1.203184 | I96: 0 | J96: 0 | K96: 0 | L96: 0 | M96: 0 | N96: 0 | O96: 0 | P96: 0 | Q96: 0 | R96: 0 | S96: 0 | T96: 0 | U96: 0 | V96: 0 | W96: 0 | X96: 0 | Y96: 0 | Z96: 0 | AA96: 0 | AB96: 0 | AC96: 0 | AD96: 0 | AE96: 0 | AF96: 0 | AG96: 0 | AH96: 0 | AI96: 0 | AJ96: 0 | AK96: 0 | AL96: 0 | AM96: 0 | AN96: 0 | AO96: 0 | AP96: 0 | AQ96: 0 | AR96: 0 | AS96: 0 | AT96: 0 | AU96: 0 | AV96: 0 | AW96: 0 | AX96: 0 | AY96: 0 | AZ96: 0 | BA96: 0 | BB96: 0 | BC96: 0 | BD96: 0 | BE96: 0 | BF96: 1 | BG96: 0 | BH96: 0
A97: ÁNCASH | B97: HUARAZ | C97: TARICA | D97: 020112 | E97: 8133 | F97: 1 | G97: 0.508488 | H97: 0.508488 | I97: 0 | J97: 0 | K97: 0 | L97: 0 | M97: 0 | N97: 0 | O97: 0 | P97: 0 | Q97: 0 | R97: 0 | S97: 0 | T97: 0 | U97: 0 | V97: 0 | W97: 0 | X97: 0 | Y97: 0 | Z97: 0 | AA97: 0 | AB97: 0 | AC97: 0 | AD97: 0 | AE97: 0 | AF97: 0 | AG97: 0 | AH97: 0 | AI97: 0 | AJ97: 0 | AK97: 0 | AL97: 0 | AM97: 0 | AN97: 0 | AO97: 0 | AP97: 0 | AQ97: 0 | AR97: 0 | AS97: 0 | AT97: 0 | AU97: 0 | AV97: 0 | AW97: 0 | AX97: 0 | AY97: 0 | AZ97: 0 | BA97: 1 | BB97: 15517.333 | BC97: 15517.333 | BD97: 8185.5 | BE97: 0 | BF97: 18 | BG97: 0 | BH97: 0
A98: ÁNCASH | B98: AIJA | C98: AIJA | D98: 020201 | E98: 2169 | F98: 1 | G98: 0.25 | H98: 0.25 | I98: 0 | J98: 0 | K98: 0 | L98: 0 | M98: 0 | N98: 0 | O98: 0 | P98: 0 | Q98: 0 | R98: 0 | S98: 0 | T98: 0 | U98: 0 | V98: 0 | W98: 0 | X98: 0 | Y98: 0 | Z98: 0 | AA98: 0 | AB98: 0 | AC98: 0 | AD98: 0 | AE98: 0 | AF98: 0 | AG98: 0 | AH98: 0 | AI98: 0 | AJ98: 0 | AK98: 0 | AL98: 0 | AM98: 0 | AN98: 0 | AO98: 0 | AP98: 0 | AQ98: 0 | AR98: 0 | AS98: 0 | AT98: 0 | AU98: 0 | AV98: 0 | AW98: 0 | AX98: 0 | AY98: 0 | AZ98: 0 | BA98: 1 | BB98: 3213 | BC98: 3213 | BD98: 0 | BE98: 238.483 | BF98: 9 | BG98: 17039.936 | BH98: 0
A99: ÁNCASH | B99: AIJA | C99: CORIS | D99: 020202 | E99: 1424 | F99: . | G99: . | H99: . | I99: 0 | J99: 0 | K99: 0 | L99: 0 | M99: 0 | N99: 0 | O99: 0 | P99: 0 | Q99: 0 | R99: 0 | S99: 0 | T99: 0 | U99: 0 | V99: 0 | W99: 0 | X99: 0 | Y99: 0 | Z99: 0 | AA99: 0 | AB99: 0 | AC99: 0 | AD99: 0 | AE99: 0 | AF99: 0 | AG99: 0 | AH99: 0 | AI99: 0 | AJ99: 0 | AK99: 0 | AL99: 0 | AM99: 0 | AN99: 0 | AO99: 0 | AP99: 0 | AQ99: 0 | AR99: 0 | AS99: 0 | AT99: 0 | AU99: 0 | AV99: 0 | AW99: 0 | AX99: 0 | AY99: 0 | AZ99: 0 | BA99: . | BB99: . | BC99: . | BD99: . | BE99: . | BF99: . | BG99: . | BH99: .
A100: ÁNCASH | B100: AIJA | C100: HUACLLAN | D100: 020203 | E100: 296 | F100: . | G100: . | H100: . | I100: 0 | J100: 0 | K100: 0 | L100: 0 | M100: 0 | N100: 0 | O100: 0 | P100: 0 | Q100: 0 | R100: 0 | S100: 0 | T100: 0 | U100: 0 | V100: 0 | W100: 0 | X100: 0 | Y100: 0 | Z100: 0 | AA100: 0 | AB100: 0 | AC100: 0 | AD100: 0 | AE100: 0 | AF100: 0 | AG100: 0 | AH100: 0 | AI100: 0 | AJ100: 0 | AK100: 0 | AL100: 0 | AM100: 0 | AN100: 0 | AO100: 0 | AP100: 0 | AQ100: 0 | AR100: 0 | AS100: 0 | AT100: 0 | AU100: 0 | AV100: 0 | AW100: 0 | AX100: 0 | AY100: 0 | AZ100: 0 | BA100: . | BB100: . | BC100: . | BD100: . | BE100: . | BF100: . | BG100: . | BH100: .
...

Sheet Fuentes y conceptos
B2: PILAR | C2: FUENTE | D2: INFORMACIÓN | E2: BASE DE DATOS | F2: VARIABLE | G2: CONCEPTO
B3: Tamaño de mercado PYME | C3: CENEC ajustado con CCNN | D3: Privada | E3: censo_cenec | F3: nro_emp_cenec_corr | G3: Número de empresas (pymes con ventas anuales entre 180 mil y 5 millones al 2024) del Censo Económico Anual Corregido
B4: Tamaño de mercado PYME | C4: CENEC ajustado con CCNN | D4: Privada | E4: censo_cenec | F4: ventas_tot_soles_cenec_corr | G4: Ventas totales de empresas (pymes con ventas anuales entre 180 mil y 5 millones al 2024) del Censo Económico Anual Corregido
B5: Tamaño de mercado PYME | C5: CENEC ajustado con CCNN | D5: Privada | E5: censo_cenec | F5: ventas_prom_soles_cenec_corr | G5: Ventas promedio de empresas (pymes con ventas anuales entre 180 mil y 5 millones al 2024) del Censo Económico Anual Corregido
B6: Tamaño de mercado PYME | C6: RT | D6: Privada | E6: t_bpe_univ_venta_rt_datamart_version5, t_bpe_sunat_vars | F6: nro_emp_rt | G6: Número de empresas (pymes con ventas mensuales entre 3 mil y 416 mil) que reportan Recaudación Tributaria
B7: Tamaño de mercado PYME | C7: RT | D7: Privada | E7: t_bpe_univ_venta_rt_datamart_version5, t_bpe_sunat_vars | F7: ventas_tot_rt | G7: Ventas totales de empresas (pymes con ventas mensuales entre 3 mil y 416 mil) que reportan Recaudación Tributaria en ios últimos 12 meses
B8: Tamaño de mercado PYME | C8: RT | D8: Privada | E8: t_bpe_univ_venta_rt_datamart_version5, t_bpe_sunat_vars | F8: ventas_prom_rt | G8: Ventas promedio de empresas (pymes con ventas mensuales entre 3 mil y 416 mil) que reportan Recaudación Tributaria en los últimos 12 meses
B9: Tamaño de mercado PYME | C9: RT | D9: Privada | E9: t_bpe_univ_venta_rt_datamart_version5, t_bpe_bn_universo_accionable, t_bpe_bn_clientes, t_bpe_sunat_vars | F9: nro_emp_rt_acc | G9: Número de empresas (pyme) con RT dentro del universo accionable
B10: Tamaño de mercado PYME | C10: RT | D10: Privada | E10: t_bpe_univ_venta_rt_datamart_version5, t_bpe_bn_universo_accionable, t_bpe_bn_clientes, t_bpe_sunat_vars | F10: ventas_tot_rt_acc | G10: Ventas totales de empresas (pyme) con RT dentro del universo accionable
B11: Tamaño de mercado PYME | C11: RT | D11: Privada | E11: t_bpe_univ_venta_rt_datamart_version5, t_bpe_bn_universo_accionable, t_bpe_bn_clientes, t_bpe_sunat_vars | F11: ventas_prom_rt_acc | G11: Ventas promedio de empresas (pyme) con RT dentro del universo accionable
B12: Penetración financiera PYME | C12: SBS | D12: Pública | E12: Carpeta de Información Financiera: https://www.sbs.gob.pe/app/stats_net/stats/EstadisticaBoletinEstadistico.aspx?p=14# | F12: peq_emp_tot_sbs | G12: Colocaciones de crédito de pequeñas empresas de la Superintendencia de Banca y Seguros
B13: Penetración financiera PYME | C13: SBS | D13: Pública | E13: Carpeta de Información Financiera: https://www.sbs.gob.pe/app/stats_net/stats/EstadisticaBoletinEstadistico.aspx?p=14# | F13: micro_emp_tot_sbs | G13: Colocaciones de crédito de microempresas de la Superintendencia de Banca y Seguros
... B25: Transaccionalidad Intercorp | C25: IBK | D25: Privada | E25: Se coordinó con Rodrigo Cornejo (IBK) | F25: tickets_unicos_transac_retail | G25: Tickets unicos del total de empresas del grupo Intercorp

Sheet Tablas
B2: TABLAS UTILIZADAS PARA EL INDICE | C2: RESPONSABLE TABLA | D2: RESPONSABLE LÓGICA
B3: censo_cenec | C3: Mauricio Aldana (AC), Adriana Bravo (AC) | D3: Mauricio Aldana (AC)
B4: t_bpe_univ_venta_rt_datamart_version5 | C4: Mauricio Aldana (AC), Adriana Bravo (AC) | D4: Edson Apari (IBK), Jose Barboza (IBK), Jenny Espinoza (IBK)
B5: t_bpe_sunat_vars | C5: Mauricio Aldana (AC), Adriana Bravo (AC) | D5: Edson Apari (IBK), Jenny Espinoza (IBK)
B6: t_bpe_bn_universo_accionable | C6: Mauricio Aldana (AC), Adriana Bravo (AC) | D6: Edson Apari (IBK), Jenny Espinoza (IBK)
B7: t_bpe_bn_clientes | C7: Mauricio Aldana (AC), Adriana Bravo (AC) | D7: Edson Apari (IBK), Jenny Espinoza (IBK)
B8: t_bpe_base_universo_sunat_variables | C8: Mauricio Aldana (AC), Adriana Bravo (AC) | D8: Edson Apari (IBK), Jose Barboza (IBK), Jenny Espinoza (IBK)
B9: t_bpe_brainstorn_vars_plin | C9: Mauricio Aldana (AC), Adriana Bravo (AC) | D9: Edson Apari (IBK), Jose Barboza (IBK), Jenny Espinoza (IBK)
B10: t_bpe_base_izipay_v2 | C10: Mauricio Aldana (AC), Adriana Bravo (AC) | D10: Edson Apari (IBK), Jose Barboza (IBK), Jenny Espinoza (IBK)

Sheet BaseIBK distritos filt
A1: departamento | B1: provincia | C1: distrito | D1: ubigeo | E1: nro_emp_cenec_corr | F1: ventas_tot_soles_cenec_corr | G1: ventas_prom_soles_cenec_corr | H1: nro_emp_rt | I1: ventas_tot_rt | J1: ventas_prom_rt | K1: nro_emp_rt_acc | L1: ventas_tot_rt_acc | M1: ventas_prom_rt_acc | N1: peq_emp_tot_sbs | O1: micro_emp_tot_sbs | P1: mto_desembolso_con_garantia_rcc | Q1: pct_rt_clf_normal_acc | R1: mto_deuda_rt_rcc | S1: mto_deuda_no_vigente_rt_rcc | T1: saldo_no_moroso_rt_rcc | U1: n_univ_tot_transac | V1: plin_univ_tot_transac | W1: izipay_univ_tot_transac | X1: n_univ_tot_transac_acc | Y1: plin_univ_tot_transac_acc | Z1: izipay_univ_tot_transac_acc | AA1: usuarios_unicos_transac_retail | AB1: mto_tot_transac_retail | AC1: tickets_unicos_transac_retail | AD1: nro_emp_cenec_corr_est | AE1: ventas_tot_mill_soles_cenec_corr_est | AF1: ventas_prom_mill_soles_cenec_corr_est | AG1: nro_emp_rt_est | AH1: ventas_tot_rt_est | AI1: ventas_prom_rt_est | AJ1: nro_emp_rt_acc_est | AK1: ventas_tot_rt_acc_est | AL1: ventas_prom_rt_acc_est | AM1: peq_emp_tot_sbs_est | AN1: micro_emp_tot_sbs_est | AO1: mto_desembolso_con_garantia_rcc_est | AP1: pct_rt_clf_normal_acc_est | AQ1: pct_rt_clf_normal_acc_est_imp | AR1: saldo_no_moroso_rt_rcc_est | AS1: saldo_no_moroso_rt_rcc_est_imp | AT1: n_univ_tot_transac_est | AU1: plin_univ_tot_transac_est | AV1: izipay_univ_tot_transac_est | AW1: n_univ_tot_transac_acc_est | AX1: plin_univ_tot_transac_acc_est | AY1: izipay_univ_tot_transac_acc_est | AZ1: usuarios_unicos_transac_retail_est | BA1: mto_tot_transac_retail_est | BB1: tickets_unicos_transac_retail_est | BC1: # Empresas (miles) | BD1: Venta prom. mensual predic (miles S/) | BE1: # Clusters | BF1: # EE en clusters (miles)
A2: ÁNCASH | B2: HUARAZ | C2: HUARAZ | D2: 020101 | E2: 1260 | F2: 863.40381 | G2: 0.68524112 | H2: 175 | I2: 8529090.5 | J2: 48737.66 | K2: 171 | L2: 8493779 | M2: 49671 | N2: 600701.75 | O2: 64169.59 | P2: 540976.33 | Q2: 0.88 | R2: 21062445 | S2: 349017.76 | T2: =IF((100-IFERROR(S2/R2*100,0))=100,50,(100-IFERROR(S2/R2*100,0))) -> 98.342938 | U2: 11028 | V2: 32727804 | W2: 5155097.8 | X2: 4184 | Y2: 19399919 | Z2: 3831949 | AA2: 333315 | AB2: 28214412 | AC2: 665818 | AD2: =(E2-MIN($E$2:$E$170))/(MAX($E$2:$E$170)-MIN($E$2:$E$170))*100 -> 8.6390858 | AE2: =(F2-MIN($F$2:$F$170))/(MAX($F$2:$F$170)-MIN($F$2:$F$170))*100 -> 7.6143093 | AF2: =(G2-MIN($G$2:$G$170))/(MAX($G$2:$G$170)-MIN($G$2:$G$170))*100 -> 29.289786 | AG2: =(H2-MIN($H$2:$H$170))/(MAX($H$2:$H$170)-MIN($H$2:$H$170))*100 -> 8.5532747 | AH2: =(I2-MIN($I$2:$I$170))/(MAX($I$2:$I$170)-MIN($I$2:$I$170))*100 -> 6.3857732 | AI2: =(J2-MIN($J$2:$J$170))/(MAX($J$2:$J$170)-MIN($J$2:$J$170))*100 -> 24.778348 | AJ2: =(K2-MIN($K$2:$K$170))/(MAX($K$2:$K$170)-MIN($K$2:$K$170))*100 -> 8.5843373 | AK2: =(L2-MIN($L$2:$L$170))/(MAX($L$2:$L$170)-MIN($L$2:$L$170))*100 -> 6.5586593 | AL2: =(M2-MIN($M$2:$M$170))/(MAX($M$2:$M$170)-MIN($M$2:$M$170))*100 -> 25.252803 | AM2: =(N2-MIN($N$2:$N$170))/(MAX($N$2:$N$170)-MIN($N$2:$N$170))*100 -> 6.4324178 | AN2: =(O2-MIN($O$2:$O$170))/(MAX($O$2:$O$170)-MIN($O$2:$O$170))*100 -> 23.771508 | AO2: =(P2-MIN($P$2:$P$170))/(MAX($P$2:$P$170)-MIN($P$2:$P$170))*100 -> 2.1982418 | AP2: =(Q2-MIN($Q$2:$Q$170))/(MAX($Q$2:$Q$170)-MIN($Q$2:$Q$170))*100 -> 88 | AQ2: =IF(AP2>=50,AP2,50) -> 88 | AR2: =(#REF!-MIN(#REF!))/(MAX(#REF!)-MIN(#REF!))*100 -> #REF! | AS2: =IF(AR2>=50,AR2,50) -> #REF! | AT2: =(U2-MIN($U$2:$U$170))/(MAX($U$2:$U$170)-MIN($U$2:$U$170))*100 -> 11.456319 | AU2: =(V2-MIN($V$2:$V$170))/(MAX($V$2:$V$170)-MIN($V$2:$V$170))*100 -> 5.940696 | AV2: =(W2-MIN($W$2:$W$170))/(MAX($W$2:$W$170)-MIN($W$2:$W$170))*100 -> 0.50334453 | AW2: =(X2-MIN($X$2:$X$170))/(MAX($X$2:$X$170)-MIN($X$2:$X$170))*100 -> 10.955189 | AX2: =(Y2-MIN($Y$2:$Y$170))/(MAX($Y$2:$Y$170)-MIN($Y$2:$Y$170))*100 -> 6.0125993 | AY2: =(Z2-MIN($Z$2:$Z$170))/(MAX($Z$2:$Z$170)-MIN($Z$2:$Z$170))*100 -> 5.0852911 | AZ2: =(AA2-MIN($AA$2:$AA$170))/(MAX($AA$2:$AA$170)-MIN($AA$2:$AA$170))*100 -> 13.770633 | BA2: =(AB2-MIN($AB$2:$AB$170))/(MAX($AB$2:$AB$170)-MIN($AB$2:$AB$170))*100 -> 5.1169704 | BB2: =(AC2-MIN($AC$2:$AC$170))/(MAX($AC$2:$AC$170)-MIN($AC$2:$AC$170))*100 -> 10.787851 | BC2: 3.6 | BD2: 177803 | BE2: 1 | BF2: 1.5
A3: ÁNCASH | B3: HUARAZ | C3: INDEPENDENCIA | D3: 020105 | E3: 386 | F3: 254.47099 | G3: 0.65925128 | H3: 99 | I3: 4698551.5 | J3: 47460.116 | K3: 93 | L3: 4631298 | M3: 49799 | N3: 210.67 | O3: 745.7 | P3: 899549 | Q3: 0.92 | R3: 12813273 | S3: 313857.6 | T3: =IF((100-IFERROR(S3/R3*100,0))=100,50,(100-IFERROR(S3/R3*100,0))) -> 97.550528 | U3: 7395 | V3: 20063518 | W3: 1718822.1 | X3: 2710 | Y3: 11090637 | Z3: 1677749 | AA3: 121061 | AB3: 4283092.3 | AC3: 166717 | AD3: =(E3-MIN($E$2:$E$170))/(MAX($E$2:$E$170)-MIN($E$2:$E$170))*100 -> 2.6227026 | AE3: =(F3-MIN($F$2:$F$170))/(MAX($F$2:$F$170)-MIN($F$2:$F$170))*100 -> 2.2287588 | AF3: =(G3-MIN($G$2:$G$170))/(MAX($G$2:$G$170)-MIN($G$2:$G$170))*100 -> 26.999616 | AG3: =(H3-MIN($H$2:$H$170))/(MAX($H$2:$H$170)-MIN($H$2:$H$170))*100 -> 4.8387097 | AH3: =(I3-MIN($I$2:$I$170))/(MAX($I$2:$I$170)-MIN($I$2:$I$170))*100 -> 3.5178293 | AI3: =(J3-MIN($J$2:$J$170))/(MAX($J$2:$J$170)-MIN($J$2:$J$170))*100 -> 24.128842 | AJ3: =(K3-MIN($K$2:$K$170))/(MAX($K$2:$K$170)-MIN($K$2:$K$170))*100 -> 4.6686747 | AK3: =(L3-MIN($L$2:$L$170))/(MAX($L$2:$L$170)-MIN($L$2:$L$170))*100 -> 3.5761592 | AL3: =(M3-MIN($M$2:$M$170))/(MAX($M$2:$M$170)-MIN($M$2:$M$170))*100 -> 25.317878 | AM3: =(N3-MIN($N$2:$N$170))/(MAX($N$2:$N$170)-MIN($N$2:$N$170))*100 -> 0.0022558907 | AN3: =(O3-MIN($O$2:$O$170))/(MAX($O$2:$O$170)-MIN($O$2:$O$170))*100 -> 0.27624321 | AO3: =(P3-MIN($P$2:$P$170))/(MAX($P$2:$P$170)-MIN($P$2:$P$170))*100 -> 3.6552916 | AP3: =(Q3-MIN($Q$2:$Q$170))/(MAX($Q$2:$Q$170)-MIN($Q$2:$Q$170))*100 -> 92 | AQ3: =IF(AP3>=50,AP3,50) -> 92 | AR3: =(#REF!-MIN(#REF!))/(MAX(#REF!)-MIN(#REF!))*100 -> #REF! | AS3: =IF(AR3>=50,AR3,50) -> #REF! | AT3: =(U3-MIN($U$2:$U$170))/(MAX($U$2:$U$170)-MIN($U$2:$U$170))*100 -> 7.6584535 | AU3: =(V3-MIN($V$2:$V$170))/(MAX($V$2:$V$170)-MIN($V$2:$V$170))*100 -> 3.6337412 | AV3: =(W3-MIN($W$2:$W$170))/(MAX($W$2:$W$170)-MIN($W$2:$W$170))*100 -> 0.16781505 | AW3: =(X3-MIN($X$2:$X$170))/(MAX($X$2:$X$170)-MIN($X$2:$X$170))*100 -> 7.0744037 | AX3: =(Y3-MIN($Y$2:$Y$170))/(MAX($Y$2:$Y$170)-MIN($Y$2:$Y$170))*100 -> 3.4292184 | AY3: =(Z3-MIN($Z$2:$Z$170))/(MAX($Z$2:$Z$170)-MIN($Z$2:$Z$170))*100 -> 2.2263759 | AZ3: =(AA3-MIN($AA$2:$AA$170))/(MAX($AA$2:$AA$170)-MIN($AA$2:$AA$170))*100 -> 5.0000351 | BA3: =(AB3-MIN($AB$2:$AB$170))/(MAX($AB$2:$AB$170)-MIN($AB$2:$AB$170))*100 -> 0.77678231 | BB3: =(AC3-MIN($AC$2:$AC$170))/(MAX($AC$2:$AC$170)-MIN($AC$2:$AC$170))*100 -> 2.7004263 | BC3: 1.8 | BD3: 89333 | BE3: 1 | BF3: 0.1
A4: ÁNCASH | B4: SANTA | C4: CHIMBOTE | D4: 021801 | E4: 3654 | F4: 2466.8819 | G4: 0.67511821 | H4: 244 | I4: 9030336.2 | J4: 37009.575 | K4: 230 | L4: 8845937 | M4: 38461 | N4: 693819.75 | O4: 87302.61 | P4: 4130695.5 | Q4: 0.9 | R4: 39197774 | S4: 917640.58 | T4: =IF((100-IFERROR(S4/R4*100,0))=100,50,(100-IFERROR(S4/R4*100,0))) -> 97.658947 | U4: 20417 | V4: 1.1757502e+08 | W4: 6974034.3 | X4: 7125 | Y4: 64404735 | Z4: 5218361 | AA4: 914523 | AB4: 1.5742866e+08 | AC4: 2228745 | AD4: =(E4-MIN($E$2:$E$170))/(MAX($E$2:$E$170)-MIN($E$2:$E$170))*100 -> 25.118744 | AE4: =(F4-MIN($F$2:$F$170))/(MAX($F$2:$F$170)-MIN($F$2:$F$170))*100 -> 21.795861 | AF4: =(G4-MIN($G$2:$G$170))/(MAX($G$2:$G$170)-MIN($G$2:$G$170))*100 -> 28.397776 | AG4: =(H4-MIN($H$2:$H$170))/(MAX($H$2:$H$170)-MIN($H$2:$H$170))*100 -> 11.925709 | AH4: =(I4-MIN($I$2:$I$170))/(MAX($I$2:$I$170)-MIN($I$2:$I$170))*100 -> 6.7610584 | AI4: =(J4-MIN($J$2:$J$170))/(MAX($J$2:$J$170)-MIN($J$2:$J$170))*100 -> 18.815761 | AJ4: =(K4-MIN($K$2:$K$170))/(MAX($K$2:$K$170)-MIN($K$2:$K$170))*100 -> 11.546185 | AK4: =(L4-MIN($L$2:$L$170))/(MAX($L$2:$L$170)-MIN($L$2:$L$170))*100 -> 6.8305859 | AL4: =(M4-MIN($M$2:$M$170))/(MAX($M$2:$M$170)-MIN($M$2:$M$170))*100 -> 19.553624 | AM4: =(N4-MIN($N$2:$N$170))/(MAX($N$2:$N$170)-MIN($N$2:$N$170))*100 -> 7.4295414 | AN4: =(O4-MIN($O$2:$O$170))/(MAX($O$2:$O$170)-MIN($O$2:$O$170))*100 -> 32.341093 | AO4: =(P4-MIN($P$2:$P$170))/(MAX($P$2:$P$170)-MIN($P$2:$P$170))*100 -> 16.784963 | AP4: =(Q4-MIN($Q$2:$Q$170))/(MAX($Q$2:$Q$170)-MIN($Q$2:$Q$170))*100 -> 90 | AQ4: =IF(AP4>=50,AP4,50) -> 90 | AR4: =(#REF!-MIN(#REF!))/(MAX(#REF!)-MIN(#REF!))*100 -> #REF! | AS4: =IF(AR4>=50,AR4,50) -> #REF! | AT4: =(U4-MIN($U$2:$U$170))/(MAX($U$2:$U$170)-MIN($U$2:$U$170))*100 -> 21.271391 | AU4: =(V4-MIN($V$2:$V$170))/(MAX($V$2:$V$170)-MIN($V$2:$V$170))*100 -> 21.396655 | AV4: =(W4-MIN($W$2:$W$170))/(MAX($W$2:$W$170)-MIN($W$2:$W$170))*100 -> 0.68095158 | AW4: =(X4-MIN($X$2:$X$170))/(MAX($X$2:$X$170)-MIN($X$2:$X$170))*100 -> 18.698331 | AX4: =(Y4-MIN($Y$2:$Y$170))/(MAX($Y$2:$Y$170)-MIN($Y$2:$Y$170))*100 -> 20.004733 | AY4: =(Z4-MIN($Z$2:$Z$170))/(MAX($Z$2:$Z$170)-MIN($Z$2:$Z$170))*100 -> 6.9252476 | AZ4: =(AA4-MIN($AA$2:$AA$170))/(MAX($AA$2:$AA$170)-MIN($AA$2:$AA$170))*100 -> 37.786868 | BA4: =(AB4-MIN($AB$2:$AB$170))/(MAX($AB$2:$AB$170)-MIN($AB$2:$AB$170))*100 -> 28.551288 | BB4: =(AC4-MIN($AC$2:$AC$170))/(MAX($AC$2:$AC$170)-MIN($AC$2:$AC$170))*100 -> 36.113494 | BC4: 6.9 | BD4: 329218 | BE4: 1 | BF4: 0.8
A5: ÁNCASH | B5: SANTA | C5: SANTA | D5: 021808 | E5: 219 | F5: 156.61161 | G5: 0.7151215 | H5: 10 | I5: 419463 | J5: 41946.3 | K5: 9 | L5: 399038 | M5: 44338 | N5: 32714.98 | O5: 13743.23 | P5: 27564.27 | Q5: 1 | R5: 168449.04 | S5: 0 | T5: =IF((100-IFERROR(S5/R5*100,0))=100,50,(100-IFERROR(S5/R5*100,0))) -> 50 | U5: 1346 | V5: 4991034.9 | W5: 79579.203 | X5: 537 | Y5: 2196064 | Z5: 76166 | AA5: 21536 | AB5: 1140661.7 | AC5: 34456 | AD5: =(E5-MIN($E$2:$E$170))/(MAX($E$2:$E$170)-MIN($E$2:$E$170))*100 -> 1.473119 | AE5: =(F5-MIN($F$2:$F$170))/(MAX($F$2:$F$170)-MIN($F$2:$F$170))*100 -> 1.3632666 | AF5: =(G5-MIN($G$2:$G$170))/(MAX($G$2:$G$170)-MIN($G$2:$G$170))*100 -> 31.922781 | AG5: =(H5-MIN($H$2:$H$170))/(MAX($H$2:$H$170)-MIN($H$2:$H$170))*100 -> 0.48875855 | AH5: =(I5-MIN($I$2:$I$170))/(MAX($I$2:$I$170)-MIN($I$2:$I$170))*100 -> 0.31405407 | AI5: =(J5-MIN($J$2:$J$170))/(MAX($J$2:$J$170)-MIN($J$2:$J$170))*100 -> 21.325604 | AJ5: =(K5-MIN($K$2:$K$170))/(MAX($K$2:$K$170)-MIN($K$2:$K$170))*100 -> 0.45180723 | AK5: =(L5-MIN($L$2:$L$170))/(MAX($L$2:$L$170)-MIN($L$2:$L$170))*100 -> 0.30812602 | AL5: =(M5-MIN($M$2:$M$170))/(MAX($M$2:$M$170)-MIN($M$2:$M$170))*100 -> 22.541498 | AM5: =(N5-MIN($N$2:$N$170))/(MAX($N$2:$N$170)-MIN($N$2:$N$170))*100 -> 0.35031764 | AN5: =(O5-MIN($O$2:$O$170))/(MAX($O$2:$O$170)-MIN($O$2:$O$170))*100 -> 5.0911545 | AO5: =(P5-MIN($P$2:$P$170))/(MAX($P$2:$P$170)-MIN($P$2:$P$170))*100 -> 0.11200662 | AP5: =(Q5-MIN($Q$2:$Q$170))/(MAX($Q$2:$Q$170)-MIN($Q$2:$Q$170))*100 -> 100 | AQ5: =IF(AP5>=50,AP5,50) -> 100 | AR5: =(#REF!-MIN(#REF!))/(MAX(#REF!)-MIN(#REF!))*100 -> #REF! | AS5: =IF(AR5>=50,AR5,50) -> #REF! | AT5: =(U5-MIN($U$2:$U$170))/(MAX($U$2:$U$170)-MIN($U$2:$U$170))*100 -> 1.3349502 | AU5: =(V5-MIN($V$2:$V$170))/(MAX($V$2:$V$170)-MIN($V$2:$V$170))*100 -> 0.88810407 | AV5: =(W5-MIN($W$2:$W$170))/(MAX($W$2:$W$170)-MIN($W$2:$W$170))*100 -> 0.0077538784 | AW5: =(X5-MIN($X$2:$X$170))/(MAX($X$2:$X$170)-MIN($X$2:$X$170))*100 -> 1.3532726 | AX5: =(Y5-MIN($Y$2:$Y$170))/(MAX($Y$2:$Y$170)-MIN($Y$2:$Y$170))*100 -> 0.66386874 | AY5: =(Z5-MIN($Z$2:$Z$170))/(MAX($Z$2:$Z$170)-MIN($Z$2:$Z$170))*100 -> 0.10085831 | AZ5: =(AA5-MIN($AA$2:$AA$170))/(MAX($AA$2:$AA$170)-MIN($AA$2:$AA$170))*100 -> 0.88753888 | BA5: =(AB5-MIN($AB$2:$AB$170))/(MAX($AB$2:$AB$170)-MIN($AB$2:$AB$170))*100 -> 0.2068706 | BB5: =(AC5-MIN($AC$2:$AC$170))/(MAX($AC$2:$AC$170)-MIN($AC$2:$AC$170))*100 -> 0.5572712 | BC5: 0.4 | BD5: 14906 | BE5: 0 | BF5: 0
A6: ÁNCASH | B6: SANTA | C6: NUEVO CHIMBOTE | D6: 021809 | E6: 1283 | F6: 793.45951 | G6: 0.61844078 | H6: 192 | I6: 8032436.9 | J6: 41835.609 | K6: 182 | L6: 7502707 | M6: 41224 | N6: 90087.98 | O6: 42786.87 | P6: 986851.98 | Q6: 0.86 | R6: 27799107 | S6: 959122.83 | T6: =IF((100-IFERROR(S6/R6*100,0))=100,50,(100-IFERROR(S6/R6*100,0))) -> 96.549807 | U6: 12682 | V6: 72835949 | W6: 2842055 | X6: 4440 | Y6: 38047143 | Z6: 2535451 | AA6: 304452 | AB6: 19344675 | AC6: 621856 | AD6: =(E6-MIN($E$2:$E$170))/(MAX($E$2:$E$170)-MIN($E$2:$E$170))*100 -> 8.7974117 | AE6: =(F6-MIN($F$2:$F$170))/(MAX($F$2:$F$170)-MIN($F$2:$F$170))*100 -> 6.9957049 | AF6: =(G6-MIN($G$2:$G$170))/(MAX($G$2:$G$170)-MIN($G$2:$G$170))*100 -> 23.403481 | AG6: =(H6-MIN($H$2:$H$170))/(MAX($H$2:$H$170)-MIN($H$2:$H$170))*100 -> 9.3841642 | AH6: =(I6-MIN($I$2:$I$170))/(MAX($I$2:$I$170)-MIN($I$2:$I$170))*100 -> 6.0139262 | AI6: =(J6-MIN($J$2:$J$170))/(MAX($J$2:$J$170)-MIN($J$2:$J$170))*100 -> 21.269328 | AJ6: =(K6-MIN($K$2:$K$170))/(MAX($K$2:$K$170)-MIN($K$2:$K$170))*100 -> 9.1365462 | AK6: =(L6-MIN($L$2:$L$170))/(MAX($L$2:$L$170)-MIN($L$2:$L$170))*100 -> 5.7933812 | AL6: =(M6-MIN($M$2:$M$170))/(MAX($M$2:$M$170)-MIN($M$2:$M$170))*100 -> 20.958337 | AM6: =(N6-MIN($N$2:$N$170))/(MAX($N$2:$N$170)-MIN($N$2:$N$170))*100 -> 0.96467761 | AN6: =(O6-MIN($O$2:$O$170))/(MAX($O$2:$O$170)-MIN($O$2:$O$170))*100 -> 15.850318 | AO6: =(P6-MIN($P$2:$P$170))/(MAX($P$2:$P$170)-MIN($P$2:$P$170))*100 -> 4.0100448 | AP6: =(Q6-MIN($Q$2:$Q$170))/(MAX($Q$2:$Q$170)-MIN($Q$2:$Q$170))*100 -> 86 | AQ6: =IF(AP6>=50,AP6,50) -> 86 | AR6: =(#REF!-MIN(#REF!))/(MAX(#REF!)-MIN(#REF!))*100 -> #REF! | AS6: =IF(AR6>=50,AR6,50) -> #REF! | AT6: =(U6-MIN($U$2:$U$170))/(MAX($U$2:$U$170)-MIN($U$2:$U$170))*100 -> 13.185377 | AU6: =(V6-MIN($V$2:$V$170))/(MAX($V$2:$V$170)-MIN($V$2:$V$170))*100 -> 13.246885 | AV6: =(W6-MIN($W$2:$W$170))/(MAX($W$2:$W$170)-MIN($W$2:$W$170))*100 -> 0.27749128 | AW6: =(X6-MIN($X$2:$X$170))/(MAX($X$2:$X$170)-MIN($X$2:$X$170))*100 -> 11.629193 | AX6: =(Y6-MIN($Y$2:$Y$170))/(MAX($Y$2:$Y$170)-MIN($Y$2:$Y$170))*100 -> 11.810078 | AY6: =(Z6-MIN($Z$2:$Z$170))/(MAX($Z$2:$Z$170)-MIN($Z$2:$Z$170))*100 -> 3.3646626 | AZ6: =(AA6-MIN($AA$2:$AA$170))/(MAX($AA$2:$AA$170)-MIN($AA$2:$AA$170))*100 -> 12.577978 | BA6: =(AB6-MIN($AB$2:$AB$170))/(MAX($AB$2:$AB$170)-MIN($AB$2:$AB$170))*100 -> 3.5083535 | BB6: =(AC6-MIN($AC$2:$AC$170))/(MAX($AC$2:$AC$170)-MIN($AC$2:$AC$170))*100 -> 10.075491 | BC6: 3.4 | BD6: 159822 | BE6: 0 | BF6: 0
A7: AREQUIPA | B7: AREQUIPA | C7: AREQUIPA | D7: 040101 | E7: 5653 | F7: 4304.0976 | G7: 0.76138291 | H7: 405 | I7: 20257213 | J7: 50017.81 | K7: 398 | L7: 19791174 | M7: 49727 | N7: 2134572.3 | O7: 94891.91 | P7: 3938302.9 | Q7: 0.91 | R7: 79958060 | S7: 1240509.8 | T7: =IF((100-IFERROR(S7/R7*100,0))=100,50,(100-IFERROR(S7/R7*100,0))) -> 98.448549 | U7: 26484 | V7: 71212946 | W7: 31821439 | X7: 11688 | Y7: 44479129 | Z7: 23010710 | AA7: 1017839 | AB7: 1.241172e+08 | AC7: 1774640 | AD7: =(E7-MIN($E$2:$E$170))/(MAX($E$2:$E$170)-MIN($E$2:$E$170))*100 -> 38.879328 | AE7: =(F7-MIN($F$2:$F$170))/(MAX($F$2:$F$170)-MIN($F$2:$F$170))*100 -> 38.044645 | AF7: =(G7-MIN($G$2:$G$170))/(MAX($G$2:$G$170)-MIN($G$2:$G$170))*100 -> 35.999238 | AG7: =(H7-MIN($H$2:$H$170))/(MAX($H$2:$H$170)-MIN($H$2:$H$170))*100 -> 19.794721 | AH7: =(I7-MIN($I$2:$I$170))/(MAX($I$2:$I$170)-MIN($I$2:$I$170))*100 -> 15.166678 | AI7: =(J7-MIN($J$2:$J$170))/(MAX($J$2:$J$170)-MIN($J$2:$J$170))*100 -> 25.42918 | AJ7: =(K7-MIN($K$2:$K$170))/(MAX($K$2:$K$170)-MIN($K$2:$K$170))*100 -> 19.97992 | AK7: =(L7-MIN($L$2:$L$170))/(MAX($L$2:$L$170)-MIN($L$2:$L$170))*100 -> 15.282193 | AL7: =(M7-MIN($M$2:$M$170))/(MAX($M$2:$M$170)-MIN($M$2:$M$170))*100 -> 25.281273 | AM7: =(N7-MIN($N$2:$N$170))/(MAX($N$2:$N$170)-MIN($N$2:$N$170))*100 -> 22.857368 | AN7: =(O7-MIN($O$2:$O$170))/(MAX($O$2:$O$170)-MIN($O$2:$O$170))*100 -> 35.152535 | AO7: =(P7-MIN($P$2:$P$170))/(MAX($P$2:$P$170)-MIN($P$2:$P$170))*100 -> 16.003181 | AP7: =(Q7-MIN($Q$2:$Q$170))/(MAX($Q$2:$Q$170)-MIN($Q$2:$Q$170))*100 -> 91 | AQ7: =IF(AP7>=50,AP7,50) -> 91 | AR7: =(#REF!-MIN(#REF!))/(MAX(#REF!)-MIN(#REF!))*100 -> #REF! | AS7: =IF(AR7>=50,AR7,50) -> #REF! | AT7: =(U7-MIN($U$2:$U$170))/(MAX($U$2:$U$170)-MIN($U$2:$U$170))*100 -> 27.613711 | AU7: =(V7-MIN($V$2:$V$170))/(MAX($V$2:$V$170)-MIN($V$2:$V$170))*100 -> 12.951236 | AV7: =(W7-MIN($W$2:$W$170))/(MAX($W$2:$W$170)-MIN($W$2:$W$170))*100 -> 3.1071355 | AW7: =(X7-MIN($X$2:$X$170))/(MAX($X$2:$X$170)-MIN($X$2:$X$170))*100 -> 30.711916 | AX7: =(Y7-MIN($Y$2:$Y$170))/(MAX($Y$2:$Y$170)-MIN($Y$2:$Y$170))*100 -> 13.809801 | AY7: =(Z7-MIN($Z$2:$Z$170))/(MAX($Z$2:$Z$170)-MIN($Z$2:$Z$170))*100 -> 30.538105 | AZ7: =(AA7-MIN($AA$2:$AA$170))/(MAX($AA$2:$AA$170)-MIN($AA$2:$AA$170))*100 -> 42.056013 | BA7: =(AB7-MIN($AB$2:$AB$170))/(MAX($AB$2:$AB$170)-MIN($AB$2:$AB$170))*100 -> 22.509916 | BB7: =(AC7-MIN($AC$2:$AC$170))/(MAX($AC$2:$AC$170)-MIN($AC$2:$AC$170))*100 -> 28.755184 | BC7: 11 | BD7: 566439 | BE7: 6 | BF7: 6.3
A8: AREQUIPA | B8: AREQUIPA | C8: ALTO SELVA ALEGRE | D8: 040102 | E8: 402 | F8: 208.9648 | G8: 0.51981294 | H8: 68 | I8: 3132970.9 | J8: 46073.102 | K8: 66 | L8: 3098338 | M8: 46945 | N8: 109611.04 | O8: 17729.58 | P8: 731979.01 | Q8: 0.88 | R8: 10108848 | S8: 331016.99 | T8: =IF((100-IFERROR(S8/R8*100,0))=100,50,(100-IFERROR(S8/R8*100,0))) -> 96.725473 | U8: 7179 | V8: 17263943 | W8: 1829225.6 | X8: 3081 | Y8: 10972276 | Z8: 728505 | AA8: 88323 | AB8: 5164659.9 | AC8: 158054 | AD8: =(E8-MIN($E$2:$E$170))/(MAX($E$2:$E$170)-MIN($E$2:$E$170))*100 -> 2.7328423 | AE8: =(F8-MIN($F$2:$F$170))/(MAX($F$2:$F$170)-MIN($F$2:$F$170))*100 -> 1.826291 | AF8: =(G8-MIN($G$2:$G$170))/(MAX($G$2:$G$170)-MIN($G$2:$G$170))*100 -> 14.712605 | AG8: =(H8-MIN($H$2:$H$170))/(MAX($H$2:$H$170)-MIN($H$2:$H$170))*100 -> 3.3235582 | AH8: =(I8-MIN($I$2:$I$170))/(MAX($I$2:$I$170)-MIN($I$2:$I$170))*100 -> 2.3456712 | AI8: =(J8-MIN($J$2:$J$170))/(MAX($J$2:$J$170)-MIN($J$2:$J$170))*100 -> 23.42368 | AJ8: =(K8-MIN($K$2:$K$170))/(MAX($K$2:$K$170)-MIN($K$2:$K$170))*100 -> 3.313253 | AK8: =(L8-MIN($L$2:$L$170))/(MAX($L$2:$L$170)-MIN($L$2:$L$170))*100 -> 2.3924502 | AL8: =(M8-MIN($M$2:$M$170))/(MAX($M$2:$M$170)-MIN($M$2:$M$170))*100 -> 23.866901 | AM8: =(N8-MIN($N$2:$N$170))/(MAX($N$2:$N$170)-MIN($N$2:$N$170))*100 -> 1.1737339 | AN8: =(O8-MIN($O$2:$O$170))/(MAX($O$2:$O$170)-MIN($O$2:$O$170))*100 -> 6.5678906 | AO8: =(P8-MIN($P$2:$P$170))/(MAX($P$2:$P$170)-MIN($P$2:$P$170))*100 -> 2.9743758 | AP8: =(Q8-MIN($Q$2:$Q$170))/(MAX($Q$2:$Q$170)-MIN($Q$2:$Q$170))*100 -> 88 | AQ8: =IF(AP8>=50,AP8,50) -> 88 | AR8: =(#REF!-MIN(#REF!))/(MAX(#REF!)-MIN(#REF!))*100 -> #REF! | AS8: =IF(AR8>=50,AR8,50) -> #REF! | AT8: =(U8-MIN($U$2:$U$170))/(MAX($U$2:$U$170)-MIN($U$2:$U$170))*100 -> 7.4326514 | AU8: =(V8-MIN($V$2:$V$170))/(MAX($V$2:$V$170)-MIN($V$2:$V$170))*100 -> 3.1237645 | AV8: =(W8-MIN($W$2:$W$170))/(MAX($W$2:$W$170)-MIN($W$2:$W$170))*100 -> 0.17859522 | AW8: =(X8-MIN($X$2:$X$170))/(MAX($X$2:$X$170)-MIN($X$2:$X$170))*100 -> 8.0511821 | AX8: =(Y8-MIN($Y$2:$Y$170))/(MAX($Y$2:$Y$170)-MIN($Y$2:$Y$170))*100 -> 3.3924196 | AY8: =(Z8-MIN($Z$2:$Z$170))/(MAX($Z$2:$Z$170)-MIN($Z$2:$Z$170))*100 -> 0.96660053 | AZ8: =(AA8-MIN($AA$2:$AA$170))/(MAX($AA$2:$AA$170)-MIN($AA$2:$AA$170))*100 -> 3.6472604 | BA8: =(AB8-MIN($AB$2:$AB$170))/(MAX($AB$2:$AB$170)-MIN($AB$2:$AB$170))*100 -> 0.93666355 | BB8: =(AC8-MIN($AC$2:$AC$170))/(MAX($AC$2:$AC$170)-MIN($AC$2:$AC$170))*100 -> 2.5600512 | BC8: 3.3 | BD8: 137970 | BE8: 0 | BF8: 0
A9: AREQUIPA | B9: AREQUIPA | C9: CAYMA | D9: 040103 | E9: 1055 | F9: 829.7999 | G9: 0.78654019 | H9: 119 | I9: 6220738.4 | J9: 52275.113 | K9: 116 | L9: 6188442 | M9: 53349 | N9: 294794.34 | O9: 28305.06 | P9: 1626179.5 | Q9: 0.87 | R9: 16819833 | S9: 363516.61 | T9: =IF((100-IFERROR(S9/R9*100,0))=100,50,(100-IFERROR(S9/R9*100,0))) -> 97.838762 | U9: 8595 | V9: 20014283 | W9: 3644454.2 | X9: 3778 | Y9: 11554579 | Z9: 3482681 | AA9: 543688 | AB9: 66746563 | AC9: 995162 | AD9: =(E9-MIN($E$2:$E$170))/(MAX($E$2:$E$170)-MIN($E$2:$E$170))*100 -> 7.2279204 | AE9: =(F9-MIN($F$2:$F$170))/(MAX($F$2:$F$170)-MIN($F$2:$F$170))*100 -> 7.3171081 | AF9: =(G9-MIN($G$2:$G$170))/(MAX($G$2:$G$170)-MIN($G$2:$G$170))*100 -> 38.216045 | AG9: =(H9-MIN($H$2:$H$170))/(MAX($H$2:$H$170)-MIN($H$2:$H$170))*100 -> 5.8162268 | AH9: =(I9-MIN($I$2:$I$170))/(MAX($I$2:$I$170)-MIN($I$2:$I$170))*100 -> 4.6574983 | AI9: =(J9-MIN($J$2:$J$170))/(MAX($J$2:$J$170)-MIN($J$2:$J$170))*100 -> 26.576798 | AJ9: =(K9-MIN($K$2:$K$170))/(MAX($K$2:$K$170)-MIN($K$2:$K$170))*100 -> 5.8232932 | AK9: =(L9-MIN($L$2:$L$170))/(MAX($L$2:$L$170)-MIN($L$2:$L$170))*100 -> 4.7785424 | AL9: =(M9-MIN($M$2:$M$170))/(MAX($M$2:$M$170)-MIN($M$2:$M$170))*100 -> 27.122703 | AM9: =(N9-MIN($N$2:$N$170))/(MAX($N$2:$N$170)-MIN($N$2:$N$170))*100 -> 3.1567086 | AN9: =(O9-MIN($O$2:$O$170))/(MAX($O$2:$O$170)-MIN($O$2:$O$170))*100 -> 10.485558 | AO9: =(P9-MIN($P$2:$P$170))/(MAX($P$2:$P$170)-MIN($P$2:$P$170))*100 -> 6.6079337 | AP9: =(Q9-MIN($Q$2:$Q$170))/(MAX($Q$2:$Q$170)-MIN($Q$2:$Q$170))*100 -> 87 | AQ9: =IF(AP9>=50,AP9,50) -> 87 | AR9: =(#REF!-MIN(#REF!))/(MAX(#REF!)-MIN(#REF!))*100 -> #REF! | AS9: =IF(AR9>=50,AR9,50) -> #REF! | AT9: =(U9-MIN($U$2:$U$170))/(MAX($U$2:$U$170)-MIN($U$2:$U$170))*100 -> 8.9129094 | AU9: =(V9-MIN($V$2:$V$170))/(MAX($V$2:$V$170)-MIN($V$2:$V$170))*100 -> 3.6247725 | AV9: =(W9-MIN($W$2:$W$170))/(MAX($W$2:$W$170)-MIN($W$2:$W$170))*100 -> 0.35584022 | AW9: =(X9-MIN($X$2:$X$170))/(MAX($X$2:$X$170)-MIN($X$2:$X$170))*100 -> 9.8862619 | AX9: =(Y9-MIN($Y$2:$Y$170))/(MAX($Y$2:$Y$170)-MIN($Y$2:$Y$170))*100 -> 3.5734593 | AY9: =(Z9-MIN($Z$2:$Z$170))/(MAX($Z$2:$Z$170)-MIN($Z$2:$Z$170))*100 -> 4.6217651 | AZ9: =(AA9-MIN($AA$2:$AA$170))/(MAX($AA$2:$AA$170)-MIN($AA$2:$AA$170))*100 -> 22.463506 | BA9: =(AB9-MIN($AB$2:$AB$170))/(MAX($AB$2:$AB$170)-MIN($AB$2:$AB$170))*100 -> 12.105167 | BB9: =(AC9-MIN($AC$2:$AC$170))/(MAX($AC$2:$AC$170)-MIN($AC$2:$AC$170))*100 -> 16.124535 | BC9: 3.6 | BD9: 165965 | BE9: 0 | BF9: 0
A10: AREQUIPA | B10: AREQUIPA | C10: CERRO COLORADO | D10: 040104 | E10: 2099 | F10: 1647.1315 | G10: 0.78472202 | H10: 266 | I10: 15947399 | J10: 59952.63 | K10: 260 | L10: 15752254 | M10: 60586 | N10: 624849.6 | O10: 88018.57 | P10: 3492921.9 | Q10: 0.93 | R10: 48907211 | S10: 419795.1 | T10: =IF((100-IFERROR(S10/R10*100,0))=100,50,(100-IFERROR(S10/R10*100,0))) -> 99.14165 | U10: 17090 | V10: 28273277 | W10: 9091918.5 | X10: 8642 | Y10: 16838791 | Z10: 4322266 | AA10: 432699 | AB10: 93252328 | AC10: 804433 | AD10: =(E10-MIN($E$2:$E$170))/(MAX($E$2:$E$170)-MIN($E$2:$E$170))*100 -> 14.414538 | AE10: =(F10-MIN($F$2:$F$170))/(MAX($F$2:$F$170)-MIN($F$2:$F$170))*100 -> 14.545788 | AF10: =(G10-MIN($G$2:$G$170))/(MAX($G$2:$G$170)-MIN($G$2:$G$170))*100 -> 38.055832 | AG10: =(H10-MIN($H$2:$H$170))/(MAX($H$2:$H$170)-MIN($H$2:$H$170))*100 -> 13.000978 | AH10: =(I10-MIN($I$2:$I$170))/(MAX($I$2:$I$170)-MIN($I$2:$I$170))*100 -> 11.939899 | AI10: =(J10-MIN($J$2:$J$170))/(MAX($J$2:$J$170)-MIN($J$2:$J$170))*100 -> 30.480067 | AJ10: =(K10-MIN($K$2:$K$170))/(MAX($K$2:$K$170)-MIN($K$2:$K$170))*100 -> 13.052209 | AK10: =(L10-MIN($L$2:$L$170))/(MAX($L$2:$L$170)-MIN($L$2:$L$170))*100 -> 12.163451 | AL10: =(M10-MIN($M$2:$M$170))/(MAX($M$2:$M$170)-MIN($M$2:$M$170))*100 -> 30.802003 | AM10: =(N10-MIN($N$2:$N$170))/(MAX($N$2:$N$170)-MIN($N$2:$N$170))*100 -> 6.6909972 | AN10: =(O10-MIN($O$2:$O$170))/(MAX($O$2:$O$170)-MIN($O$2:$O$170))*100 -> 32.606319 | AO10: =(P10-MIN($P$2:$P$170))/(MAX($P$2:$P$170)-MIN($P$2:$P$170))*100 -> 14.193388 | AP10: =(Q10-MIN($Q$2:$Q$170))/(MAX($Q$2:$Q$170)-MIN($Q$2:$Q$170))*100 -> 93 | AQ10: =IF(AP10>=50,AP10,50) -> 93 | AR10: =(#REF!-MIN(#REF!))/(MAX(#REF!)-MIN(#REF!))*100 -> #REF! | AS10: =IF(AR10>=50,AR10,50) -> #REF! | AT10: =(U10-MIN($U$2:$U$170))/(MAX($U$2:$U$170)-MIN($U$2:$U$170))*100 -> 17.793412 | AU10: =(V10-MIN($V$2:$V$170))/(MAX($V$2:$V$170)-MIN($V$2:$V$170))*100 -> 5.1292494 | AV10: =(W10-MIN($W$2:$W$170))/(MAX($W$2:$W$170)-MIN($W$2:$W$170))*100 -> 0.8877489 | AW10: =(X10-MIN($X$2:$X$170))/(MAX($X$2:$X$170)-MIN($X$2:$X$170))*100 -> 22.692328 | AX10: =(Y10-MIN($Y$2:$Y$170))/(MAX($Y$2:$Y$170)-MIN($Y$2:$Y$170))*100 -> 5.2163368 | AY10: =(Z10-MIN($Z$2:$Z$170))/(MAX($Z$2:$Z$170)-MIN($Z$2:$Z$170))*100 -> 5.7360082 | AZ10: =(AA10-MIN($AA$2:$AA$170))/(MAX($AA$2:$AA$170)-MIN($AA$2:$AA$170))*100 -> 17.877303 | BA10: =(AB10-MIN($AB$2:$AB$170))/(MAX($AB$2:$AB$170)-MIN($AB$2:$AB$170))*100 -> 16.912257 | BB10: =(AC10-MIN($AC$2:$AC$170))/(MAX($AC$2:$AC$170)-MIN($AC$2:$AC$170))*100 -> 13.033966 | BC10: 6.5 | BD10: 316064 | BE10: 0 | BF10: 0
A11: AREQUIPA | B11: AREQUIPA | C11: CHARACATO | D11: 040105 | E11: 23 | F11: 17.904082 | G11: 0.77843837 | H11: 7 | I11: 310331.13 | J11: 44333.019 | K11: 7 | L11: 310331 | M11: 44333 | N11: 0 | O11: 0 | P11: 300000 | Q11: 1 | R11: 1121515.9 | S11: 0 | T11: =IF((100-IFERROR(S11/R11*100,0))=100,50,(100-IFERROR(S11/R11*100,0))) -> 50 | U11: 699 | V11: 860467.7 | W11: 501417.7 | X11: 341 | Y11: 562839 | Z11: 501418 | AA11: 700 | AB11: 28808.43 | AC11: 1006 | AD11: =(E11-MIN($E$2:$E$170))/(MAX($E$2:$E$170)-MIN($E$2:$E$170))*100 -> 0.12390721 | AE11: =(F11-MIN($F$2:$F$170))/(MAX($F$2:$F$170)-MIN($F$2:$F$170))*100 -> 0.13650336 | AF11: =(G11-MIN($G$2:$G$170))/(MAX($G$2:$G$170)-MIN($G$2:$G$170))*100 -> 37.502129 | AG11: =(H11-MIN($H$2:$H$170))/(MAX($H$2:$H$170)-MIN($H$2:$H$170))*100 -> 0.34213099 | AH11: =(I11-MIN($I$2:$I$170))/(MAX($I$2:$I$170)-MIN($I$2:$I$170))*100 -> 0.23234649 | AI11: =(J11-MIN($J$2:$J$170))/(MAX($J$2:$J$170)-MIN($J$2:$J$170))*100 -> 22.539018 | AJ11: =(K11-MIN($K$2:$K$170))/(MAX($K$2:$K$170)-MIN($K$2:$K$170))*100 -> 0.35140562 | AK11: =(L11-MIN($L$2:$L$170))/(MAX($L$2:$L$170)-MIN($L$2:$L$170))*100 -> 0.23962895 | AL11: =(M11-MIN($M$2:$M$170))/(MAX($M$2:$M$170)-MIN($M$2:$M$170))*100 -> 22.538956 | AM11: =(N11-MIN($N$2:$N$170))/(MAX($N$2:$N$170)-MIN($N$2:$N$170))*100 -> 0 | AN11: =(O11-MIN($O$2:$O$170))/(MAX($O$2:$O$170)-MIN($O$2:$O$170))*100 -> 0 | AO11: =(P11-MIN($P$2:$P$170))/(MAX($P$2:$P$170)-MIN($P$2:$P$170))*100 -> 1.2190414 | AP11: =(Q11-MIN($Q$2:$Q$170))/(MAX($Q$2:$Q$170)-MIN($Q$2:$Q$170))*100 -> 100 | AQ11: =IF(AP11>=50,AP11,50) -> 100 | AR11: =(#REF!-MIN(#REF!))/(MAX(#REF!)-MIN(#REF!))*100 -> #REF! | AS11: =IF(AR11>=50,AR11,50) -> #REF! | AT11: =(U11-MIN($U$2:$U$170))/(MAX($U$2:$U$170)-MIN($U$2:$U$170))*100 -> 0.65858936 | AU11: =(V11-MIN($V$2:$V$170))/(MAX($V$2:$V$170)-MIN($V$2:$V$170))*100 -> 0.1356707 | AV11: =(W11-MIN($W$2:$W$170))/(MAX($W$2:$W$170)-MIN($W$2:$W$170))*100 -> 0.048943603 | AW11: =(X11-MIN($X$2:$X$170))/(MAX($X$2:$X$170)-MIN($X$2:$X$170))*100 -> 0.83723869 | AX11: =(Y11-MIN($Y$2:$Y$170))/(MAX($Y$2:$Y$170)-MIN($Y$2:$Y$170))*100 -> 0.15609415 | AY11: =(Z11-MIN($Z$2:$Z$170))/(MAX($Z$2:$Z$170)-MIN($Z$2:$Z$170))*100 -> 0.66522532 | AZ11: =(AA11-MIN($AA$2:$AA$170))/(MAX($AA$2:$AA$170)-MIN($AA$2:$AA$170))*100 -> 0.026569556 | BA11: =(AB11-MIN($AB$2:$AB$170))/(MAX($AB$2:$AB$170)-MIN($AB$2:$AB$170))*100 -> 0.0052247015 | BB11: =(AC11-MIN($AC$2:$AC$170))/(MAX($AC$2:$AC$170)-MIN($AC$2:$AC$170))*100 -> 0.015247948 | BC11: 0.1 | BD11: 6148 | BE11: 0 | BF11: 0
A12: AREQUIPA | B12: AREQUIPA | C12: JACOBO HUNTER | D12: 040107 | E12: 498 | F12: 312.35048 | G12: 0.62720979 | H12: 43 | I12: 1517968.8 | J12: 35301.599 | K12: 42 | L12: 1514038 | M12: 36049 | N12: 120993.04 | O12: 24955.83 | P12: 320325.45 | Q12: 0.89 | R12: 5469146.6 | S12: 46007.74 | T12: =IF((100-IFERROR(S12/R12*100,0))=100,50,(100-IFERROR(S12/R12*100,0))) -> 99.158777 | U12: 4472 | V12: 7851658.6 | W12: 435225.91 | X12: 1880 | Y12: 5102435 | Z12: 420816 | AA12: 71299 | AB12: 4452406.9 | AC12: 123930 | AD12: =(E12-MIN($E$2:$E$170))/(MAX($E$2:$E$170)-MIN($E$2:$E$170))*100 -> 3.3936807 | AE12: =(F12-MIN($F$2:$F$170))/(MAX($F$2:$F$170)-MIN($F$2:$F$170))*100 -> 2.7406591 | AF12: =(G12-MIN($G$2:$G$170))/(MAX($G$2:$G$170)-MIN($G$2:$G$170))*100 -> 24.176188 | AG12: =(H12-MIN($H$2:$H$170))/(MAX($H$2:$H$170)-MIN($H$2:$H$170))*100 -> 2.1016618 | AH12: =(I12-MIN($I$2:$I$170))/(MAX($I$2:$I$170)-MIN($I$2:$I$170))*100 -> 1.1365109 | AI12: =(J12-MIN($J$2:$J$170))/(MAX($J$2:$J$170)-MIN($J$2:$J$170))*100 -> 17.947421 | AJ12: =(K12-MIN($K$2:$K$170))/(MAX($K$2:$K$170)-MIN($K$2:$K$170))*100 -> 2.1084337 | AK12: =(L12-MIN($L$2:$L$170))/(MAX($L$2:$L$170)-MIN($L$2:$L$170))*100 -> 1.1690979 | AL12: =(M12-MIN($M$2:$M$170))/(MAX($M$2:$M$170)-MIN($M$2:$M$170))*100 -> 18.32736 | AM12: =(N12-MIN($N$2:$N$170))/(MAX($N$2:$N$170)-MIN($N$2:$N$170))*100 -> 1.2956143 | AN12: =(O12-MIN($O$2:$O$170))/(MAX($O$2:$O$170)-MIN($O$2:$O$170))*100 -> 9.2448418 | AO12: =(P12-MIN($P$2:$P$170))/(MAX($P$2:$P$170)-MIN($P$2:$P$170))*100 -> 1.3016333 | AP12: =(Q12-MIN($Q$2:$Q$170))/(MAX($Q$2:$Q$170)-MIN($Q$2:$Q$170))*100 -> 89 | AQ12: =IF(AP12>=50,AP12,50) -> 89 | AR12: =(#REF!-MIN(#REF!))/(MAX(#REF!)-MIN(#REF!))*100 -> #REF! | AS12: =IF(AR12>=50,AR12,50) -> #REF! | AT12: =(U12-MIN($U$2:$U$170))/(MAX($U$2:$U$170)-MIN($U$2:$U$170))*100 -> 4.6028079 | AU12: =(V12-MIN($V$2:$V$170))/(MAX($V$2:$V$170)-MIN($V$2:$V$170))*100 -> 1.4092017 | AV12: =(W12-MIN($W$2:$W$170))/(MAX($W$2:$W$170)-MIN($W$2:$W$170))*100 -> 0.042480415 | AW12: =(X12-MIN($X$2:$X$170))/(MAX($X$2:$X$170)-MIN($X$2:$X$170))*100 -> 4.889158 | AX12: =(Y12-MIN($Y$2:$Y$170))/(MAX($Y$2:$Y$170)-MIN($Y$2:$Y$170))*100 -> 1.5674683 | AY12: =(Z12-MIN($Z$2:$Z$170))/(MAX($Z$2:$Z$170)-MIN($Z$2:$Z$170))*100 -> 0.55825555 | AZ12: =(AA12-MIN($AA$2:$AA$170))/(MAX($AA$2:$AA$170)-MIN($AA$2:$AA$170))*100 -> 2.9438077 | BA12: =(AB12-MIN($AB$2:$AB$170))/(MAX($AB$2:$AB$170)-MIN($AB$2:$AB$170))*100 -> 0.80748923 | BB12: =(AC12-MIN($AC$2:$AC$170))/(MAX($AC$2:$AC$170)-MIN($AC$2:$AC$170))*100 -> 2.0071064 | BC12: 1.9 | BD12: 78485 | BE12: 0 | BF12: 0
A13: AREQUIPA | B13: AREQUIPA | C13: MARIANO MELGAR | D13: 040109 | E13: 697 | F13: 546.54434 | G13: 0.78413822 | H13: 61 | I13: 3853529.9 | J13: 63172.622 | K13: 60 | L13: 3850404 | M13: 64173 | N13: 1952.43 | O13: 6.54 | P13: 472592.22 | Q13: 0.87 | R13: 8426281.5 | S13: 266426.77 | T13: =IF((100-IFERROR(S13/R13*100,0))=100,50,(100-IFERROR(S13/R13*100,0))) -> 96.838145 | U13: 6056 | V13: 13276863 | W13: 956751.89 | X13: 2716 | Y13: 8196122 | Z13: 833454 | AA13: 52111 | AB13: 2874723.5 | AC13: 85410 | AD13: =(E13-MIN($E$2:$E$170))/(MAX($E$2:$E$170)-MIN($E$2:$E$170))*100 -> 4.7635437 | AE13: =(F13-MIN($F$2:$F$170))/(MAX($F$2:$F$170)-MIN($F$2:$F$170))*100 -> 4.8119268 | AF13: =(G13-MIN($G$2:$G$170))/(MAX($G$2:$G$170)-MIN($G$2:$G$170))*100 -> 38.004388 | AG13: =(H13-MIN($H$2:$H$170))/(MAX($H$2:$H$170)-MIN($H$2:$H$170))*100 -> 2.9814272 | AH13: =(I13-MIN($I$2:$I$170))/(MAX($I$2:$I$170)-MIN($I$2:$I$170))*100 -> 2.8851574 | AI13: =(J13-MIN($J$2:$J$170))/(MAX($J$2:$J$170)-MIN($J$2:$J$170))*100 -> 32.117119 | AJ13: =(K13-MIN($K$2:$K$170))/(MAX($K$2:$K$170)-MIN($K$2:$K$170))*100 -> 3.0120482 | AK13: =(L13-MIN($L$2:$L$170))/(MAX($L$2:$L$170)-MIN($L$2:$L$170))*100 -> 2.9731746 | AL13: =(M13-MIN($M$2:$M$170))/(MAX($M$2:$M$170)-MIN($M$2:$M$170))*100 -> 32.625639 | AM13: =(N13-MIN($N$2:$N$170))/(MAX($N$2:$N$170)-MIN($N$2:$N$170))*100 -> 0.020906957 | AN13: =(O13-MIN($O$2:$O$170))/(MAX($O$2:$O$170)-MIN($O$2:$O$170))*100 -> 0.0024227311 | AO13: =(P13-MIN($P$2:$P$170))/(MAX($P$2:$P$170)-MIN($P$2:$P$170))*100 -> 1.920365 | AP13: =(Q13-MIN($Q$2:$Q$170))/(MAX($Q$2:$Q$170)-MIN($Q$2:$Q$170))*100 -> 87 | AQ13: =IF(AP13>=50,AP13,50) -> 87 | AR13: =(#REF!-MIN(#REF!))/(MAX(#REF!)-MIN(#REF!))*100 -> #REF! | AS13: =IF(AR13>=50,AR13,50) -> #REF! | AT13: =(U13-MIN($U$2:$U$170))/(MAX($U$2:$U$170)-MIN($U$2:$U$170))*100 -> 6.2586897 | AU13: =(V13-MIN($V$2:$V$170))/(MAX($V$2:$V$170)-MIN($V$2:$V$170))*100 -> 2.397469 | AV13: =(W13-MIN($W$2:$W$170))/(MAX($W$2:$W$170)-MIN($W$2:$W$170))*100 -> 0.09340396 | AW13: =(X13-MIN($X$2:$X$170))/(MAX($X$2:$X$170)-MIN($X$2:$X$170))*100 -> 7.0902006 | AX13: =(Y13-MIN($Y$2:$Y$170))/(MAX($Y$2:$Y$170)-MIN($Y$2:$Y$170))*100 -> 2.5293049 | AY13: =(Z13-MIN($Z$2:$Z$170))/(MAX($Z$2:$Z$170)-MIN($Z$2:$Z$170))*100 -> 1.1058821 | AZ13: =(AA13-MIN($AA$2:$AA$170))/(MAX($AA$2:$AA$170)-MIN($AA$2:$AA$170))*100 -> 2.1509357 | BA13: =(AB13-MIN($AB$2:$AB$170))/(MAX($AB$2:$AB$170)-MIN($AB$2:$AB$170))*100 -> 0.52136032 | BB13: =(AC13-MIN($AC$2:$AC$170))/(MAX($AC$2:$AC$170)-MIN($AC$2:$AC$170))*100 -> 1.382929 | BC13: 3.1 | BD13: 146897 | BE13: 1 | BF13: 0.8
... A15: AREQUIPA | B15: AREQUIPA | C15: PAUCARPATA | D15: 040112 | E15: 1156 | F15: 823.49739 | G15: 0.71236798 | H15: 148 | I15: 7109628.8 | J15: 48038.033 | K15: 142 | L15: 7036064 | M15: 49550 | N15: 379243.78 | O15: 46340.09 | P15: 1999931.7 | Q15: 0.93 | R15: 29864369 | S15: 276225.79 | T15: =IF((100-IFERROR(S15/R15*100,0))=100,50,(100-IFERROR(S15/R15*100,0))) -> 99.075066 | U15: 13036 | V15: 25230203 | W15: 4941542.1 | X15: 5778 | Y15: 15405350 | Z15: 2094298 | AA15: 206066 | AB15: 13406085 | AC15: 328025 | AD15: =(E15-MIN($E$2:$E$170))/(MAX($E$2:$E$170)-MIN($E$2:$E$170))*100 -> 7.9231775 | AE15: =(F15-MIN($F$2:$F$170))/(MAX($F$2:$F$170)-MIN($F$2:$F$170))*100 -> 7.2613672 | AF15: =(G15-MIN($G$2:$G$170))/(MAX($G$2:$G$170)-MIN($G$2:$G$170))*100 -> 31.680147 | AG15: =(H15-MIN($H$2:$H$170))/(MAX($H$2:$H$170)-MIN($H$2:$H$170))*100 -> 7.2336266 | AH15: =(I15-MIN($I$2:$I$170))/(MAX($I$2:$I$170)-MIN($I$2:$I$170))*100 -> 5.3230151 | AI15: =(J15-MIN($J$2:$J$170))/(MAX($J$2:$J$170)-MIN($J$2:$J$170))*100 -> 24.422656 | AJ15: =(K15-MIN($K$2:$K$170))/(MAX($K$2:$K$170)-MIN($K$2:$K$170))*100 -> 7.1285141 | AK15: =(L15-MIN($L$2:$L$170))/(MAX($L$2:$L$170)-MIN($L$2:$L$170))*100 -> 5.4330525 | AL15: =(M15-MIN($M$2:$M$170))/(MAX($M$2:$M$170)-MIN($M$2:$M$170))*100 -> 25.191286 | AM15: =(N15-MIN($N$2:$N$170))/(MAX($N$2:$N$170)-MIN($N$2:$N$170))*100 -> 4.0610077 | AN15: =(O15-MIN($O$2:$O$170))/(MAX($O$2:$O$170)-MIN($O$2:$O$170))*100 -> 17.166602 | AO15: =(P15-MIN($P$2:$P$170))/(MAX($P$2:$P$170)-MIN($P$2:$P$170))*100 -> 8.1266654 | AP15: =(Q15-MIN($Q$2:$Q$170))/(MAX($Q$2:$Q$170)-MIN($Q$2:$Q$170))*100 -> 93 | AQ15: =IF(AP15>=50,AP15,50) -> 93 | AR15: =(#REF!-MIN(#REF!))/(MAX(#REF!)-MIN(#REF!))*100 -> #REF! | AS15: =IF(AR15>=50,AR15,50) -> #REF! | AT15: =(U15-MIN($U$2:$U$170))/(MAX($U$2:$U$170)-MIN($U$2:$U$170))*100 -> 13.555442 | AU15: =(V15-MIN($V$2:$V$170))/(MAX($V$2:$V$170)-MIN($V$2:$V$170))*100 -> 4.5749162 | AV15: =(W15-MIN($W$2:$W$170))/(MAX($W$2:$W$170)-MIN($W$2:$W$170))*100 -> 0.48249224 | AW15: =(X15-MIN($X$2:$X$170))/(MAX($X$2:$X$170)-MIN($X$2:$X$170))*100 -> 15.151914 | AX15: =(Y15-MIN($Y$2:$Y$170))/(MAX($Y$2:$Y$170)-MIN($Y$2:$Y$170))*100 -> 4.7706757 | AY15: =(Z15-MIN($Z$2:$Z$170))/(MAX($Z$2:$Z$170)-MIN($Z$2:$Z$170))*100 -> 2.7791928 | AZ15: =(AA15-MIN($AA$2:$AA$170))/(MAX($AA$2:$AA$170)-MIN($AA$2:$AA$170))*100 -> 8.512547 | BA15: =(AB15-MIN($AB$2:$AB$170))/(MAX($AB$2:$AB$170)-MIN($AB$2:$AB$170))*100 -> 2.4313298 | BB15: =(AC15-MIN($AC$2:$AC$170))/(MAX($AC$2:$AC$170)-MIN($AC$2:$AC$170))*100 -> 5.3142584 | BC15: 6.5 | BD15: 295147 | BE15: 1 | BF15: 0.2
A16: AREQUIPA | B16: AREQUIPA | C16: SABANDIA | D16: 040116 | E16: 5 | F16: 2.9186705 | G16: 0.5837341 | H16: 0 | I16: 0 | J16: 0 | K16: 0 | L16: 0 | M16: 0 | N16: 0 | O16: 0 | P16: 0 | Q16: 0 | R16: 0 | S16: 0 | T16: =IF((100-IFERROR(S16/R16*100,0))=100,50,(100-IFERROR(S16/R16*100,0))) -> 50 | U16: 279 | V16: 819738.4 | W16: 326402.63 | X16: 127 | Y16: 478761 | Z16: 326403 | AD16: =(E16-MIN($E$2:$E$170))/(MAX($E$2:$E$170)-MIN($E$2:$E$170))*100 -> 0 | AE16: =(F16-MIN($F$2:$F$170))/(MAX($F$2:$F$170)-MIN($F$2:$F$170))*100 -> 0.0039687233 | AF16: =(G16-MIN($G$2:$G$170))/(MAX($G$2:$G$170)-MIN($G$2:$G$170))*100 -> 20.345202 | AG16: =(H16-MIN($H$2:$H$170))/(MAX($H$2:$H$170)-MIN($H$2:$H$170))*100 -> 0 | AH16: =(I16-MIN($I$2:$I$170))/(MAX($I$2:$I$170)-MIN($I$2:$I$170))*100 -> 0 | AI16: =(J16-MIN($J$2:$J$170))/(MAX($J$2:$J$170)-MIN($J$2:$J$170))*100 -> 0 | AJ16: =(K16-MIN($K$2:$K$170))/(MAX($K$2:$K$170)-MIN($K$2:$K$170))*100 -> 0 | AK16: =(L16-MIN($L$2:$L$170))/(MAX($L$2:$L$170)-MIN($L$2:$L$170))*100 -> 0 | AL16: =(M16-MIN($M$2:$M$170))/(MAX($M$2:$M$170)-MIN($M$2:$M$170))*100 -> 0 | AM16: =(N16-MIN($N$2:$N$170))/(MAX($N$2:$N$170)-MIN($N$2:$N$170))*100 -> 0 | AN16: =(O16-MIN($O$2:$O$170))/(MAX($O$2:$O$170)-MIN($O$2:$O$170))*100 -> 0 | AO16: =(P16-MIN($P$2:$P$170))/(MAX($P$2:$P$170)-MIN($P$2:$P$170))*100 -> 0 | AP16: =(Q16-MIN($Q$2:$Q$170))/(MAX($Q$2:$Q$170)-MIN($Q$2:$Q$170))*100 -> 0 | AQ16: =IF(AP16>=50,AP16,50) -> 50 | AR16: =(#REF!-MIN(#REF!))/(MAX(#REF!)-MIN(#REF!))*100 -> #REF! | AS16: =IF(AR16>=50,AR16,50) -> #REF! | AT16: =(U16-MIN($U$2:$U$170))/(MAX($U$2:$U$170)-MIN($U$2:$U$170))*100 -> 0.21952979 | AU16: =(V16-MIN($V$2:$V$170))/(MAX($V$2:$V$170)-MIN($V$2:$V$170))*100 -> 0.12825136 | AV16: =(W16-MIN($W$2:$W$170))/(MAX($W$2:$W$170)-MIN($W$2:$W$170))*100 -> 0.031854546 | AW16: =(X16-MIN($X$2:$X$170))/(MAX($X$2:$X$170)-MIN($X$2:$X$170))*100 -> 0.27381391 | AX16: =(Y16-MIN($Y$2:$Y$170))/(MAX($Y$2:$Y$170)-MIN($Y$2:$Y$170))*100 -> 0.12995404 | AY16: =(Z16-MIN($Z$2:$Z$170))/(MAX($Z$2:$Z$170)-MIN($Z$2:$Z$170))*100 -> 0.43295671 | AZ16: =(AA16-MIN($AA$2:$AA$170))/(MAX($AA$2:$AA$170)-MIN($AA$2:$AA$170))*100 -> -0.0023553106 | BA16: =(AB16-MIN($AB$2:$AB$170))/(MAX($AB$2:$AB$170)-MIN($AB$2:$AB$170))*100 -> 0 | BB16: =(AC16-MIN($AC$2:$AC$170))/(MAX($AC$2:$AC$170)-MIN($AC$2:$AC$170))*100 -> -0.0010532589 | BC16: 0.1 | BD16: 4048 | BE16: 0 | BF16: 0
A17: AREQUIPA | B17: AREQUIPA | C17: SACHACA | D17: 040117 | E17: 153 | F17: 119.28382 | G17: 0.77963279 | H17: 40 | I17: 3280434.6 | J17: 82010.865 | K17: 39 | L17: 3276500 | M17: 84013 | N17: 0 | O17: 0 | P17: 380226.22 | Q17: 0.81 | R17: 6524783.7 | S17: 401910.62 | T17: =IF((100-IFERROR(S17/R17*100,0))=100,50,(100-IFERROR(S17/R17*100,0))) -> 93.840246 | U17: 2663 | V17: 6142905.3 | W17: 3171054.9 | X17: 1229 | Y17: 3319517 | Z17: 1962290 | AA17: 1634 | AB17: 89598.81 | AC17: 2961 | AD17: =(E17-MIN($E$2:$E$170))/(MAX($E$2:$E$170)-MIN($E$2:$E$170))*100 -> 1.0187926 | AE17: =(F17-MIN($F$2:$F$170))/(MAX($F$2:$F$170)-MIN($F$2:$F$170))*100 -> 1.0331305 | AF17: =(G17-MIN($G$2:$G$170))/(MAX($G$2:$G$170)-MIN($G$2:$G$170))*100 -> 37.607379 | AG17: =(H17-MIN($H$2:$H$170))/(MAX($H$2:$H$170)-MIN($H$2:$H$170))*100 -> 1.9550342 | AH17: =(I17-MIN($I$2:$I$170))/(MAX($I$2:$I$170)-MIN($I$2:$I$170))*100 -> 2.456078 | AI17: =(J17-MIN($J$2:$J$170))/(MAX($J$2:$J$170)-MIN($J$2:$J$170))*100 -> 41.694529 | AJ17: =(K17-MIN($K$2:$K$170))/(MAX($K$2:$K$170)-MIN($K$2:$K$170))*100 -> 1.9578313 | AK17: =(L17-MIN($L$2:$L$170))/(MAX($L$2:$L$170)-MIN($L$2:$L$170))*100 -> 2.530022 | AL17: =(M17-MIN($M$2:$M$170))/(MAX($M$2:$M$170)-MIN($M$2:$M$170))*100 -> 42.712321 | AM17: =(N17-MIN($N$2:$N$170))/(MAX($N$2:$N$170)-MIN($N$2:$N$170))*100 -> 0 | AN17: =(O17-MIN($O$2:$O$170))/(MAX($O$2:$O$170)-MIN($O$2:$O$170))*100 -> 0 | AO17: =(P17-MIN($P$2:$P$170))/(MAX($P$2:$P$170)-MIN($P$2:$P$170))*100 -> 1.5450384 | AP17: =(Q17-MIN($Q$2:$Q$170))/(MAX($Q$2:$Q$170)-MIN($Q$2:$Q$170))*100 -> 81 | AQ17: =IF(AP17>=50,AP17,50) -> 81 | AR17: =(#REF!-MIN(#REF!))/(MAX(#REF!)-MIN(#REF!))*100 -> #REF! | AS17: =IF(AR17>=50,AR17,50) -> #REF! | AT17: =(U17-MIN($U$2:$U$170))/(MAX($U$2:$U$170)-MIN($U$2:$U$170))*100 -> 2.7117156 | AU17: =(V17-MIN($V$2:$V$170))/(MAX($V$2:$V$170)-MIN($V$2:$V$170))*100 -> 1.0979314 | AV17: =(W17-MIN($W$2:$W$170))/(MAX($W$2:$W$170)-MIN($W$2:$W$170))*100 -> 0.30961593 | AW17: =(X17-MIN($X$2:$X$170))/(MAX($X$2:$X$170)-MIN($X$2:$X$170))*100 -> 3.1751882 | AX17: =(Y17-MIN($Y$2:$Y$170))/(MAX($Y$2:$Y$170)-MIN($Y$2:$Y$170))*100 -> 1.0131537 | AY17: =(Z17-MIN($Z$2:$Z$170))/(MAX($Z$2:$Z$170)-MIN($Z$2:$Z$170))*100 -> 2.6040003 | AZ17: =(AA17-MIN($AA$2:$AA$170))/(MAX($AA$2:$AA$170)-MIN($AA$2:$AA$170))*100 -> 0.065163593 | BA17: =(AB17-MIN($AB$2:$AB$170))/(MAX($AB$2:$AB$170)-MIN($AB$2:$AB$170))*100 -> 0.016249655 | BB17: =(AC17-MIN($AC$2:$AC$170))/(MAX($AC$2:$AC$170)-MIN($AC$2:$AC$170))*100 -> 0.046926736 | BC17: 0.8 | BD17: 37526 | BE17: 0 | BF17: 0
A18: AREQUIPA | B18: AREQUIPA | C18: SOCABAYA | D18: 040122 | E18: 366 | F18: 243.71614 | G18: 0.66589109 | H18: 63 | I18: 3511790.6 | J18: 55742.708 | K18: 60 | L18: 3346961 | M18: 55783 | N18: 73834.19 | O18: 8800.57 | P18: 1337724.9 | Q18: 0.94 | R18: 10977752 | S18: 5914.65 | T18: =IF((100-IFERROR(S18/R18*100,0))=100,50,(100-IFERROR(S18/R18*100,0))) -> 99.946121 | U18: 6277 | V18: 13124658 | W18: 874394.86 | X18: 2795 | Y18: 7596285 | Z18: 856008 | AA18: 57310 | AB18: 3713239.3 | AC18: 103585 | AD18: =(E18-MIN($E$2:$E$170))/(MAX($E$2:$E$170)-MIN($E$2:$E$170))*100 -> 2.4850279 | AE18: =(F18-MIN($F$2:$F$170))/(MAX($F$2:$F$170)-MIN($F$2:$F$170))*100 -> 2.1336403 | AF18: =(G18-MIN($G$2:$G$170))/(MAX($G$2:$G$170)-MIN($G$2:$G$170))*100 -> 27.584702 | AG18: =(H18-MIN($H$2:$H$170))/(MAX($H$2:$H$170)-MIN($H$2:$H$170))*100 -> 3.0791789 | AH18: =(I18-MIN($I$2:$I$170))/(MAX($I$2:$I$170)-MIN($I$2:$I$170))*100 -> 2.6292954 | AI18: =(J18-MIN($J$2:$J$170))/(MAX($J$2:$J$170)-MIN($J$2:$J$170))*100 -> 28.339732 | AJ18: =(K18-MIN($K$2:$K$170))/(MAX($K$2:$K$170)-MIN($K$2:$K$170))*100 -> 3.0120482 | AK18: =(L18-MIN($L$2:$L$170))/(MAX($L$2:$L$170)-MIN($L$2:$L$170))*100 -> 2.58443 | AL18: =(M18-MIN($M$2:$M$170))/(MAX($M$2:$M$170)-MIN($M$2:$M$170))*100 -> 28.360152 | AM18: =(N18-MIN($N$2:$N$170))/(MAX($N$2:$N$170)-MIN($N$2:$N$170))*100 -> 0.79062923 | AN18: =(O18-MIN($O$2:$O$170))/(MAX($O$2:$O$170)-MIN($O$2:$O$170))*100 -> 3.2601551 | AO18: =(P18-MIN($P$2:$P$170))/(MAX($P$2:$P$170)-MIN($P$2:$P$170))*100 -> 5.4358069 | AP18: =(Q18-MIN($Q$2:$Q$170))/(MAX($Q$2:$Q$170)-MIN($Q$2:$Q$170))*100 -> 94 | AQ18: =IF(AP18>=50,AP18,50) -> 94 | AR18: =(#REF!-MIN(#REF!))/(MAX(#REF!)-MIN(#REF!))*100 -> #REF! | AS18: =IF(AR18>=50,AR18,50) -> #REF! | AT18: =(U18-MIN($U$2:$U$170))/(MAX($U$2:$U$170)-MIN($U$2:$U$170))*100 -> 6.4897187 | AU18: =(V18-MIN($V$2:$V$170))/(MAX($V$2:$V$170)-MIN($V$2:$V$170))*100 -> 2.369743 | AV18: =(W18-MIN($W$2:$W$170))/(MAX($W$2:$W$170)-MIN($W$2:$W$170))*100 -> 0.085362343 | AW18: =(X18-MIN($X$2:$X$170))/(MAX($X$2:$X$170)-MIN($X$2:$X$170))*100 -> 7.2981939 | AX18: =(Y18-MIN($Y$2:$Y$170))/(MAX($Y$2:$Y$170)-MIN($Y$2:$Y$170))*100 -> 2.3428138 | AY18: =(Z18-MIN($Z$2:$Z$170))/(MAX($Z$2:$Z$170)-MIN($Z$2:$Z$170))*100 -> 1.1358143 | AZ18: =(AA18-MIN($AA$2:$AA$170))/(MAX($AA$2:$AA$170)-MIN($AA$2:$AA$170))*100 -> 2.3657649 | BA18: =(AB18-MIN($AB$2:$AB$170))/(MAX($AB$2:$AB$170)-MIN($AB$2:$AB$170))*100 -> 0.67343368 | BB18: =(AC18-MIN($AC$2:$AC$170))/(MAX($AC$2:$AC$170)-MIN($AC$2:$AC$170))*100 -> 1.6774364 | BC18: 2.7 | BD18: 122649 | BE18: 0 | BF18: 0
A19: AREQUIPA | B19: AREQUIPA | C19: TIABAYA | D19: 040123 | E19: 117 | F19: 68.296865 | G19: 0.58373389 | H19: 13 | I19: 1119553.8 | J19: 86119.52 | K19: 13 | L19: 1119554 | M19: 86120 | N19: 0 | O19: 0 | P19: 58658.6 | Q19: 0.91 | R19: 3243913.2 | S19: 70990.62 | T19: =IF((100-IFERROR(S19/R19*100,0))=100,50,(100-IFERROR(S19/R19*100,0))) -> 97.811575 | U19: 1222 | V19: 2607154.2 | W19: 358990.16 | X19: 516 | Y19: 1144894 | Z19: 308358 | AA19: 34916 | AB19: 2123049 | AC19: 67656 | AD19: =(E19-MIN($E$2:$E$170))/(MAX($E$2:$E$170)-MIN($E$2:$E$170))*100 -> 0.77097818 | AE19: =(F19-MIN($F$2:$F$170))/(MAX($F$2:$F$170)-MIN($F$2:$F$170))*100 -> 0.58218943 | AF19: =(G19-MIN($G$2:$G$170))/(MAX($G$2:$G$170)-MIN($G$2:$G$170))*100 -> 20.345183 | AG19: =(H19-MIN($H$2:$H$170))/(MAX($H$2:$H$170)-MIN($H$2:$H$170))*100 -> 0.63538612 | AH19: =(I19-MIN($I$2:$I$170))/(MAX($I$2:$I$170)-MIN($I$2:$I$170))*100 -> 0.83821556 | AI19: =(J19-MIN($J$2:$J$170))/(MAX($J$2:$J$170)-MIN($J$2:$J$170))*100 -> 43.78338 | AJ19: =(K19-MIN($K$2:$K$170))/(MAX($K$2:$K$170)-MIN($K$2:$K$170))*100 -> 0.65261044 | AK19: =(L19-MIN($L$2:$L$170))/(MAX($L$2:$L$170)-MIN($L$2:$L$170))*100 -> 0.86448839 | AL19: =(M19-MIN($M$2:$M$170))/(MAX($M$2:$M$170)-MIN($M$2:$M$170))*100 -> 43.783523 | AM19: =(N19-MIN($N$2:$N$170))/(MAX($N$2:$N$170)-MIN($N$2:$N$170))*100 -> 0 | AN19: =(O19-MIN($O$2:$O$170))/(MAX($O$2:$O$170)-MIN($O$2:$O$170))*100 -> 0 | AO19: =(P19-MIN($P$2:$P$170))/(MAX($P$2:$P$170)-MIN($P$2:$P$170))*100 -> 0.23835754 | AP19: =(Q19-MIN($Q$2:$Q$170))/(MAX($Q$2:$Q$170)-MIN($Q$2:$Q$170))*100 -> 91 | AQ19: =IF(AP19>=50,AP19,50) -> 91 | AR19: =(#REF!-MIN(#REF!))/(MAX(#REF!)-MIN(#REF!))*100 -> #REF! | AS19: =IF(AR19>=50,AR19,50) -> #REF! | AT19: =(U19-MIN($U$2:$U$170))/(MAX($U$2:$U$170)-MIN($U$2:$U$170))*100 -> 1.2053231 | AU19: =(V19-MIN($V$2:$V$170))/(MAX($V$2:$V$170)-MIN($V$2:$V$170))*100 -> 0.45385102 | AV19: =(W19-MIN($W$2:$W$170))/(MAX($W$2:$W$170)-MIN($W$2:$W$170))*100 -> 0.035036501 | AW19: =(X19-MIN($X$2:$X$170))/(MAX($X$2:$X$170)-MIN($X$2:$X$170))*100 -> 1.2979833 | AX19: =(Y19-MIN($Y$2:$Y$170))/(MAX($Y$2:$Y$170)-MIN($Y$2:$Y$170))*100 -> 0.33705681 | AY19: =(Z19-MIN($Z$2:$Z$170))/(MAX($Z$2:$Z$170)-MIN($Z$2:$Z$170))*100 -> 0.40900855 | AZ19: =(AA19-MIN($AA$2:$AA$170))/(MAX($AA$2:$AA$170)-MIN($AA$2:$AA$170))*100 -> 1.440417 | BA19: =(AB19-MIN($AB$2:$AB$170))/(MAX($AB$2:$AB$170)-MIN($AB$2:$AB$170))*100 -> 0.3850365 | BB19: =(AC19-MIN($AC$2:$AC$170))/(MAX($AC$2:$AC$170)-MIN($AC$2:$AC$170))*100 -> 1.0952435 | BC19: 0.5 | BD19: 21926 | BE19: 0 | BF19: 0
A20: AREQUIPA | B20: AREQUIPA | C20: UCHUMAYO | D20: 040124 | E20: 35 | F20: 20.288917 | G20: 0.57968335 | H20: 14 | I20: 1145137.6 | J20: 81795.539 | K20: 14 | L20: 1145138 | M20: 81796 | N20: 0 | O20: 0 | P20: 231296.68 | Q20: 1 | R20: 3769785 | S20: 0 | T20: =IF((100-IFERROR(S20/R20*100,0))=100,50,(100-IFERROR(S20/R20*100,0))) -> 50 | U20: 948 | V20: 1547649 | W20: 1313752.7 | X20: 424 | Y20: 736068 | Z20: 1313753 | AA20: 677 | AB20: 32585.99 | AC20: 947 | AD20: =(E20-MIN($E$2:$E$170))/(MAX($E$2:$E$170)-MIN($E$2:$E$170))*100 -> 0.20651201 | AE20: =(F20-MIN($F$2:$F$170))/(MAX($F$2:$F$170)-MIN($F$2:$F$170))*100 -> 0.15759543 | AF20: =(G20-MIN($G$2:$G$170))/(MAX($G$2:$G$170)-MIN($G$2:$G$170))*100 -> 19.988259 | AG20: =(H20-MIN($H$2:$H$170))/(MAX($H$2:$H$170)-MIN($H$2:$H$170))*100 -> 0.68426197 | AH20: =(I20-MIN($I$2:$I$170))/(MAX($I$2:$I$170)-MIN($I$2:$I$170))*100 -> 0.85737028 | AI20: =(J20-MIN($J$2:$J$170))/(MAX($J$2:$J$170)-MIN($J$2:$J$170))*100 -> 41.585057 | AJ20: =(K20-MIN($K$2:$K$170))/(MAX($K$2:$K$170)-MIN($K$2:$K$170))*100 -> 0.70281124 | AK20: =(L20-MIN($L$2:$L$170))/(MAX($L$2:$L$170)-MIN($L$2:$L$170))*100 -> 0.88424364 | AL20: =(M20-MIN($M$2:$M$170))/(MAX($M$2:$M$170)-MIN($M$2:$M$170))*100 -> 41.585195 | AM20: =(N20-MIN($N$2:$N$170))/(MAX($N$2:$N$170)-MIN($N$2:$N$170))*100 -> 0 | AN20: =(O20-MIN($O$2:$O$170))/(MAX($O$2:$O$170)-MIN($O$2:$O$170))*100 -> 0 | AO20: =(P20-MIN($P$2:$P$170))/(MAX($P$2:$P$170)-MIN($P$2:$P$170))*100 -> 0.93986744 | AP20: =(Q20-MIN($Q$2:$Q$170))/(MAX($Q$2:$Q$170)-MIN($Q$2:$Q$170))*100 -> 100 | AQ20: =IF(AP20>=50,AP20,50) -> 100 | AR20: =(#REF!-MIN(#REF!))/(MAX(#REF!)-MIN(#REF!))*100 -> #REF! | AS20: =IF(AR20>=50,AR20,50) -> #REF! | AT20: =(U20-MIN($U$2:$U$170))/(MAX($U$2:$U$170)-MIN($U$2:$U$170))*100 -> 0.91888897 | AU20: =(V20-MIN($V$2:$V$170))/(MAX($V$2:$V$170)-MIN($V$2:$V$170))*100 -> 0.26084919 | AV20: =(W20-MIN($W$2:$W$170))/(MAX($W$2:$W$170)-MIN($W$2:$W$170))*100 -> 0.12826272 | AW20: =(X20-MIN($X$2:$X$170))/(MAX($X$2:$X$170)-MIN($X$2:$X$170))*100 -> 1.0557633 | AX20: =(Y20-MIN($Y$2:$Y$170))/(MAX($Y$2:$Y$170)-MIN($Y$2:$Y$170))*100 -> 0.20995157 | AY20: =(Z20-MIN($Z$2:$Z$170))/(MAX($Z$2:$Z$170)-MIN($Z$2:$Z$170))*100 -> 1.7433039 | AZ20: =(AA20-MIN($AA$2:$AA$170))/(MAX($AA$2:$AA$170)-MIN($AA$2:$AA$170))*100 -> 0.025619168 | BA20: =(AB20-MIN($AB$2:$AB$170))/(MAX($AB$2:$AB$170)-MIN($AB$2:$AB$170))*100 -> 0.0059098004 | BB20: =(AC20-MIN($AC$2:$AC$170))/(MAX($AC$2:$AC$170)-MIN($AC$2:$AC$170))*100 -> 0.014291913 | BC20: 0.3 | BD20: 11317 | BE20: 0 | BF20: 0
A21: AREQUIPA | B21: AREQUIPA | C21: YANAHUARA | D21: 040126 | E21: 540 | F21: 526.65252 | G21: 0.97528245 | H21: 103 | I21: 6996463.5 | J21: 67926.83 | K21: 100 | L21: 6674460 | M21: 66745 | N21: 86104.79 | O21: 3712.03 | P21: 1189167.1 | Q21: 0.86 | R21: 18073682 | S21: 630954.67 | T21: =IF((100-IFERROR(S21/R21*100,0))=100,50,(100-IFERROR(S21/R21*100,0))) -> 96.508987 | U21: 4571 | V21: 15138855 | W21: 10835648 | X21: 2061 | Y21: 8480263 | Z21: 6271257 | AA21: 155905 | AB21: 10686501 | AC21: 241231 | AD21: =(E21-MIN($E$2:$E$170))/(MAX($E$2:$E$170)-MIN($E$2:$E$170))*100 -> 3.6827975 | AE21: =(F21-MIN($F$2:$F$170))/(MAX($F$2:$F$170)-MIN($F$2:$F$170))*100 -> 4.6359987 | AF21: =(G21-MIN($G$2:$G$170))/(MAX($G$2:$G$170)-MIN($G$2:$G$170))*100 -> 54.847612 | AG21: =(H21-MIN($H$2:$H$170))/(MAX($H$2:$H$170)-MIN($H$2:$H$170))*100 -> 5.0342131 | AH21: =(I21-MIN($I$2:$I$170))/(MAX($I$2:$I$170)-MIN($I$2:$I$170))*100 -> 5.2382876 | AI21: =(J21-MIN($J$2:$J$170))/(MAX($J$2:$J$170)-MIN($J$2:$J$170))*100 -> 34.534171 | AJ21: =(K21-MIN($K$2:$K$170))/(MAX($K$2:$K$170)-MIN($K$2:$K$170))*100 -> 5.0200803 | AK21: =(L21-MIN($L$2:$L$170))/(MAX($L$2:$L$170)-MIN($L$2:$L$170))*100 -> 5.1538319 | AL21: =(M21-MIN($M$2:$M$170))/(MAX($M$2:$M$170)-MIN($M$2:$M$170))*100 -> 33.933247 | AM21: =(N21-MIN($N$2:$N$170))/(MAX($N$2:$N$170)-MIN($N$2:$N$170))*100 -> 0.92202492 | AN21: =(O21-MIN($O$2:$O$170))/(MAX($O$2:$O$170)-MIN($O$2:$O$170))*100 -> 1.3751148 | AO21: =(P21-MIN($P$2:$P$170))/(MAX($P$2:$P$170)-MIN($P$2:$P$170))*100 -> 4.8321464 | AP21: =(Q21-MIN($Q$2:$Q$170))/(MAX($Q$2:$Q$170)-MIN($Q$2:$Q$170))*100 -> 86 | AQ21: =IF(AP21>=50,AP21,50) -> 86 | AR21: =(#REF!-MIN(#REF!))/(MAX(#REF!)-MIN(#REF!))*100 -> #REF! | AS21: =IF(AR21>=50,AR21,50) -> #REF! | AT21: =(U21-MIN($U$2:$U$170))/(MAX($U$2:$U$170)-MIN($U$2:$U$170))*100 -> 4.7063005 | AU21: =(V21-MIN($V$2:$V$170))/(MAX($V$2:$V$170)-MIN($V$2:$V$170))*100 -> 2.7366537 | AV21: =(W21-MIN($W$2:$W$170))/(MAX($W$2:$W$170)-MIN($W$2:$W$170))*100 -> 1.0580125 | AW21: =(X21-MIN($X$2:$X$170))/(MAX($X$2:$X$170)-MIN($X$2:$X$170))*100 -> 5.3656995 | AX21: =(Y21-MIN($Y$2:$Y$170))/(MAX($Y$2:$Y$170)-MIN($Y$2:$Y$170))*100 -> 2.6176452 | AY21: =(Z21-MIN($Z$2:$Z$170))/(MAX($Z$2:$Z$170)-MIN($Z$2:$Z$170))*100 -> 8.3225832 | AZ21: =(AA21-MIN($AA$2:$AA$170))/(MAX($AA$2:$AA$170)-MIN($AA$2:$AA$170))*100 -> 6.4398324 | BA21: =(AB21-MIN($AB$2:$AB$170))/(MAX($AB$2:$AB$170)-MIN($AB$2:$AB$170))*100 -> 1.9381056 | BB21: =(AC21-MIN($AC$2:$AC$170))/(MAX($AC$2:$AC$170)-MIN($AC$2:$AC$170))*100 -> 3.9078499 | BC21: 1.5 | BD21: 82122 | BE21: 1 | BF21: 0.1
A22: AREQUIPA | B22: AREQUIPA | C22: YURA | D22: 040128 | E22: 160 | F22: 80.378337 | G22: 0.50236461 | H22: 8 | I22: 289715.5 | J22: 36214.437 | K22: 8 | L22: 289715 | M22: 36214 | N22: 91229.74 | O22: 14771.92 | P22: 70700 | Q22: 1 | R22: 916051.03 | S22: 0 | T22: =IF((100-IFERROR(S22/R22*100,0))=100,50,(100-IFERROR(S22/R22*100,0))) -> 50 | U22: 1651 | V22: 1452392.9 | W22: 398222.86 | X22: 824 | Y22: 1022165 | Z22: 397602 | AA22: 24643 | AB22: 1227631.7 | AC22: 39979 | AD22: =(E22-MIN($E$2:$E$170))/(MAX($E$2:$E$170)-MIN($E$2:$E$170))*100 -> 1.0669787 | AE22: =(F22-MIN($F$2:$F$170))/(MAX($F$2:$F$170)-MIN($F$2:$F$170))*100 -> 0.68904092 | AF22: =(G22-MIN($G$2:$G$170))/(MAX($G$2:$G$170)-MIN($G$2:$G$170))*100 -> 13.175095 | AG22: =(H22-MIN($H$2:$H$170))/(MAX($H$2:$H$170)-MIN($H$2:$H$170))*100 -> 0.39100684 | AH22: =(I22-MIN($I$2:$I$170))/(MAX($I$2:$I$170)-MIN($I$2:$I$170))*100 -> 0.21691146 | AI22: =(J22-MIN($J$2:$J$170))/(MAX($J$2:$J$170)-MIN($J$2:$J$170))*100 -> 18.411511 | AJ22: =(K22-MIN($K$2:$K$170))/(MAX($K$2:$K$170)-MIN($K$2:$K$170))*100 -> 0.40160643 | AK22: =(L22-MIN($L$2:$L$170))/(MAX($L$2:$L$170)-MIN($L$2:$L$170))*100 -> 0.22370985 | AL22: =(M22-MIN($M$2:$M$170))/(MAX($M$2:$M$170)-MIN($M$2:$M$170))*100 -> 18.411246 | AM22: =(N22-MIN($N$2:$N$170))/(MAX($N$2:$N$170)-MIN($N$2:$N$170))*100 -> 0.97690377 | AN22: =(O22-MIN($O$2:$O$170))/(MAX($O$2:$O$170)-MIN($O$2:$O$170))*100 -> 5.4722309 | AO22: =(P22-MIN($P$2:$P$170))/(MAX($P$2:$P$170)-MIN($P$2:$P$170))*100 -> 0.28728743 | AP22: =(Q22-MIN($Q$2:$Q$170))/(MAX($Q$2:$Q$170)-MIN($Q$2:$Q$170))*100 -> 100 | AQ22: =IF(AP22>=50,AP22,50) -> 100 | AR22: =(#REF!-MIN(#REF!))/(MAX(#REF!)-MIN(#REF!))*100 -> #REF! | AS22: =IF(AR22>=50,AR22,50) -> #REF! | AT22: =(U22-MIN($U$2:$U$170))/(MAX($U$2:$U$170)-MIN($U$2:$U$170))*100 -> 1.6537911 | AU22: =(V22-MIN($V$2:$V$170))/(MAX($V$2:$V$170)-MIN($V$2:$V$170))*100 -> 0.24349711 | AV22: =(W22-MIN($W$2:$W$170))/(MAX($W$2:$W$170)-MIN($W$2:$W$170))*100 -> 0.038867314 | AW22: =(X22-MIN($X$2:$X$170))/(MAX($X$2:$X$170)-MIN($X$2:$X$170))*100 -> 2.1088937 | AX22: =(Y22-MIN($Y$2:$Y$170))/(MAX($Y$2:$Y$170)-MIN($Y$2:$Y$170))*100 -> 0.29889999 | AY22: =(Z22-MIN($Z$2:$Z$170))/(MAX($Z$2:$Z$170)-MIN($Z$2:$Z$170))*100 -> 0.52744742 | AZ22: =(AA22-MIN($AA$2:$AA$170))/(MAX($AA$2:$AA$170)-MIN($AA$2:$AA$170))*100 -> 1.015924 | BA22: =(AB22-MIN($AB$2:$AB$170))/(MAX($AB$2:$AB$170)-MIN($AB$2:$AB$170))*100 -> 0.22264348 | BB22: =(AC22-MIN($AC$2:$AC$170))/(MAX($AC$2:$AC$170)-MIN($AC$2:$AC$170))*100 -> 0.6467658 | BC22: 0.3 | BD22: 14601 | BE22: 0 | BF22: 0
A23: AREQUIPA | B23: AREQUIPA | C23: JOSE LUIS BUSTAMANTE Y RIVERO | D23: 040129 | E23: 2305 | F23: 1297.4547 | G23: 0.56288709 | H23: 216 | I23: 11694720 | J23: 54142.22 | K23: 209 | L23: 11583511 | M23: 55423 | N23: 622437.57 | O23: 60019.38 | P23: 2105445.6 | Q23: 0.89 | R23: 42007659 | S23: 2045215.6 | T23: =IF((100-IFERROR(S23/R23*100,0))=100,50,(100-IFERROR(S23/R23*100,0))) -> 95.131327 | U23: 12464 | V23: 37167020 | W23: 7565585 | X23: 5478 | Y23: 23551002 | Z23: 7242350 | AA23: 439680 | AB23: 1.1607417e+08 | AC23: 779387 | AD23: =(E23-MIN($E$2:$E$170))/(MAX($E$2:$E$170)-MIN($E$2:$E$170))*100 -> 15.832588 | AE23: =(F23-MIN($F$2:$F$170))/(MAX($F$2:$F$170)-MIN($F$2:$F$170))*100 -> 11.453162 | AF23: =(G23-MIN($G$2:$G$170))/(MAX($G$2:$G$170)-MIN($G$2:$G$170))*100 -> 18.508208 | AG23: =(H23-MIN($H$2:$H$170))/(MAX($H$2:$H$170)-MIN($H$2:$H$170))*100 -> 10.557185 | AH23: =(I23-MIN($I$2:$I$170))/(MAX($I$2:$I$170)-MIN($I$2:$I$170))*100 -> 8.7558957 | AI23: =(J23-MIN($J$2:$J$170))/(MAX($J$2:$J$170)-MIN($J$2:$J$170))*100 -> 27.52604 | AJ23: =(K23-MIN($K$2:$K$170))/(MAX($K$2:$K$170)-MIN($K$2:$K$170))*100 -> 10.491968 | AK23: =(L23-MIN($L$2:$L$170))/(MAX($L$2:$L$170)-MIN($L$2:$L$170))*100 -> 8.9444643 | AL23: =(M23-MIN($M$2:$M$170))/(MAX($M$2:$M$170)-MIN($M$2:$M$170))*100 -> 28.177127 | AM23: =(N23-MIN($N$2:$N$170))/(MAX($N$2:$N$170)-MIN($N$2:$N$170))*100 -> 6.6651687 | AN23: =(O23-MIN($O$2:$O$170))/(MAX($O$2:$O$170)-MIN($O$2:$O$170))*100 -> 22.23407 | AO23: =(P23-MIN($P$2:$P$170))/(MAX($P$2:$P$170)-MIN($P$2:$P$170))*100 -> 8.5554178 | AP23: =(Q23-MIN($Q$2:$Q$170))/(MAX($Q$2:$Q$170)-MIN($Q$2:$Q$170))*100 -> 89 | AQ23: =IF(AP23>=50,AP23,50) -> 89 | AR23: =(#REF!-MIN(#REF!))/(MAX(#REF!)-MIN(#REF!))*100 -> #REF! | AS23: =IF(AR23>=50,AR23,50) -> #REF! | AT23: =(U23-MIN($U$2:$U$170))/(MAX($U$2:$U$170)-MIN($U$2:$U$170))*100 -> 12.957484 | AU23: =(V23-MIN($V$2:$V$170))/(MAX($V$2:$V$170)-MIN($V$2:$V$170))*100 -> 6.7493534 | AV23: =(W23-MIN($W$2:$W$170))/(MAX($W$2:$W$170)-MIN($W$2:$W$170))*100 -> 0.73871258 | AW23: =(X23-MIN($X$2:$X$170))/(MAX($X$2:$X$170)-MIN($X$2:$X$170))*100 -> 14.362066 | AX23: =(Y23-MIN($Y$2:$Y$170))/(MAX($Y$2:$Y$170)-MIN($Y$2:$Y$170))*100 -> 7.3031835 | AY23: =(Z23-MIN($Z$2:$Z$170))/(MAX($Z$2:$Z$170)-MIN($Z$2:$Z$170))*100 -> 9.6113552 | AZ23: =(AA23-MIN($AA$2:$AA$170))/(MAX($AA$2:$AA$170)-MIN($AA$2:$AA$170))*100 -> 18.165767 | BA23: =(AB23-MIN($AB$2:$AB$170))/(MAX($AB$2:$AB$170)-MIN($AB$2:$AB$170))*100 -> 21.051231 | BB23: =(AC23-MIN($AC$2:$AC$170))/(MAX($AC$2:$AC$170)-MIN($AC$2:$AC$170))*100 -> 12.628121 | BC23: 3.7 | BD23: 182840 | BE23: 3 | BF23: 0.4
A24: AYACUCHO | B24: HUAMANGA | C24: AYACUCHO | D24: 050101 | E24: 2140 | F24: 1360.3427 | G24: 0.63567418 | H24: 236 | I24: 11763274 | J24: 49844.383 | K24: 227 | L24: 11585530 | M24: 51038 | N24: 647041.92 | O24: 82349.51 | P24: 4768490.7 | Q24: 0.87 | R24: 39208717 | S24: 432563.02 | T24: =IF((100-IFERROR(S24/R24*100,0))=100,50,(100-IFERROR(S24/R24*100,0))) -> 98.896768 | U24: 14320 | V24: 77312334 | W24: 4975492.1 | X24: 5159 | Y24: 40131532 | Z24: 2837267 | AA24: 361201 | AB24: 24550023 | AC24: 659005 | AD24: =(E24-MIN($E$2:$E$170))/(MAX($E$2:$E$170)-MIN($E$2:$E$170))*100 -> 14.696772 | AE24: =(F24-MIN($F$2:$F$170))/(MAX($F$2:$F$170)-MIN($F$2:$F$170))*100 -> 12.009358 | AF24: =(G24-MIN($G$2:$G$170))/(MAX($G$2:$G$170)-MIN($G$2:$G$170))*100 -> 24.922052 | AG24: =(H24-MIN($H$2:$H$170))/(MAX($H$2:$H$170)-MIN($H$2:$H$170))*100 -> 11.534702 | AH24: =(I24-MIN($I$2:$I$170))/(MAX($I$2:$I$170)-MIN($I$2:$I$170))*100 -> 8.807223 | AI24: =(J24-MIN($J$2:$J$170))/(MAX($J$2:$J$170)-MIN($J$2:$J$170))*100 -> 25.341009 | AJ24: =(K24-MIN($K$2:$K$170))/(MAX($K$2:$K$170)-MIN($K$2:$K$170))*100 -> 11.395582 | AK24: =(L24-MIN($L$2:$L$170))/(MAX($L$2:$L$170)-MIN($L$2:$L$170))*100 -> 8.9460233 | AL24: =(M24-MIN($M$2:$M$170))/(MAX($M$2:$M$170)-MIN($M$2:$M$170))*100 -> 25.947787 | AM24: =(N24-MIN($N$2:$N$170))/(MAX($N$2:$N$170)-MIN($N$2:$N$170))*100 -> 6.9286363 | AN24: =(O24-MIN($O$2:$O$170))/(MAX($O$2:$O$170)-MIN($O$2:$O$170))*100 -> 30.506226 | AO24: =(P24-MIN($P$2:$P$170))/(MAX($P$2:$P$170)-MIN($P$2:$P$170))*100 -> 19.376626 | AP24: =(Q24-MIN($Q$2:$Q$170))/(MAX($Q$2:$Q$170)-MIN($Q$2:$Q$170))*100 -> 87 | AQ24: =IF(AP24>=50,AP24,50) -> 87 | AR24: =(#REF!-MIN(#REF!))/(MAX(#REF!)-MIN(#REF!))*100 -> #REF! | AS24: =IF(AR24>=50,AR24,50) -> #REF! | AT24: =(U24-MIN($U$2:$U$170))/(MAX($U$2:$U$170)-MIN($U$2:$U$170))*100 -> 14.89771 | AU24: =(V24-MIN($V$2:$V$170))/(MAX($V$2:$V$170)-MIN($V$2:$V$170))*100 -> 14.062314 | AV24: =(W24-MIN($W$2:$W$170))/(MAX($W$2:$W$170)-MIN($W$2:$W$170))*100 -> 0.48580723 | AW24: =(X24-MIN($X$2:$X$170))/(MAX($X$2:$X$170)-MIN($X$2:$X$170))*100 -> 13.522195 | AX24: =(Y24-MIN($Y$2:$Y$170))/(MAX($Y$2:$Y$170)-MIN($Y$2:$Y$170))*100 -> 12.45812 | AY24: =(Z24-MIN($Z$2:$Z$170))/(MAX($Z$2:$Z$170)-MIN($Z$2:$Z$170))*100 -> 3.7652133 | AZ24: =(AA24-MIN($AA$2:$AA$170))/(MAX($AA$2:$AA$170)-MIN($AA$2:$AA$170))*100 -> 14.922917 | BA24: =(AB24-MIN($AB$2:$AB$170))/(MAX($AB$2:$AB$170)-MIN($AB$2:$AB$170))*100 -> 4.4523961 | BB24: =(AC24-MIN($AC$2:$AC$170))/(MAX($AC$2:$AC$170)-MIN($AC$2:$AC$170))*100 -> 10.677453 | BC24: 5.1 | BD24: 231893 | BE24: 3 | BF24: 1.1
A25: AYACUCHO | B25: HUAMANGA | C25: CARMEN ALTO | D25: 050104 | E25: 77 | F25: 52.828336 | G25: 0.68608229 | H25: 3 | I25: 51930.834 | J25: 17310.278 | K25: 3 | L25: 51931 | M25: 17310 | N25: 0 | O25: 0 | P25: 0 | Q25: 1 | R25: 284033.45 | S25: 0 | T25: =IF((100-IFERROR(S25/R25*100,0))=100,50,(100-IFERROR(S25/R25*100,0))) -> 50 | U25: 1453 | V25: 6590900.5 | W25: 360230.83 | X25: 534 | Y25: 3198826 | Z25: 360231 | AA25: 20117 | AB25: 819244.64 | AC25: 33340 | AD25: =(E25-MIN($E$2:$E$170))/(MAX($E$2:$E$170)-MIN($E$2:$E$170))*100 -> 0.49562883 | AE25: =(F25-MIN($F$2:$F$170))/(MAX($F$2:$F$170)-MIN($F$2:$F$170))*100 -> 0.44538199 | AF25: =(G25-MIN($G$2:$G$170))/(MAX($G$2:$G$170)-MIN($G$2:$G$170))*100 -> 29.363908 | AG25: =(H25-MIN($H$2:$H$170))/(MAX($H$2:$H$170)-MIN($H$2:$H$170))*100 -> 0.14662757 | AH25: =(I25-MIN($I$2:$I$170))/(MAX($I$2:$I$170)-MIN($I$2:$I$170))*100 -> 0.038880878 | AI25: =(J25-MIN($J$2:$J$170))/(MAX($J$2:$J$170)-MIN($J$2:$J$170))*100 -> 8.8005887 | AJ25: =(K25-MIN($K$2:$K$170))/(MAX($K$2:$K$170)-MIN($K$2:$K$170))*100 -> 0.15060241 | AK25: =(L25-MIN($L$2:$L$170))/(MAX($L$2:$L$170)-MIN($L$2:$L$170))*100 -> 0.04009967 | AL25: =(M25-MIN($M$2:$M$170))/(MAX($M$2:$M$170)-MIN($M$2:$M$170))*100 -> 8.8004271 | AM25: =(N25-MIN($N$2:$N$170))/(MAX($N$2:$N$170)-MIN($N$2:$N$170))*100 -> 0 | AN25: =(O25-MIN($O$2:$O$170))/(MAX($O$2:$O$170)-MIN($O$2:$O$170))*100 -> 0 | AO25: =(P25-MIN($P$2:$P$170))/(MAX($P$2:$P$170)-MIN($P$2:$P$170))*100 -> 0 | AP25: =(Q25-MIN($Q$2:$Q$170))/(MAX($Q$2:$Q$170)-MIN($Q$2:$Q$170))*100 -> 100 | AQ25: =IF(AP25>=50,AP25,50) -> 100 | AR25: =(#REF!-MIN(#REF!))/(MAX(#REF!)-MIN(#REF!))*100 -> #REF! | AS25: =IF(AR25>=50,AR25,50) -> #REF! | AT25: =(U25-MIN($U$2:$U$170))/(MAX($U$2:$U$170)-MIN($U$2:$U$170))*100 -> 1.4468058 | AU25: =(V25-MIN($V$2:$V$170))/(MAX($V$2:$V$170)-MIN($V$2:$V$170))*100 -> 1.1795392 | AV25: =(W25-MIN($W$2:$W$170))/(MAX($W$2:$W$170)-MIN($W$2:$W$170))*100 -> 0.035157644 | AW25: =(X25-MIN($X$2:$X$170))/(MAX($X$2:$X$170)-MIN($X$2:$X$170))*100 -> 1.3453741 | AX25: =(Y25-MIN($Y$2:$Y$170))/(MAX($Y$2:$Y$170)-MIN($Y$2:$Y$170))*100 -> 0.97563048 | AY25: =(Z25-MIN($Z$2:$Z$170))/(MAX($Z$2:$Z$170)-MIN($Z$2:$Z$170))*100 -> 0.47785104 | AZ25: =(AA25-MIN($AA$2:$AA$170))/(MAX($AA$2:$AA$170)-MIN($AA$2:$AA$170))*100 -> 0.82890404 | BA25: =(AB25-MIN($AB$2:$AB$170))/(MAX($AB$2:$AB$170)-MIN($AB$2:$AB$170))*100 -> 0.14857834 | BB25: =(AC25-MIN($AC$2:$AC$170))/(MAX($AC$2:$AC$170)-MIN($AC$2:$AC$170))*100 -> 0.53918755 | BC25: 0.5 | BD25: 20476 | BE25: 0 | BF25: 0
A26: AYACUCHO | B26: HUAMANGA | C26: JESUS NAZARENO | D26: 050115 | E26: 266 | F26: 194.58143 | G26: 0.73150915 | H26: 9 | I26: 614797.6 | J26: 68310.844 | K26: 8 | L26: 607012 | M26: 75876 | N26: 0 | O26: 0 | P26: 0 | Q26: 0.83 | R26: 905430.91 | S26: 47675.37 | T26: =IF((100-IFERROR(S26/R26*100,0))=100,50,(100-IFERROR(S26/R26*100,0))) -> 94.73451 | U26: 1749 | V26: 6252753.8 | W26: 507072.45 | X26: 638 | Y26: 2944267 | Z26: 455779 | AA26: 14438 | AB26: 694768.44 | AC26: 20401 | AD26: =(E26-MIN($E$2:$E$170))/(MAX($E$2:$E$170)-MIN($E$2:$E$170))*100 -> 1.7966545 | AE26: =(F26-MIN($F$2:$F$170))/(MAX($F$2:$F$170)-MIN($F$2:$F$170))*100 -> 1.699081 | AF26: =(G26-MIN($G$2:$G$170))/(MAX($G$2:$G$170)-MIN($G$2:$G$170))*100 -> 33.366826 | AG26: =(H26-MIN($H$2:$H$170))/(MAX($H$2:$H$170)-MIN($H$2:$H$170))*100 -> 0.4398827 | AH26: =(I26-MIN($I$2:$I$170))/(MAX($I$2:$I$170)-MIN($I$2:$I$170))*100 -> 0.46030207 | AI26: =(J26-MIN($J$2:$J$170))/(MAX($J$2:$J$170)-MIN($J$2:$J$170))*100 -> 34.729404 | AJ26: =(K26-MIN($K$2:$K$170))/(MAX($K$2:$K$170)-MIN($K$2:$K$170))*100 -> 0.40160643 | AK26: =(L26-MIN($L$2:$L$170))/(MAX($L$2:$L$170)-MIN($L$2:$L$170))*100 -> 0.46871774 | AL26: =(M26-MIN($M$2:$M$170))/(MAX($M$2:$M$170)-MIN($M$2:$M$170))*100 -> 38.575459 | AM26: =(N26-MIN($N$2:$N$170))/(MAX($N$2:$N$170)-MIN($N$2:$N$170))*100 -> 0 | AN26: =(O26-MIN($O$2:$O$170))/(MAX($O$2:$O$170)-MIN($O$2:$O$170))*100 -> 0 | AO26: =(P26-MIN($P$2:$P$170))/(MAX($P$2:$P$170)-MIN($P$2:$P$170))*100 -> 0 | AP26: =(Q26-MIN($Q$2:$Q$170))/(MAX($Q$2:$Q$170)-MIN($Q$2:$Q$170))*100 -> 83 | AQ26: =IF(AP26>=50,AP26,50) -> 83 | AR26: =(#REF!-MIN(#REF!))/(MAX(#REF!)-MIN(#REF!))*100 -> #REF! | AS26: =IF(AR26>=50,AR26,50) -> #REF! | AT26: =(U26-MIN($U$2:$U$170))/(MAX($U$2:$U$170)-MIN($U$2:$U$170))*100 -> 1.7562383 | AU26: =(V26-MIN($V$2:$V$170))/(MAX($V$2:$V$170)-MIN($V$2:$V$170))*100 -> 1.1179416 | AV26: =(W26-MIN($W$2:$W$170))/(MAX($W$2:$W$170)-MIN($W$2:$W$170))*100 -> 0.049495752 | AW26: =(X26-MIN($X$2:$X$170))/(MAX($X$2:$X$170)-MIN($X$2:$X$170))*100 -> 1.619188 | AX26: =(Y26-MIN($Y$2:$Y$170))/(MAX($Y$2:$Y$170)-MIN($Y$2:$Y$170))*100 -> 0.89648731 | AY26: =(Z26-MIN($Z$2:$Z$170))/(MAX($Z$2:$Z$170)-MIN($Z$2:$Z$170))*100 -> 0.60465618 | AZ26: =(AA26-MIN($AA$2:$AA$170))/(MAX($AA$2:$AA$170)-MIN($AA$2:$AA$170))*100 -> 0.59424073 | BA26: =(AB26-MIN($AB$2:$AB$170))/(MAX($AB$2:$AB$170)-MIN($AB$2:$AB$170))*100 -> 0.12600332 | BB26: =(AC26-MIN($AC$2:$AC$170))/(MAX($AC$2:$AC$170)-MIN($AC$2:$AC$170))*100 -> 0.32952421 | BC26: 0.6 | BD26: 29852 | BE26: 0 | BF26: 0
A27: AYACUCHO | B27: HUAMANGA | C27: ANDRÉS AVELINO CÁCERES DORREGARAY | D27: 050116 | E27: 215 | F27: 132.9276 | G27: 0.61826789 | H27: 9 | I27: 610930.28 | J27: 67881.142 | K27: 8 | L27: 217775 | M27: 27222 | N27: 0 | O27: 0 | P27: 150000 | Q27: 0.67 | R27: 699284.87 | S27: 220302.37 | T27: =IF((100-IFERROR(S27/R27*100,0))=100,50,(100-IFERROR(S27/R27*100,0))) -> 68.496048 | U27: 1376 | V27: 4876608.5 | W27: 221895.96 | X27: 626 | Y27: 2754501 | Z27: 213671 | AD27: =(E27-MIN($E$2:$E$170))/(MAX($E$2:$E$170)-MIN($E$2:$E$170))*100 -> 1.4455841 | AE27: =(F27-MIN($F$2:$F$170))/(MAX($F$2:$F$170)-MIN($F$2:$F$170))*100 -> 1.1537994 | AF27: =(G27-MIN($G$2:$G$170))/(MAX($G$2:$G$170)-MIN($G$2:$G$170))*100 -> 23.388246 | AG27: =(H27-MIN($H$2:$H$170))/(MAX($H$2:$H$170)-MIN($H$2:$H$170))*100 -> 0.4398827 | AH27: =(I27-MIN($I$2:$I$170))/(MAX($I$2:$I$170)-MIN($I$2:$I$170))*100 -> 0.45740659 | AI27: =(J27-MIN($J$2:$J$170))/(MAX($J$2:$J$170)-MIN($J$2:$J$170))*100 -> 34.510943 | AJ27: =(K27-MIN($K$2:$K$170))/(MAX($K$2:$K$170)-MIN($K$2:$K$170))*100 -> 0.40160643 | AK27: =(L27-MIN($L$2:$L$170))/(MAX($L$2:$L$170)-MIN($L$2:$L$170))*100 -> 0.16815978 | AL27: =(M27-MIN($M$2:$M$170))/(MAX($M$2:$M$170)-MIN($M$2:$M$170))*100 -> 13.839701 | AM27: =(N27-MIN($N$2:$N$170))/(MAX($N$2:$N$170)-MIN($N$2:$N$170))*100 -> 0 | AN27: =(O27-MIN($O$2:$O$170))/(MAX($O$2:$O$170)-MIN($O$2:$O$170))*100 -> 0 | AO27: =(P27-MIN($P$2:$P$170))/(MAX($P$2:$P$170)-MIN($P$2:$P$170))*100 -> 0.60952071 | AP27: =(Q27-MIN($Q$2:$Q$170))/(MAX($Q$2:$Q$170)-MIN($Q$2:$Q$170))*100 -> 67 | AQ27: =IF(AP27>=50,AP27,50) -> 67 | AR27: =(#REF!-MIN(#REF!))/(MAX(#REF!)-MIN(#REF!))*100 -> #REF! | AS27: =IF(AR27>=50,AR27,50) -> #REF! | AT27: =(U27-MIN($U$2:$U$170))/(MAX($U$2:$U$170)-MIN($U$2:$U$170))*100 -> 1.3663116 | AU27: =(V27-MIN($V$2:$V$170))/(MAX($V$2:$V$170)-MIN($V$2:$V$170))*100 -> 0.86725989 | AV27: =(W27-MIN($W$2:$W$170))/(MAX($W$2:$W$170)-MIN($W$2:$W$170))*100 -> 0.021650164 | AW27: =(X27-MIN($X$2:$X$170))/(MAX($X$2:$X$170)-MIN($X$2:$X$170))*100 -> 1.5875941 | AX27: =(Y27-MIN($Y$2:$Y$170))/(MAX($Y$2:$Y$170)-MIN($Y$2:$Y$170))*100 -> 0.83748849 | AY27: =(Z27-MIN($Z$2:$Z$170))/(MAX($Z$2:$Z$170)-MIN($Z$2:$Z$170))*100 -> 0.28334607 | AZ27: =(AA27-MIN($AA$2:$AA$170))/(MAX($AA$2:$AA$170)-MIN($AA$2:$AA$170))*100 -> -0.0023553106 | BA27: =(AB27-MIN($AB$2:$AB$170))/(MAX($AB$2:$AB$170)-MIN($AB$2:$AB$170))*100 -> 0 | BB27: =(AC27-MIN($AC$2:$AC$170))/(MAX($AC$2:$AC$170)-MIN($AC$2:$AC$170))*100 -> -0.0010532589 | BC27: 0.6 | BD27: 28433 | BE27: 0 | BF27: 0
A28: CAJAMARCA | B28: CAJAMARCA | C28: CAJAMARCA | D28: 060101 | E28: 4640 | F28: 3303.1932 | G28: 0.71189509 | H28: 460 | I28: 20658290 | J28: 44909.325 | K28: 453 | L28: 20607198 | M28: 45491 | N28: 866215.11 | O28: 111352.1 | P28: 5722333 | Q28: 0.86 | R28: 73520913 | S28: 4496991.2 | T28: =IF((100-IFERROR(S28/R28*100,0))=100,50,(100-IFERROR(S28/R28*100,0))) -> 93.883385 | U28: 26105 | V28: 74403297 | W28: 16097760 | X28: 9888 | Y28: 38759122 | Z28: 10302076 | AA28: 875304 | AB28: 1.594913e+08 | AC28: 2090404 | AD28: =(E28-MIN($E$2:$E$170))/(MAX($E$2:$E$170)-MIN($E$2:$E$170))*100 -> 31.906106 | AE28: =(F28-MIN($F$2:$F$170))/(MAX($F$2:$F$170)-MIN($F$2:$F$170))*100 -> 29.192402 | AF28: =(G28-MIN($G$2:$G$170))/(MAX($G$2:$G$170)-MIN($G$2:$G$170))*100 -> 31.638477 | AG28: =(H28-MIN($H$2:$H$170))/(MAX($H$2:$H$170)-MIN($H$2:$H$170))*100 -> 22.482893 | AH28: =(I28-MIN($I$2:$I$170))/(MAX($I$2:$I$170)-MIN($I$2:$I$170))*100 -> 15.466966 | AI28: =(J28-MIN($J$2:$J$170))/(MAX($J$2:$J$170)-MIN($J$2:$J$170))*100 -> 22.832013 | AJ28: =(K28-MIN($K$2:$K$170))/(MAX($K$2:$K$170)-MIN($K$2:$K$170))*100 -> 22.740964 | AK28: =(L28-MIN($L$2:$L$170))/(MAX($L$2:$L$170)-MIN($L$2:$L$170))*100 -> 15.912304 | AL28: =(M28-MIN($M$2:$M$170))/(MAX($M$2:$M$170)-MIN($M$2:$M$170))*100 -> 23.127685 | AM28: =(N28-MIN($N$2:$N$170))/(MAX($N$2:$N$170)-MIN($N$2:$N$170))*100 -> 9.2755806 | AN28: =(O28-MIN($O$2:$O$170))/(MAX($O$2:$O$170)-MIN($O$2:$O$170))*100 -> 41.250183 | AO28: =(P28-MIN($P$2:$P$170))/(MAX($P$2:$P$170)-MIN($P$2:$P$170))*100 -> 23.252536 | AP28: =(Q28-MIN($Q$2:$Q$170))/(MAX($Q$2:$Q$170)-MIN($Q$2:$Q$170))*100 -> 86 | AQ28: =IF(AP28>=50,AP28,50) -> 86 | AR28: =(#REF!-MIN(#REF!))/(MAX(#REF!)-MIN(#REF!))*100 -> #REF! | AS28: =IF(AR28>=50,AR28,50) -> #REF! | AT28: =(U28-MIN($U$2:$U$170))/(MAX($U$2:$U$170)-MIN($U$2:$U$170))*100 -> 27.217512 | AU28: =(V28-MIN($V$2:$V$170))/(MAX($V$2:$V$170)-MIN($V$2:$V$170))*100 -> 13.532397 | AV28: =(W28-MIN($W$2:$W$170))/(MAX($W$2:$W$170)-MIN($W$2:$W$170))*100 -> 1.5718228 | AW28: =(X28-MIN($X$2:$X$170))/(MAX($X$2:$X$170)-MIN($X$2:$X$170))*100 -> 25.972829 | AX28: =(Y28-MIN($Y$2:$Y$170))/(MAX($Y$2:$Y$170)-MIN($Y$2:$Y$170))*100 -> 12.031434 | AY28: =(Z28-MIN($Z$2:$Z$170))/(MAX($Z$2:$Z$170)-MIN($Z$2:$Z$170))*100 -> 13.672026 | AZ28: =(AA28-MIN($AA$2:$AA$170))/(MAX($AA$2:$AA$170)-MIN($AA$2:$AA$170))*100 -> 36.16629 | BA28: =(AB28-MIN($AB$2:$AB$170))/(MAX($AB$2:$AB$170)-MIN($AB$2:$AB$170))*100 -> 28.925369 | BB28: =(AC28-MIN($AC$2:$AC$170))/(MAX($AC$2:$AC$170)-MIN($AC$2:$AC$170))*100 -> 33.871819 | BC28: 9.7 | BD28: 495574 | BE28: 3 | BF28: 1.5
A29: CAJAMARCA | B29: CAJAMARCA | C29: JESUS | D29: 060106 | E29: 35 | F29: 20.346175 | G29: 0.58131929 | H29: 1 | I29: 3813.583 | J29: 3813.583 | K29: 1 | L29: 3814 | M29: 3814 | N29: 0 | O29: 0 | P29: 0 | Q29: 0 | R29: 0 | S29: 0 | T29: =IF((100-IFERROR(S29/R29*100,0))=100,50,(100-IFERROR(S29/R29*100,0))) -> 50 | U29: 264 | V29: 898910.69 | W29: 3328.277 | X29: 95 | Y29: 594907 | Z29: 3328 | AA29: 6636 | AB29: 278557.76 | AC29: 13015 | AD29: =(E29-MIN($E$2:$E$170))/(MAX($E$2:$E$170)-MIN($E$2:$E$170))*100 -> 0.20651201 | AE29: =(F29-MIN($F$2:$F$170))/(MAX($F$2:$F$170)-MIN($F$2:$F$170))*100 -> 0.15810183 | AF29: =(G29-MIN($G$2:$G$170))/(MAX($G$2:$G$170)-MIN($G$2:$G$170))*100 -> 20.132414 | AG29: =(H29-MIN($H$2:$H$170))/(MAX($H$2:$H$170)-MIN($H$2:$H$170))*100 -> 0.048875855 | AH29: =(I29-MIN($I$2:$I$170))/(MAX($I$2:$I$170)-MIN($I$2:$I$170))*100 -> 0.0028552489 | AI29: =(J29-MIN($J$2:$J$170))/(MAX($J$2:$J$170)-MIN($J$2:$J$170))*100 -> 1.9388352 | AJ29: =(K29-MIN($K$2:$K$170))/(MAX($K$2:$K$170)-MIN($K$2:$K$170))*100 -> 0.050200803 | AK29: =(L29-MIN($L$2:$L$170))/(MAX($L$2:$L$170)-MIN($L$2:$L$170))*100 -> 0.0029450645 | AL29: =(M29-MIN($M$2:$M$170))/(MAX($M$2:$M$170)-MIN($M$2:$M$170))*100 -> 1.9390427 | AM29: =(N29-MIN($N$2:$N$170))/(MAX($N$2:$N$170)-MIN($N$2:$N$170))*100 -> 0 | AN29: =(O29-MIN($O$2:$O$170))/(MAX($O$2:$O$170)-MIN($O$2:$O$170))*100 -> 0 | AO29: =(P29-MIN($P$2:$P$170))/(MAX($P$2:$P$170)-MIN($P$2:$P$170))*100 -> 0 | AP29: =(Q29-MIN($Q$2:$Q$170))/(MAX($Q$2:$Q$170)-MIN($Q$2:$Q$170))*100 -> 0 | AQ29: =IF(AP29>=50,AP29,50) -> 50 | AR29: =(#REF!-MIN(#REF!))/(MAX(#REF!)-MIN(#REF!))*100 -> #REF! | AS29: =IF(AR29>=50,AR29,50) -> #REF! | AT29: =(U29-MIN($U$2:$U$170))/(MAX($U$2:$U$170)-MIN($U$2:$U$170))*100 -> 0.20384909 | AU29: =(V29-MIN($V$2:$V$170))/(MAX($V$2:$V$170)-MIN($V$2:$V$170))*100 -> 0.14267356 | AV29: =(W29-MIN($W$2:$W$170))/(MAX($W$2:$W$170)-MIN($W$2:$W$170))*100 -> 0.0003084824 | AW29: =(X29-MIN($X$2:$X$170))/(MAX($X$2:$X$170)-MIN($X$2:$X$170))*100 -> 0.18956348 | AX29: =(Y29-MIN($Y$2:$Y$170))/(MAX($Y$2:$Y$170)-MIN($Y$2:$Y$170))*100 -> 0.16606419 | AY29: =(Z29-MIN($Z$2:$Z$170))/(MAX($Z$2:$Z$170)-MIN($Z$2:$Z$170))*100 -> 0.0041924209 | AZ29: =(AA29-MIN($AA$2:$AA$170))/(MAX($AA$2:$AA$170)-MIN($AA$2:$AA$170))*100 -> 0.27185243 | BA29: =(AB29-MIN($AB$2:$AB$170))/(MAX($AB$2:$AB$170)-MIN($AB$2:$AB$170))*100 -> 0.05051928 | BB29: =(AC29-MIN($AC$2:$AC$170))/(MAX($AC$2:$AC$170)-MIN($AC$2:$AC$170))*100 -> 0.20984159 | BC29: 0.1 | BD29: 2859 | BE29: 0 | BF29: 0
A30: CAJAMARCA | B30: CAJAMARCA | C30: LLACANORA | D30: 060107 | E30: 15 | F30: 7.544544 | G30: 0.5029696 | H30: 0 | I30: 0 | J30: 0 | K30: 0 | L30: 0 | M30: 0 | N30: 0 | O30: 0 | P30: 0 | Q30: 0 | R30: 0 | S30: 0 | T30: =IF((100-IFERROR(S30/R30*100,0))=100,50,(100-IFERROR(S30/R30*100,0))) -> 50 | U30: 170 | V30: 213595.31 | W30: 8813.7 | X30: 57 | Y30: 169458 | Z30: 8814 | AD30: =(E30-MIN($E$2:$E$170))/(MAX($E$2:$E$170)-MIN($E$2:$E$170))*100 -> 0.068837337 | AE30: =(F30-MIN($F$2:$F$170))/(MAX($F$2:$F$170)-MIN($F$2:$F$170))*100 -> 0.044881077 | AF30: =(G30-MIN($G$2:$G$170))/(MAX($G$2:$G$170)-MIN($G$2:$G$170))*100 -> 13.228406 | AG30: =(H30-MIN($H$2:$H$170))/(MAX($H$2:$H$170)-MIN($H$2:$H$170))*100 -> 0 | AH30: =(I30-MIN($I$2:$I$170))/(MAX($I$2:$I$170)-MIN($I$2:$I$170))*100 -> 0 | AI30: =(J30-MIN($J$2:$J$170))/(MAX($J$2:$J$170)-MIN($J$2:$J$170))*100 -> 0 | AJ30: =(K30-MIN($K$2:$K$170))/(MAX($K$2:$K$170)-MIN($K$2:$K$170))*100 -> 0 | AK30: =(L30-MIN($L$2:$L$170))/(MAX($L$2:$L$170)-MIN($L$2:$L$170))*100 -> 0 | AL30: =(M30-MIN($M$2:$M$170))/(MAX($M$2:$M$170)-MIN($M$2:$M$170))*100 -> 0 | AM30: =(N30-MIN($N$2:$N$170))/(MAX($N$2:$N$170)-MIN($N$2:$N$170))*100 -> 0 | AN30: =(O30-MIN($O$2:$O$170))/(MAX($O$2:$O$170)-MIN($O$2:$O$170))*100 -> 0 | AO30: =(P30-MIN($P$2:$P$170))/(MAX($P$2:$P$170)-MIN($P$2:$P$170))*100 -> 0 | AP30: =(Q30-MIN($Q$2:$Q$170))/(MAX($Q$2:$Q$170)-MIN($Q$2:$Q$170))*100 -> 0 | AQ30: =IF(AP30>=50,AP30,50) -> 50 | AR30: =(#REF!-MIN(#REF!))/(MAX(#REF!)-MIN(#REF!))*100 -> #REF! | AS30: =IF(AR30>=50,AR30,50) -> #REF! | AT30: =(U30-MIN($U$2:$U$170))/(MAX($U$2:$U$170)-MIN($U$2:$U$170))*100 -> 0.10558337 | AU30: =(V30-MIN($V$2:$V$170))/(MAX($V$2:$V$170)-MIN($V$2:$V$170))*100 -> 0.017834982 | AV30: =(W30-MIN($W$2:$W$170))/(MAX($W$2:$W$170)-MIN($W$2:$W$170))*100 -> 0.00084409749 | AW30: =(X30-MIN($X$2:$X$170))/(MAX($X$2:$X$170)-MIN($X$2:$X$170))*100 -> 0.089516087 | AX30: =(Y30-MIN($Y$2:$Y$170))/(MAX($Y$2:$Y$170)-MIN($Y$2:$Y$170))*100 -> 0.033790806 | AY30: =(Z30-MIN($Z$2:$Z$170))/(MAX($Z$2:$Z$170)-MIN($Z$2:$Z$170))*100 -> 0.011473086 | AZ30: =(AA30-MIN($AA$2:$AA$170))/(MAX($AA$2:$AA$170)-MIN($AA$2:$AA$170))*100 -> -0.0023553106 | BA30: =(AB30-MIN($AB$2:$AB$170))/(MAX($AB$2:$AB$170)-MIN($AB$2:$AB$170))*100 -> 0 | BB30: =(AC30-MIN($AC$2:$AC$170))/(MAX($AC$2:$AC$170)-MIN($AC$2:$AC$170))*100 -> -0.0010532589 | BC30: 0 | BD30: 1120 | BE30: 0 | BF30: 0
A31: CAJAMARCA | B31: CAJAMARCA | C31: LOS BAÑOS DEL INCA | D31: 060108 | E31: 278 | F31: 148.63066 | G31: 0.53464267 | H31: 34 | I31: 964183.27 | J31: 28358.331 | K31: 32 | L31: 936208 | M31: 29256 | N31: 9513.21 | O31: 1427.04 | P31: 120006 | Q31: 0.93 | R31: 2887187.7 | S31: 38073.53 | T31: =IF((100-IFERROR(S31/R31*100,0))=100,50,(100-IFERROR(S31/R31*100,0))) -> 98.681294 | U31: 2078 | V31: 3959371.8 | W31: 1361002.7 | X31: 845 | Y31: 2588751 | Z31: 1192515 | AA31: 46936 | AB31: 3063006 | AC31: 83188 | AD31: =(E31-MIN($E$2:$E$170))/(MAX($E$2:$E$170)-MIN($E$2:$E$170))*100 -> 1.8792593 | AE31: =(F31-MIN($F$2:$F$170))/(MAX($F$2:$F$170)-MIN($F$2:$F$170))*100 -> 1.2926811 | AF31: =(G31-MIN($G$2:$G$170))/(MAX($G$2:$G$170)-MIN($G$2:$G$170))*100 -> 16.019369 | AG31: =(H31-MIN($H$2:$H$170))/(MAX($H$2:$H$170)-MIN($H$2:$H$170))*100 -> 1.6617791 | AH31: =(I31-MIN($I$2:$I$170))/(MAX($I$2:$I$170)-MIN($I$2:$I$170))*100 -> 0.72188889 | AI31: =(J31-MIN($J$2:$J$170))/(MAX($J$2:$J$170)-MIN($J$2:$J$170))*100 -> 14.417447 | AJ31: =(K31-MIN($K$2:$K$170))/(MAX($K$2:$K$170)-MIN($K$2:$K$170))*100 -> 1.6064257 | AK31: =(L31-MIN($L$2:$L$170))/(MAX($L$2:$L$170)-MIN($L$2:$L$170))*100 -> 0.72291372 | AL31: =(M31-MIN($M$2:$M$170))/(MAX($M$2:$M$170)-MIN($M$2:$M$170))*100 -> 14.873789 | AM31: =(N31-MIN($N$2:$N$170))/(MAX($N$2:$N$170)-MIN($N$2:$N$170))*100 -> 0.10186909 | AN31: =(O31-MIN($O$2:$O$170))/(MAX($O$2:$O$170)-MIN($O$2:$O$170))*100 -> 0.52864437 | AO31: =(P31-MIN($P$2:$P$170))/(MAX($P$2:$P$170)-MIN($P$2:$P$170))*100 -> 0.48764095 | AP31: =(Q31-MIN($Q$2:$Q$170))/(MAX($Q$2:$Q$170)-MIN($Q$2:$Q$170))*100 -> 93 | AQ31: =IF(AP31>=50,AP31,50) -> 93 | AR31: =(#REF!-MIN(#REF!))/(MAX(#REF!)-MIN(#REF!))*100 -> #REF! | AS31: =IF(AR31>=50,AR31,50) -> #REF! | AT31: =(U31-MIN($U$2:$U$170))/(MAX($U$2:$U$170)-MIN($U$2:$U$170))*100 -> 2.1001683 | AU31: =(V31-MIN($V$2:$V$170))/(MAX($V$2:$V$170)-MIN($V$2:$V$170))*100 -> 0.700174 | AV31: =(W31-MIN($W$2:$W$170))/(MAX($W$2:$W$170)-MIN($W$2:$W$170))*100 -> 0.13287637 | AW31: =(X31-MIN($X$2:$X$170))/(MAX($X$2:$X$170)-MIN($X$2:$X$170))*100 -> 2.164183 | AX31: =(Y31-MIN($Y$2:$Y$170))/(MAX($Y$2:$Y$170)-MIN($Y$2:$Y$170))*100 -> 0.78595631 | AY31: =(Z31-MIN($Z$2:$Z$170))/(MAX($Z$2:$Z$170)-MIN($Z$2:$Z$170))*100 -> 1.5824046 | AZ31: =(AA31-MIN($AA$2:$AA$170))/(MAX($AA$2:$AA$170)-MIN($AA$2:$AA$170))*100 -> 1.9370983 | BA31: =(AB31-MIN($AB$2:$AB$170))/(MAX($AB$2:$AB$170)-MIN($AB$2:$AB$170))*100 -> 0.55550727 | BB31: =(AC31-MIN($AC$2:$AC$170))/(MAX($AC$2:$AC$170)-MIN($AC$2:$AC$170))*100 -> 1.3469237 | BC31: 0.5 | BD31: 21756 | BE31: 0 | BF31: 0
A32: CAJAMARCA | B32: CAJAMARCA | C32: MAGDALENA | D32: 060109 | E32: 18 | F32: 6.6478866 | G32: 0.36932703 | H32: 0 | I32: 0 | J32: 0 | K32: 0 | L32: 0 | M32: 0 | N32: 0 | O32: 0 | P32: 0 | Q32: 0 | R32: 0 | S32: 0 | T32: =IF((100-IFERROR(S32/R32*100,0))=100,50,(100-IFERROR(S32/R32*100,0))) -> 50 | U32: 240 | V32: 516108.23 | W32: 29846.762 | X32: 87 | Y32: 208570 | Z32: 29847 | AD32: =(E32-MIN($E$2:$E$170))/(MAX($E$2:$E$170)-MIN($E$2:$E$170))*100 -> 0.089488539 | AE32: =(F32-MIN($F$2:$F$170))/(MAX($F$2:$F$170)-MIN($F$2:$F$170))*100 -> 0.036950821 | AF32: =(G32-MIN($G$2:$G$170))/(MAX($G$2:$G$170)-MIN($G$2:$G$170))*100 -> 1.452106 | AG32: =(H32-MIN($H$2:$H$170))/(MAX($H$2:$H$170)-MIN($H$2:$H$170))*100 -> 0 | AH32: =(I32-MIN($I$2:$I$170))/(MAX($I$2:$I$170)-MIN($I$2:$I$170))*100 -> 0 | AI32: =(J32-MIN($J$2:$J$170))/(MAX($J$2:$J$170)-MIN($J$2:$J$170))*100 -> 0 | AJ32: =(K32-MIN($K$2:$K$170))/(MAX($K$2:$K$170)-MIN($K$2:$K$170))*100 -> 0 | AK32: =(L32-MIN($L$2:$L$170))/(MAX($L$2:$L$170)-MIN($L$2:$L$170))*100 -> 0 | AL32: =(M32-MIN($M$2:$M$170))/(MAX($M$2:$M$170)-MIN($M$2:$M$170))*100 -> 0 | AM32: =(N32-MIN($N$2:$N$170))/(MAX($N$2:$N$170)-MIN($N$2:$N$170))*100 -> 0 | AN32: =(O32-MIN($O$2:$O$170))/(MAX($O$2:$O$170)-MIN($O$2:$O$170))*100 -> 0 | AO32: =(P32-MIN($P$2:$P$170))/(MAX($P$2:$P$170)-MIN($P$2:$P$170))*100 -> 0 | AP32: =(Q32-MIN($Q$2:$Q$170))/(MAX($Q$2:$Q$170)-MIN($Q$2:$Q$170))*100 -> 0 | AQ32: =IF(AP32>=50,AP32,50) -> 50 | AR32: =(#REF!-MIN(#REF!))/(MAX(#REF!)-MIN(#REF!))*100 -> #REF! | AS32: =IF(AR32>=50,AR32,50) -> #REF! | AT32: =(U32-MIN($U$2:$U$170))/(MAX($U$2:$U$170)-MIN($U$2:$U$170))*100 -> 0.17875997 | AU32: =(V32-MIN($V$2:$V$170))/(MAX($V$2:$V$170)-MIN($V$2:$V$170))*100 -> 0.072941412 | AV32: =(W32-MIN($W$2:$W$170))/(MAX($W$2:$W$170)-MIN($W$2:$W$170))*100 -> 0.0028978362 | AW32: =(X32-MIN($X$2:$X$170))/(MAX($X$2:$X$170)-MIN($X$2:$X$170))*100 -> 0.16850087 | AX32: =(Y32-MIN($Y$2:$Y$170))/(MAX($Y$2:$Y$170)-MIN($Y$2:$Y$170))*100 -> 0.045950845 | AY32: =(Z32-MIN($Z$2:$Z$170))/(MAX($Z$2:$Z$170)-MIN($Z$2:$Z$170))*100 -> 0.039386726 | AZ32: =(AA32-MIN($AA$2:$AA$170))/(MAX($AA$2:$AA$170)-MIN($AA$2:$AA$170))*100 -> -0.0023553106 | BA32: =(AB32-MIN($AB$2:$AB$170))/(MAX($AB$2:$AB$170)-MIN($AB$2:$AB$170))*100 -> 0 | BB32: =(AC32-MIN($AC$2:$AC$170))/(MAX($AC$2:$AC$170)-MIN($AC$2:$AC$170))*100 -> -0.0010532589 | BC32: 0.1 | BD32: 2527 | BE32: 0 | BF32: 0
A33: CALLAO | B33: CALLAO | C33: CALLAO | D33: 070101 | E33: 5348 | F33: 3726.5766 | G33: 0.69681688 | H33: 638 | I33: 38425977 | J33: 60228.805 | K33: 613 | L33: 37554648 | M33: 61264 | N33: 769467.41 | O33: 17339.42 | P33: 6161822 | Q33: 0.84 | R33: 88057433 | S33: 3891954.8 | T33: =IF((100-IFERROR(S33/R33*100,0))=100,50,(100-IFERROR(S33/R33*100,0))) -> 95.580209 | U33: 44921 | V33: 2.7569856e+08 | W33: 25945339 | X33: 15485 | Y33: 141968806 | Z33: 13343623 | AA33: 758781 | AB33: 63867485 | AC33: 1384450 | AD33: =(E33-MIN($E$2:$E$170))/(MAX($E$2:$E$170)-MIN($E$2:$E$170))*100 -> 36.779789 | AE33: =(F33-MIN($F$2:$F$170))/(MAX($F$2:$F$170)-MIN($F$2:$F$170))*100 -> 32.936909 | AF33: =(G33-MIN($G$2:$G$170))/(MAX($G$2:$G$170)-MIN($G$2:$G$170))*100 -> 30.309817 | AG33: =(H33-MIN($H$2:$H$170))/(MAX($H$2:$H$170)-MIN($H$2:$H$170))*100 -> 31.182796 | AH33: =(I33-MIN($I$2:$I$170))/(MAX($I$2:$I$170)-MIN($I$2:$I$170))*100 -> 28.769724 | AI33: =(J33-MIN($J$2:$J$170))/(MAX($J$2:$J$170)-MIN($J$2:$J$170))*100 -> 30.620475 | AJ33: =(K33-MIN($K$2:$K$170))/(MAX($K$2:$K$170)-MIN($K$2:$K$170))*100 -> 30.773092 | AK33: =(L33-MIN($L$2:$L$170))/(MAX($L$2:$L$170)-MIN($L$2:$L$170))*100 -> 28.998652 | AL33: =(M33-MIN($M$2:$M$170))/(MAX($M$2:$M$170)-MIN($M$2:$M$170))*100 -> 31.146699 | AM33: =(N33-MIN($N$2:$N$170))/(MAX($N$2:$N$170)-MIN($N$2:$N$170))*100 -> 8.2395896 | AN33: =(O33-MIN($O$2:$O$170))/(MAX($O$2:$O$170)-MIN($O$2:$O$170))*100 -> 6.4233566 | AO33: =(P33-MIN($P$2:$P$170))/(MAX($P$2:$P$170)-MIN($P$2:$P$170))*100 -> 25.038387 | AP33: =(Q33-MIN($Q$2:$Q$170))/(MAX($Q$2:$Q$170)-MIN($Q$2:$Q$170))*100 -> 84 | AQ33: =IF(AP33>=50,AP33,50) -> 84 | AR33: =(#REF!-MIN(#REF!))/(MAX(#REF!)-MIN(#REF!))*100 -> #REF! | AS33: =IF(AR33>=50,AR33,50) -> #REF! | AT33: =(U33-MIN($U$2:$U$170))/(MAX($U$2:$U$170)-MIN($U$2:$U$170))*100 -> 46.887381 | AU33: =(V33-MIN($V$2:$V$170))/(MAX($V$2:$V$170)-MIN($V$2:$V$170))*100 -> 50.200793 | AV33: =(W33-MIN($W$2:$W$170))/(MAX($W$2:$W$170)-MIN($W$2:$W$170))*100 -> 2.5333734 | AW33: =(X33-MIN($X$2:$X$170))/(MAX($X$2:$X$170)-MIN($X$2:$X$170))*100 -> 40.708757 | AX33: =(Y33-MIN($Y$2:$Y$170))/(MAX($Y$2:$Y$170)-MIN($Y$2:$Y$170))*100 -> 44.119637 | AY33: =(Z33-MIN($Z$2:$Z$170))/(MAX($Z$2:$Z$170)-MIN($Z$2:$Z$170))*100 -> 17.708571 | AZ33: =(AA33-MIN($AA$2:$AA$170))/(MAX($AA$2:$AA$170)-MIN($AA$2:$AA$170))*100 -> 31.351415 | BA33: =(AB33-MIN($AB$2:$AB$170))/(MAX($AB$2:$AB$170)-MIN($AB$2:$AB$170))*100 -> 11.583017 | BB33: =(AC33-MIN($AC$2:$AC$170))/(MAX($AC$2:$AC$170)-MIN($AC$2:$AC$170))*100 -> 22.432552 | BC33: 13.1 | BD33: 673710 | BE33: 3 | BF33: 0.6
A34: CALLAO | B34: CALLAO | C34: BELLAVISTA | D34: 070102 | E34: 1025 | F34: 969.00306 | G34: 0.94536884 | H34: 134 | I34: 8318286.1 | J34: 62076.762 | K34: 129 | L34: 8082159 | M34: 62652 | N34: 93105.94 | O34: 8925.68 | P34: 1075964.1 | Q34: 0.86 | R34: 19027185 | S34: 669566.16 | T34: =IF((100-IFERROR(S34/R34*100,0))=100,50,(100-IFERROR(S34/R34*100,0))) -> 96.481003 | U34: 9660 | V34: 66425528 | W34: 4619531.7 | X34: 3229 | Y34: 35190408 | Z34: 3326056 | AA34: 183774 | AB34: 11516430 | AC34: 302038 | AD34: =(E34-MIN($E$2:$E$170))/(MAX($E$2:$E$170)-MIN($E$2:$E$170))*100 -> 7.0214084 | AE34: =(F34-MIN($F$2:$F$170))/(MAX($F$2:$F$170)-MIN($F$2:$F$170))*100 -> 8.5482548 | AF34: =(G34-MIN($G$2:$G$170))/(MAX($G$2:$G$170)-MIN($G$2:$G$170))*100 -> 52.211688 | AG34: =(H34-MIN($H$2:$H$170))/(MAX($H$2:$H$170)-MIN($H$2:$H$170))*100 -> 6.5493646 | AH34: =(I34-MIN($I$2:$I$170))/(MAX($I$2:$I$170)-MIN($I$2:$I$170))*100 -> 6.2279429 | AI34: =(J34-MIN($J$2:$J$170))/(MAX($J$2:$J$170)-MIN($J$2:$J$170))*100 -> 31.559981 | AJ34: =(K34-MIN($K$2:$K$170))/(MAX($K$2:$K$170)-MIN($K$2:$K$170))*100 -> 6.4759036 | AK34: =(L34-MIN($L$2:$L$170))/(MAX($L$2:$L$170)-MIN($L$2:$L$170))*100 -> 6.2408179 | AL34: =(M34-MIN($M$2:$M$170))/(MAX($M$2:$M$170)-MIN($M$2:$M$170))*100 -> 31.85236 | AM34: =(N34-MIN($N$2:$N$170))/(MAX($N$2:$N$170)-MIN($N$2:$N$170))*100 -> 0.99699444 | AN34: =(O34-MIN($O$2:$O$170))/(MAX($O$2:$O$170)-MIN($O$2:$O$170))*100 -> 3.3065019 | AO34: =(P34-MIN($P$2:$P$170))/(MAX($P$2:$P$170)-MIN($P$2:$P$170))*100 -> 4.3721494 | AP34: =(Q34-MIN($Q$2:$Q$170))/(MAX($Q$2:$Q$170)-MIN($Q$2:$Q$170))*100 -> 86 | AQ34: =IF(AP34>=50,AP34,50) -> 86 | AR34: =(#REF!-MIN(#REF!))/(MAX(#REF!)-MIN(#REF!))*100 -> #REF! | AS34: =IF(AR34>=50,AR34,50) -> #REF! | AT34: =(U34-MIN($U$2:$U$170))/(MAX($U$2:$U$170)-MIN($U$2:$U$170))*100 -> 10.026239 | AU34: =(V34-MIN($V$2:$V$170))/(MAX($V$2:$V$170)-MIN($V$2:$V$170))*100 -> 12.079149 | AV34: =(W34-MIN($W$2:$W$170))/(MAX($W$2:$W$170)-MIN($W$2:$W$170))*100 -> 0.45105006 | AW34: =(X34-MIN($X$2:$X$170))/(MAX($X$2:$X$170)-MIN($X$2:$X$170))*100 -> 8.4408404 | AX34: =(Y34-MIN($Y$2:$Y$170))/(MAX($Y$2:$Y$170)-MIN($Y$2:$Y$170))*100 -> 10.92191 | AY34: =(Z34-MIN($Z$2:$Z$170))/(MAX($Z$2:$Z$170)-MIN($Z$2:$Z$170))*100 -> 4.4139025 | AZ34: =(AA34-MIN($AA$2:$AA$170))/(MAX($AA$2:$AA$170)-MIN($AA$2:$AA$170))*100 -> 7.5914139 | BA34: =(AB34-MIN($AB$2:$AB$170))/(MAX($AB$2:$AB$170)-MIN($AB$2:$AB$170))*100 -> 2.0886215 | BB34: =(AC34-MIN($AC$2:$AC$170))/(MAX($AC$2:$AC$170)-MIN($AC$2:$AC$170))*100 -> 4.8931655 | BC34: 2.3 | BD34: 128886 | BE34: 1 | BF34: 0.2
A35: CALLAO | B35: CALLAO | C35: CARMEN DE LA LEGUA REYNOSO | D35: 070103 | E35: 380 | F35: 287.40893 | G35: 0.75633928 | H35: 44 | I35: 2728171.1 | J35: 62003.889 | K35: 43 | L35: 2715182 | M35: 63144 | N35: 3527.16 | O35: 4.75 | P35: 817359.98 | Q35: 0.82 | R35: 5374782.2 | S35: 3285.05 | T35: =IF((100-IFERROR(S35/R35*100,0))=100,50,(100-IFERROR(S35/R35*100,0))) -> 99.93888 | U35: 4458 | V35: 29405361 | W35: 5732546.3 | X35: 1462 | Y35: 16268488 | Z35: 580512 | AA35: 92169 | AB35: 5270113.7 | AC35: 159205 | AD35: =(E35-MIN($E$2:$E$170))/(MAX($E$2:$E$170)-MIN($E$2:$E$170))*100 -> 2.5814002 | AE35: =(F35-MIN($F$2:$F$170))/(MAX($F$2:$F$170)-MIN($F$2:$F$170))*100 -> 2.52007 | AF35: =(G35-MIN($G$2:$G$170))/(MAX($G$2:$G$170)-MIN($G$2:$G$170))*100 -> 35.554805 | AG35: =(H35-MIN($H$2:$H$170))/(MAX($H$2:$H$170)-MIN($H$2:$H$170))*100 -> 2.1505376 | AH35: =(I35-MIN($I$2:$I$170))/(MAX($I$2:$I$170)-MIN($I$2:$I$170))*100 -> 2.0425955 | AI35: =(J35-MIN($J$2:$J$170))/(MAX($J$2:$J$170)-MIN($J$2:$J$170))*100 -> 31.522933 | AJ35: =(K35-MIN($K$2:$K$170))/(MAX($K$2:$K$170)-MIN($K$2:$K$170))*100 -> 2.1586345 | AK35: =(L35-MIN($L$2:$L$170))/(MAX($L$2:$L$170)-MIN($L$2:$L$170))*100 -> 2.0965878 | AL35: =(M35-MIN($M$2:$M$170))/(MAX($M$2:$M$170)-MIN($M$2:$M$170))*100 -> 32.102494 | AM35: =(N35-MIN($N$2:$N$170))/(MAX($N$2:$N$170)-MIN($N$2:$N$170))*100 -> 0.037769437 | AN35: =(O35-MIN($O$2:$O$170))/(MAX($O$2:$O$170)-MIN($O$2:$O$170))*100 -> 0.0017596288 | AO35: =(P35-MIN($P$2:$P$170))/(MAX($P$2:$P$170)-MIN($P$2:$P$170))*100 -> 3.3213189 | AP35: =(Q35-MIN($Q$2:$Q$170))/(MAX($Q$2:$Q$170)-MIN($Q$2:$Q$170))*100 -> 82 | AQ35: =IF(AP35>=50,AP35,50) -> 82 | AR35: =(#REF!-MIN(#REF!))/(MAX(#REF!)-MIN(#REF!))*100 -> #REF! | AS35: =IF(AR35>=50,AR35,50) -> #REF! | AT35: =(U35-MIN($U$2:$U$170))/(MAX($U$2:$U$170)-MIN($U$2:$U$170))*100 -> 4.5881726 | AU35: =(V35-MIN($V$2:$V$170))/(MAX($V$2:$V$170)-MIN($V$2:$V$170))*100 -> 5.3354724 | AV35: =(W35-MIN($W$2:$W$170))/(MAX($W$2:$W$170)-MIN($W$2:$W$170))*100 -> 0.55972854 | AW35: =(X35-MIN($X$2:$X$170))/(MAX($X$2:$X$170)-MIN($X$2:$X$170))*100 -> 3.7886367 | AX35: =(Y35-MIN($Y$2:$Y$170))/(MAX($Y$2:$Y$170)-MIN($Y$2:$Y$170))*100 -> 5.0390279 | AY35: =(Z35-MIN($Z$2:$Z$170))/(MAX($Z$2:$Z$170)-MIN($Z$2:$Z$170))*100 -> 0.77019377 | AZ35: =(AA35-MIN($AA$2:$AA$170))/(MAX($AA$2:$AA$170)-MIN($AA$2:$AA$170))*100 -> 3.8061819 | BA35: =(AB35-MIN($AB$2:$AB$170))/(MAX($AB$2:$AB$170)-MIN($AB$2:$AB$170))*100 -> 0.95578868 | BB35: =(AC35-MIN($AC$2:$AC$170))/(MAX($AC$2:$AC$170)-MIN($AC$2:$AC$170))*100 -> 2.5787019 | BC35: 1.5 | BD35: 68134 | BE35: 0 | BF35: 0
A36: CALLAO | B36: CALLAO | C36: LA PERLA | D36: 070104 | E36: 406 | F36: 277.13065 | G36: 0.6825878 | H36: 76 | I36: 6217324.6 | J36: 81806.902 | K36: 73 | L36: 6158753 | M36: 84366 | N36: 61023.01 | O36: 374.86 | P36: 1419417.4 | Q36: 0.85 | R36: 15030519 | S36: 1661604.3 | T36: =IF((100-IFERROR(S36/R36*100,0))=100,50,(100-IFERROR(S36/R36*100,0))) -> 88.94513 | U36: 6921 | V36: 44984079 | W36: 4014087.2 | X36: 2053 | Y36: 20510790 | Z36: 3633622 | AA36: 60537 | AB36: 3257774.5 | AC36: 103617 | AD36: =(E36-MIN($E$2:$E$170))/(MAX($E$2:$E$170)-MIN($E$2:$E$170))*100 -> 2.7603772 | AE36: =(F36-MIN($F$2:$F$170))/(MAX($F$2:$F$170)-MIN($F$2:$F$170))*100 -> 2.4291664 | AF36: =(G36-MIN($G$2:$G$170))/(MAX($G$2:$G$170)-MIN($G$2:$G$170))*100 -> 29.055981 | AG36: =(H36-MIN($H$2:$H$170))/(MAX($H$2:$H$170)-MIN($H$2:$H$170))*100 -> 3.714565 | AH36: =(I36-MIN($I$2:$I$170))/(MAX($I$2:$I$170)-MIN($I$2:$I$170))*100 -> 4.6549424 | AI36: =(J36-MIN($J$2:$J$170))/(MAX($J$2:$J$170)-MIN($J$2:$J$170))*100 -> 41.590834 | AJ36: =(K36-MIN($K$2:$K$170))/(MAX($K$2:$K$170)-MIN($K$2:$K$170))*100 -> 3.6646586 | AK36: =(L36-MIN($L$2:$L$170))/(MAX($L$2:$L$170)-MIN($L$2:$L$170))*100 -> 4.7556174 | AL36: =(M36-MIN($M$2:$M$170))/(MAX($M$2:$M$170)-MIN($M$2:$M$170))*100 -> 42.891787 | AM36: =(N36-MIN($N$2:$N$170))/(MAX($N$2:$N$170)-MIN($N$2:$N$170))*100 -> 0.6534449 | AN36: =(O36-MIN($O$2:$O$170))/(MAX($O$2:$O$170)-MIN($O$2:$O$170))*100 -> 0.1388662 | AO36: =(P36-MIN($P$2:$P$170))/(MAX($P$2:$P$170)-MIN($P$2:$P$170))*100 -> 5.7677621 | AP36: =(Q36-MIN($Q$2:$Q$170))/(MAX($Q$2:$Q$170)-MIN($Q$2:$Q$170))*100 -> 85 | AQ36: =IF(AP36>=50,AP36,50) -> 85 | AR36: =(#REF!-MIN(#REF!))/(MAX(#REF!)-MIN(#REF!))*100 -> #REF! | AS36: =IF(AR36>=50,AR36,50) -> #REF! | AT36: =(U36-MIN($U$2:$U$170))/(MAX($U$2:$U$170)-MIN($U$2:$U$170))*100 -> 7.1629434 | AU36: =(V36-MIN($V$2:$V$170))/(MAX($V$2:$V$170)-MIN($V$2:$V$170))*100 -> 8.1733264 | AV36: =(W36-MIN($W$2:$W$170))/(MAX($W$2:$W$170)-MIN($W$2:$W$170))*100 -> 0.39193242 | AW36: =(X36-MIN($X$2:$X$170))/(MAX($X$2:$X$170)-MIN($X$2:$X$170))*100 -> 5.3446369 | AX36: =(Y36-MIN($Y$2:$Y$170))/(MAX($Y$2:$Y$170)-MIN($Y$2:$Y$170))*100 -> 6.3579724 | AY36: =(Z36-MIN($Z$2:$Z$170))/(MAX($Z$2:$Z$170)-MIN($Z$2:$Z$170))*100 -> 4.8220843 | AZ36: =(AA36-MIN($AA$2:$AA$170))/(MAX($AA$2:$AA$170)-MIN($AA$2:$AA$170))*100 -> 2.4991085 | BA36: =(AB36-MIN($AB$2:$AB$170))/(MAX($AB$2:$AB$170)-MIN($AB$2:$AB$170))*100 -> 0.59083051 | BB36: =(AC36-MIN($AC$2:$AC$170))/(MAX($AC$2:$AC$170)-MIN($AC$2:$AC$170))*100 -> 1.6779549 | BC36: 2 | BD36: 104004 | BE36: 0 | BF36: 0
A37: CALLAO | B37: CALLAO | C37: LA PUNTA | D37: 070105 | E37: 183 | F37: 118.47452 | G37: 0.64740178 | H37: 8 | I37: 803618.23 | J37: 100452.28 | K37: 6 | L37: 755111 | M37: 125852 | N37: 116.77 | O37: 35.6 | P37: 0 | Q37: 0.6 | R37: 1491401.9 | S37: 0 | T37: =IF((100-IFERROR(S37/R37*100,0))=100,50,(100-IFERROR(S37/R37*100,0))) -> 50 | U37: 680 | V37: 2642398 | W37: 884594.29 | X37: 206 | Y37: 1510969 | Z37: 586374 | AA37: 26972 | AB37: 2002961.7 | AC37: 58365 | AD37: =(E37-MIN($E$2:$E$170))/(MAX($E$2:$E$170)-MIN($E$2:$E$170))*100 -> 1.2253046 | AE37: =(F37-MIN($F$2:$F$170))/(MAX($F$2:$F$170)-MIN($F$2:$F$170))*100 -> 1.0259729 | AF37: =(G37-MIN($G$2:$G$170))/(MAX($G$2:$G$170)-MIN($G$2:$G$170))*100 -> 25.955463 | AG37: =(H37-MIN($H$2:$H$170))/(MAX($H$2:$H$170)-MIN($H$2:$H$170))*100 -> 0.39100684 | AH37: =(I37-MIN($I$2:$I$170))/(MAX($I$2:$I$170)-MIN($I$2:$I$170))*100 -> 0.60167303 | AI37: =(J37-MIN($J$2:$J$170))/(MAX($J$2:$J$170)-MIN($J$2:$J$170))*100 -> 51.07019 | AJ37: =(K37-MIN($K$2:$K$170))/(MAX($K$2:$K$170)-MIN($K$2:$K$170))*100 -> 0.30120482 | AK37: =(L37-MIN($L$2:$L$170))/(MAX($L$2:$L$170)-MIN($L$2:$L$170))*100 -> 0.58307566 | AL37: =(M37-MIN($M$2:$M$170))/(MAX($M$2:$M$170)-MIN($M$2:$M$170))*100 -> 63.983324 | AM37: =(N37-MIN($N$2:$N$170))/(MAX($N$2:$N$170)-MIN($N$2:$N$170))*100 -> 0.0012503933 | AN37: =(O37-MIN($O$2:$O$170))/(MAX($O$2:$O$170)-MIN($O$2:$O$170))*100 -> 0.013187955 | AO37: =(P37-MIN($P$2:$P$170))/(MAX($P$2:$P$170)-MIN($P$2:$P$170))*100 -> 0 | AP37: =(Q37-MIN($Q$2:$Q$170))/(MAX($Q$2:$Q$170)-MIN($Q$2:$Q$170))*100 -> 60 | AQ37: =IF(AP37>=50,AP37,50) -> 60 | AR37: =(#REF!-MIN(#REF!))/(MAX(#REF!)-MIN(#REF!))*100 -> #REF! | AS37: =IF(AR37>=50,AR37,50) -> #REF! | AT37: =(U37-MIN($U$2:$U$170))/(MAX($U$2:$U$170)-MIN($U$2:$U$170))*100 -> 0.63872715 | AU37: =(V37-MIN($V$2:$V$170))/(MAX($V$2:$V$170)-MIN($V$2:$V$170))*100 -> 0.46027111 | AV37: =(W37-MIN($W$2:$W$170))/(MAX($W$2:$W$170)-MIN($W$2:$W$170))*100 -> 0.08635825 | AW37: =(X37-MIN($X$2:$X$170))/(MAX($X$2:$X$170)-MIN($X$2:$X$170))*100 -> 0.48180717 | AX37: =(Y37-MIN($Y$2:$Y$170))/(MAX($Y$2:$Y$170)-MIN($Y$2:$Y$170))*100 -> 0.45087063 | AY37: =(Z37-MIN($Z$2:$Z$170))/(MAX($Z$2:$Z$170)-MIN($Z$2:$Z$170))*100 -> 0.77797344 | AZ37: =(AA37-MIN($AA$2:$AA$170))/(MAX($AA$2:$AA$170)-MIN($AA$2:$AA$170))*100 -> 1.1121611 | BA37: =(AB37-MIN($AB$2:$AB$170))/(MAX($AB$2:$AB$170)-MIN($AB$2:$AB$170))*100 -> 0.36325746 | BB37: =(AC37-MIN($AC$2:$AC$170))/(MAX($AC$2:$AC$170)-MIN($AC$2:$AC$170))*100 -> 0.94469224 | BC37: 0.2 | BD37: 10688 | BE37: 0 | BF37: 0
A38: CALLAO | B38: CALLAO | C38: VENTANILLA | D38: 070106 | E38: 1657 | F38: 928.03234 | G38: 0.5600678 | H38: 225 | I38: 12989136 | J38: 57729.495 | K38: 217 | L38: 12826986 | M38: 59111 | N38: 353044.39 | O38: 101982.67 | P38: 1790113 | Q38: 0.87 | R38: 33832676 | S38: 631051.26 | T38: =IF((100-IFERROR(S38/R38*100,0))=100,50,(100-IFERROR(S38/R38*100,0))) -> 98.134788 | U38: 20398 | V38: 1.2028432e+08 | W38: 6414019.3 | X38: 8057 | Y38: 69147785 | Z38: 4887348 | AA38: 289306 | AB38: 18564592 | AC38: 533892 | AD38: =(E38-MIN($E$2:$E$170))/(MAX($E$2:$E$170)-MIN($E$2:$E$170))*100 -> 11.371928 | AE38: =(F38-MIN($F$2:$F$170))/(MAX($F$2:$F$170)-MIN($F$2:$F$170))*100 -> 8.1858998 | AF38: =(G38-MIN($G$2:$G$170))/(MAX($G$2:$G$170)-MIN($G$2:$G$170))*100 -> 18.259778 | AG38: =(H38-MIN($H$2:$H$170))/(MAX($H$2:$H$170)-MIN($H$2:$H$170))*100 -> 10.997067 | AH38: =(I38-MIN($I$2:$I$170))/(MAX($I$2:$I$170)-MIN($I$2:$I$170))*100 -> 9.7250321 | AI38: =(J38-MIN($J$2:$J$170))/(MAX($J$2:$J$170)-MIN($J$2:$J$170))*100 -> 29.34982 | AJ38: =(K38-MIN($K$2:$K$170))/(MAX($K$2:$K$170)-MIN($K$2:$K$170))*100 -> 10.893574 | AK38: =(L38-MIN($L$2:$L$170))/(MAX($L$2:$L$170)-MIN($L$2:$L$170))*100 -> 9.904641 | AL38: =(M38-MIN($M$2:$M$170))/(MAX($M$2:$M$170)-MIN($M$2:$M$170))*100 -> 30.052111 | AM38: =(N38-MIN($N$2:$N$170))/(MAX($N$2:$N$170)-MIN($N$2:$N$170))*100 -> 3.7804601 | AN38: =(O38-MIN($O$2:$O$170))/(MAX($O$2:$O$170)-MIN($O$2:$O$170))*100 -> 37.779294 | AO38: =(P38-MIN($P$2:$P$170))/(MAX($P$2:$P$170)-MIN($P$2:$P$170))*100 -> 7.2740731 | AP38: =(Q38-MIN($Q$2:$Q$170))/(MAX($Q$2:$Q$170)-MIN($Q$2:$Q$170))*100 -> 87 | AQ38: =IF(AP38>=50,AP38,50) -> 87 | AR38: =(#REF!-MIN(#REF!))/(MAX(#REF!)-MIN(#REF!))*100 -> #REF! | AS38: =IF(AR38>=50,AR38,50) -> #REF! | AT38: =(U38-MIN($U$2:$U$170))/(MAX($U$2:$U$170)-MIN($U$2:$U$170))*100 -> 21.251529 | AU38: =(V38-MIN($V$2:$V$170))/(MAX($V$2:$V$170)-MIN($V$2:$V$170))*100 -> 21.890187 | AV38: =(W38-MIN($W$2:$W$170))/(MAX($W$2:$W$170)-MIN($W$2:$W$170))*100 -> 0.62626984 | AW38: =(X38-MIN($X$2:$X$170))/(MAX($X$2:$X$170)-MIN($X$2:$X$170))*100 -> 21.152125 | AX38: =(Y38-MIN($Y$2:$Y$170))/(MAX($Y$2:$Y$170)-MIN($Y$2:$Y$170))*100 -> 21.479361 | AY38: =(Z38-MIN($Z$2:$Z$170))/(MAX($Z$2:$Z$170)-MIN($Z$2:$Z$170))*100 -> 6.4859485 | AZ38: =(AA38-MIN($AA$2:$AA$170))/(MAX($AA$2:$AA$170)-MIN($AA$2:$AA$170))*100 -> 11.952127 | BA38: =(AB38-MIN($AB$2:$AB$170))/(MAX($AB$2:$AB$170)-MIN($AB$2:$AB$170))*100 -> 3.3668773 | BB38: =(AC38-MIN($AC$2:$AC$170))/(MAX($AC$2:$AC$170)-MIN($AC$2:$AC$170))*100 -> 8.6501239 | BC38: 5.6 | BD38: 234880 | BE38: 0 | BF38: 0
A39: CALLAO | B39: CALLAO | C39: MI PERU | D39: 070107 | E39: 132 | F39: 67.25556 | G39: 0.50951181 | H39: 21 | I39: 1223985.9 | J39: 58285.045 | K39: 20 | L39: 1220858 | M39: 61043 | N39: 0 | O39: 0 | P39: 0 | Q39: 0.89 | R39: 3329952 | S39: 0 | T39: =IF((100-IFERROR(S39/R39*100,0))=100,50,(100-IFERROR(S39/R39*100,0))) -> 50 | U39: 1284 | V39: 11658568 | W39: 268791.89 | X39: 566 | Y39: 7504791 | Z39: 205941 | AD39: =(E39-MIN($E$2:$E$170))/(MAX($E$2:$E$170)-MIN($E$2:$E$170))*100 -> 0.87423418 | AE39: =(F39-MIN($F$2:$F$170))/(MAX($F$2:$F$170)-MIN($F$2:$F$170))*100 -> 0.57297987 | AF39: =(G39-MIN($G$2:$G$170))/(MAX($G$2:$G$170)-MIN($G$2:$G$170))*100 -> 13.804892 | AG39: =(H39-MIN($H$2:$H$170))/(MAX($H$2:$H$170)-MIN($H$2:$H$170))*100 -> 1.026393 | AH39: =(I39-MIN($I$2:$I$170))/(MAX($I$2:$I$170)-MIN($I$2:$I$170))*100 -> 0.91640447 | AI39: =(J39-MIN($J$2:$J$170))/(MAX($J$2:$J$170)-MIN($J$2:$J$170))*100 -> 29.632263 | AJ39: =(K39-MIN($K$2:$K$170))/(MAX($K$2:$K$170)-MIN($K$2:$K$170))*100 -> 1.0040161 | AK39: =(L39-MIN($L$2:$L$170))/(MAX($L$2:$L$170)-MIN($L$2:$L$170))*100 -> 0.94271251 | AL39: =(M39-MIN($M$2:$M$170))/(MAX($M$2:$M$170)-MIN($M$2:$M$170))*100 -> 31.034343 | AM39: =(N39-MIN($N$2:$N$170))/(MAX($N$2:$N$170)-MIN($N$2:$N$170))*100 -> 0 | AN39: =(O39-MIN($O$2:$O$170))/(MAX($O$2:$O$170)-MIN($O$2:$O$170))*100 -> 0 | AO39: =(P39-MIN($P$2:$P$170))/(MAX($P$2:$P$170)-MIN($P$2:$P$170))*100 -> 0 | AP39: =(Q39-MIN($Q$2:$Q$170))/(MAX($Q$2:$Q$170)-MIN($Q$2:$Q$170))*100 -> 89 | AQ39: =IF(AP39>=50,AP39,50) -> 89 | AR39: =(#REF!-MIN(#REF!))/(MAX(#REF!)-MIN(#REF!))*100 -> #REF! | AS39: =IF(AR39>=50,AR39,50) -> #REF! | AT39: =(U39-MIN($U$2:$U$170))/(MAX($U$2:$U$170)-MIN($U$2:$U$170))*100 -> 1.2701366 | AU39: =(V39-MIN($V$2:$V$170))/(MAX($V$2:$V$170)-MIN($V$2:$V$170))*100 -> 2.1026767 | AV39: =(W39-MIN($W$2:$W$170))/(MAX($W$2:$W$170)-MIN($W$2:$W$170))*100 -> 0.026229239 | AW39: =(X39-MIN($X$2:$X$170))/(MAX($X$2:$X$170)-MIN($X$2:$X$170))*100 -> 1.4296246 | AX39: =(Y39-MIN($Y$2:$Y$170))/(MAX($Y$2:$Y$170)-MIN($Y$2:$Y$170))*100 -> 2.314368 | AY39: =(Z39-MIN($Z$2:$Z$170))/(MAX($Z$2:$Z$170)-MIN($Z$2:$Z$170))*100 -> 0.27308732 | AZ39: =(AA39-MIN($AA$2:$AA$170))/(MAX($AA$2:$AA$170)-MIN($AA$2:$AA$170))*100 -> -0.0023553106 | BA39: =(AB39-MIN($AB$2:$AB$170))/(MAX($AB$2:$AB$170)-MIN($AB$2:$AB$170))*100 -> 0 | BB39: =(AC39-MIN($AC$2:$AC$170))/(MAX($AC$2:$AC$170)-MIN($AC$2:$AC$170))*100 -> -0.0010532589 | BC39: 0.5 | BD39: 21059 | BE39: 1 | BF39: 0.2
A40: CUSCO | B40: CUSCO | C40: CUSCO | D40: 080101 | E40: 2118 | F40: 1549.2146 | G40: 0.73145166 | H40: 271 | I40: 13168729 | J40: 48593.095 | K40: 265 | L40: 12687599 | M40: 47878 | N40: 1115680.4 | O40: 58609.35 | P40: 2364743.5 | Q40: 0.92 | R40: 35913480 | S40: 544785.6 | T40: =IF((100-IFERROR(S40/R40*100,0))=100,50,(100-IFERROR(S40/R40*100,0))) -> 98.483061 | U40: 18690 | V40: 74295098 | W40: 55291327 | X40: 8033 | Y40: 45955154 | Z40: 38301843 | AA40: 909572 | AB40: 1.7742587e+08 | AC40: 1765695 | AD40: =(E40-MIN($E$2:$E$170))/(MAX($E$2:$E$170)-MIN($E$2:$E$170))*100 -> 14.545329 | AE40: =(F40-MIN($F$2:$F$170))/(MAX($F$2:$F$170)-MIN($F$2:$F$170))*100 -> 13.679787 | AF40: =(G40-MIN($G$2:$G$170))/(MAX($G$2:$G$170)-MIN($G$2:$G$170))*100 -> 33.36176 | AG40: =(H40-MIN($H$2:$H$170))/(MAX($H$2:$H$170)-MIN($H$2:$H$170))*100 -> 13.245357 | AH40: =(I40-MIN($I$2:$I$170))/(MAX($I$2:$I$170)-MIN($I$2:$I$170))*100 -> 9.8594937 | AI40: =(J40-MIN($J$2:$J$170))/(MAX($J$2:$J$170)-MIN($J$2:$J$170))*100 -> 24.704851 | AJ40: =(K40-MIN($K$2:$K$170))/(MAX($K$2:$K$170)-MIN($K$2:$K$170))*100 -> 13.303213 | AK40: =(L40-MIN($L$2:$L$170))/(MAX($L$2:$L$170)-MIN($L$2:$L$170))*100 -> 9.7970102 | AL40: =(M40-MIN($M$2:$M$170))/(MAX($M$2:$M$170)-MIN($M$2:$M$170))*100 -> 24.341239 | AM40: =(N40-MIN($N$2:$N$170))/(MAX($N$2:$N$170)-MIN($N$2:$N$170))*100 -> 11.946898 | AN40: =(O40-MIN($O$2:$O$170))/(MAX($O$2:$O$170)-MIN($O$2:$O$170))*100 -> 21.711727 | AO40: =(P40-MIN($P$2:$P$170))/(MAX($P$2:$P$170)-MIN($P$2:$P$170))*100 -> 9.6090676 | AP40: =(Q40-MIN($Q$2:$Q$170))/(MAX($Q$2:$Q$170)-MIN($Q$2:$Q$170))*100 -> 92 | AQ40: =IF(AP40>=50,AP40,50) -> 92 | AR40: =(#REF!-MIN(#REF!))/(MAX(#REF!)-MIN(#REF!))*100 -> #REF! | AS40: =IF(AR40>=50,AR40,50) -> #REF! | AT40: =(U40-MIN($U$2:$U$170))/(MAX($U$2:$U$170)-MIN($U$2:$U$170))*100 -> 19.46602 | AU40: =(V40-MIN($V$2:$V$170))/(MAX($V$2:$V$170)-MIN($V$2:$V$170))*100 -> 13.512687 | AV40: =(W40-MIN($W$2:$W$170))/(MAX($W$2:$W$170)-MIN($W$2:$W$170))*100 -> 5.398814 | AW40: =(X40-MIN($X$2:$X$170))/(MAX($X$2:$X$170)-MIN($X$2:$X$170))*100 -> 21.088937 | AX40: =(Y40-MIN($Y$2:$Y$170))/(MAX($Y$2:$Y$170)-MIN($Y$2:$Y$170))*100 -> 14.268702 | AY40: =(Z40-MIN($Z$2:$Z$170))/(MAX($Z$2:$Z$170)-MIN($Z$2:$Z$170))*100 -> 50.831509 | AZ40: =(AA40-MIN($AA$2:$AA$170))/(MAX($AA$2:$AA$170)-MIN($AA$2:$AA$170))*100 -> 37.582286 | BA40: =(AB40-MIN($AB$2:$AB$170))/(MAX($AB$2:$AB$170)-MIN($AB$2:$AB$170))*100 -> 32.177985 | BB40: =(AC40-MIN($AC$2:$AC$170))/(MAX($AC$2:$AC$170)-MIN($AC$2:$AC$170))*100 -> 28.610239 | BC40: 7.5 | BD40: 348136 | BE40: 4 | BF40: 3.3
A41: CUSCO | B41: CUSCO | C41: SAN JERONIMO | D41: 080104 | E41: 558 | F41: 323.043 | G41: 0.57893011 | H41: 89 | I41: 4950386.8 | J41: 55622.324 | K41: 86 | L41: 4879651 | M41: 56740 | N41: 276892.46 | O41: 40664.24 | P41: 570154.51 | Q41: 0.91 | R41: 12571293 | S41: 285702.79 | T41: =IF((100-IFERROR(S41/R41*100,0))=100,50,(100-IFERROR(S41/R41*100,0))) -> 97.72734 | U41: 5953 | V41: 16445911 | W41: 2633826.9 | X41: 2691 | Y41: 10264428 | Z41: 1401813 | AA41: 216511 | AB41: 1.1082902e+08 | AC41: 398083 | AD41: =(E41-MIN($E$2:$E$170))/(MAX($E$2:$E$170)-MIN($E$2:$E$170))*100 -> 3.8067048 | AE41: =(F41-MIN($F$2:$F$170))/(MAX($F$2:$F$170)-MIN($F$2:$F$170))*100 -> 2.8352264 | AF41: =(G41-MIN($G$2:$G$170))/(MAX($G$2:$G$170)-MIN($G$2:$G$170))*100 -> 19.921885 | AG41: =(H41-MIN($H$2:$H$170))/(MAX($H$2:$H$170)-MIN($H$2:$H$170))*100 -> 4.3499511 | AH41: =(I41-MIN($I$2:$I$170))/(MAX($I$2:$I$170)-MIN($I$2:$I$170))*100 -> 3.7063796 | AI41: =(J41-MIN($J$2:$J$170))/(MAX($J$2:$J$170)-MIN($J$2:$J$170))*100 -> 28.278529 | AJ41: =(K41-MIN($K$2:$K$170))/(MAX($K$2:$K$170)-MIN($K$2:$K$170))*100 -> 4.3172691 | AK41: =(L41-MIN($L$2:$L$170))/(MAX($L$2:$L$170)-MIN($L$2:$L$170))*100 -> 3.7679305 | AL41: =(M41-MIN($M$2:$M$170))/(MAX($M$2:$M$170)-MIN($M$2:$M$170))*100 -> 28.846692 | AM41: =(N41-MIN($N$2:$N$170))/(MAX($N$2:$N$170)-MIN($N$2:$N$170))*100 -> 2.9650122 | AN41: =(O41-MIN($O$2:$O$170))/(MAX($O$2:$O$170)-MIN($O$2:$O$170))*100 -> 15.063994 | AO41: =(P41-MIN($P$2:$P$170))/(MAX($P$2:$P$170)-MIN($P$2:$P$170))*100 -> 2.3168065 | AP41: =(Q41-MIN($Q$2:$Q$170))/(MAX($Q$2:$Q$170)-MIN($Q$2:$Q$170))*100 -> 91 | AQ41: =IF(AP41>=50,AP41,50) -> 91 | AR41: =(#REF!-MIN(#REF!))/(MAX(#REF!)-MIN(#REF!))*100 -> #REF! | AS41: =IF(AR41>=50,AR41,50) -> #REF! | AT41: =(U41-MIN($U$2:$U$170))/(MAX($U$2:$U$170)-MIN($U$2:$U$170))*100 -> 6.1510156 | AU41: =(V41-MIN($V$2:$V$170))/(MAX($V$2:$V$170)-MIN($V$2:$V$170))*100 -> 2.97475 | AV41: =(W41-MIN($W$2:$W$170))/(MAX($W$2:$W$170)-MIN($W$2:$W$170))*100 -> 0.25715918 | AW41: =(X41-MIN($X$2:$X$170))/(MAX($X$2:$X$170)-MIN($X$2:$X$170))*100 -> 7.02438 | AX41: =(Y41-MIN($Y$2:$Y$170))/(MAX($Y$2:$Y$170)-MIN($Y$2:$Y$170))*100 -> 3.1723475 | AY41: =(Z41-MIN($Z$2:$Z$170))/(MAX($Z$2:$Z$170)-MIN($Z$2:$Z$170))*100 -> 1.8601714 | AZ41: =(AA41-MIN($AA$2:$AA$170))/(MAX($AA$2:$AA$170)-MIN($AA$2:$AA$170))*100 -> 8.9441473 | BA41: =(AB41-MIN($AB$2:$AB$170))/(MAX($AB$2:$AB$170)-MIN($AB$2:$AB$170))*100 -> 20.09997 | BB41: =(AC41-MIN($AC$2:$AC$170))/(MAX($AC$2:$AC$170)-MIN($AC$2:$AC$170))*100 -> 6.4494771 | BC41: 1 | BD41: 48565 | BE41: 0 | BF41: 0
A42: CUSCO | B42: CUSCO | C42: SAN SEBASTIAN | D42: 080105 | E42: 709 | F42: 422.48677 | G42: 0.59589107 | H42: 135 | I42: 5958206.9 | J42: 44134.866 | K42: 129 | L42: 5894660 | M42: 45695 | N42: 442945.06 | O42: 54403.9 | P42: 1864138.4 | Q42: 0.93 | R42: 23818169 | S42: 104393.46 | T42: =IF((100-IFERROR(S42/R42*100,0))=100,50,(100-IFERROR(S42/R42*100,0))) -> 99.561707 | U42: 10704 | V42: 32328561 | W42: 5946941.7 | X42: 4532 | Y42: 19251353 | Z42: 5523199 | AA42: 90825 | AB42: 6133200 | AC42: 142963 | AD42: =(E42-MIN($E$2:$E$170))/(MAX($E$2:$E$170)-MIN($E$2:$E$170))*100 -> 4.8461486 | AE42: =(F42-MIN($F$2:$F$170))/(MAX($F$2:$F$170)-MIN($F$2:$F$170))*100 -> 3.7147314 | AF42: =(G42-MIN($G$2:$G$170))/(MAX($G$2:$G$170)-MIN($G$2:$G$170))*100 -> 21.416449 | AG42: =(H42-MIN($H$2:$H$170))/(MAX($H$2:$H$170)-MIN($H$2:$H$170))*100 -> 6.5982405 | AH42: =(I42-MIN($I$2:$I$170))/(MAX($I$2:$I$170)-MIN($I$2:$I$170))*100 -> 4.4609396 | AI42: =(J42-MIN($J$2:$J$170))/(MAX($J$2:$J$170)-MIN($J$2:$J$170))*100 -> 22.438276 | AJ42: =(K42-MIN($K$2:$K$170))/(MAX($K$2:$K$170)-MIN($K$2:$K$170))*100 -> 6.4759036 | AK42: =(L42-MIN($L$2:$L$170))/(MAX($L$2:$L$170)-MIN($L$2:$L$170))*100 -> 4.5516921 | AL42: =(M42-MIN($M$2:$M$170))/(MAX($M$2:$M$170)-MIN($M$2:$M$170))*100 -> 23.231399 | AM42: =(N42-MIN($N$2:$N$170))/(MAX($N$2:$N$170)-MIN($N$2:$N$170))*100 -> 4.743132 | AN42: =(O42-MIN($O$2:$O$170))/(MAX($O$2:$O$170)-MIN($O$2:$O$170))*100 -> 20.153826 | AO42: =(P42-MIN($P$2:$P$170))/(MAX($P$2:$P$170)-MIN($P$2:$P$170))*100 -> 7.5748732 | AP42: =(Q42-MIN($Q$2:$Q$170))/(MAX($Q$2:$Q$170)-MIN($Q$2:$Q$170))*100 -> 93 | AQ42: =IF(AP42>=50,AP42,50) -> 93 | AR42: =(#REF!-MIN(#REF!))/(MAX(#REF!)-MIN(#REF!))*100 -> #REF! | AS42: =IF(AR42>=50,AR42,50) -> #REF! | AT42: =(U42-MIN($U$2:$U$170))/(MAX($U$2:$U$170)-MIN($U$2:$U$170))*100 -> 11.117616 | AU42: =(V42-MIN($V$2:$V$170))/(MAX($V$2:$V$170)-MIN($V$2:$V$170))*100 -> 5.867969 | AV42: =(W42-MIN($W$2:$W$170))/(MAX($W$2:$W$170)-MIN($W$2:$W$170))*100 -> 0.58066282 | AW42: =(X42-MIN($X$2:$X$170))/(MAX($X$2:$X$170)-MIN($X$2:$X$170))*100 -> 11.871413 | AX42: =(Y42-MIN($Y$2:$Y$170))/(MAX($Y$2:$Y$170)-MIN($Y$2:$Y$170))*100 -> 5.9664097 | AY42: =(Z42-MIN($Z$2:$Z$170))/(MAX($Z$2:$Z$170)-MIN($Z$2:$Z$170))*100 -> 7.3298089 | AZ42: =(AA42-MIN($AA$2:$AA$170))/(MAX($AA$2:$AA$170)-MIN($AA$2:$AA$170))*100 -> 3.7506462 | BA42: =(AB42-MIN($AB$2:$AB$170))/(MAX($AB$2:$AB$170)-MIN($AB$2:$AB$170))*100 -> 1.1123182 | BB42: =(AC42-MIN($AC$2:$AC$170))/(MAX($AC$2:$AC$170)-MIN($AC$2:$AC$170))*100 -> 2.3155168 | BC42: 3.6 | BD42: 163263 | BE42: 2 | BF42: 0.3
A43: CUSCO | B43: CUSCO | C43: SANTIAGO | D43: 080106 | E43: 764 | F43: 436.12625 | G43: 0.57084587 | H43: 83 | I43: 3847056.3 | J43: 46350.076 | K43: 81 | L43: 3814007 | M43: 47087 | N43: 236627.68 | O43: 32335.07 | P43: 947134.19 | Q43: 0.89 | R43: 10301118 | S43: 958998.65 | T43: =IF((100-IFERROR(S43/R43*100,0))=100,50,(100-IFERROR(S43/R43*100,0))) -> 90.690344 | U43: 10011 | V43: 30318977 | W43: 4896645.3 | X43: 4149 | Y43: 17661127 | Z43: 2696795 | AA43: 13402 | AB43: 575517.39 | AC43: 21900 | AD43: =(E43-MIN($E$2:$E$170))/(MAX($E$2:$E$170)-MIN($E$2:$E$170))*100 -> 5.2247539 | AE43: =(F43-MIN($F$2:$F$170))/(MAX($F$2:$F$170)-MIN($F$2:$F$170))*100 -> 3.8353622 | AF43: =(G43-MIN($G$2:$G$170))/(MAX($G$2:$G$170)-MIN($G$2:$G$170))*100 -> 19.209519 | AG43: =(H43-MIN($H$2:$H$170))/(MAX($H$2:$H$170)-MIN($H$2:$H$170))*100 -> 4.056696 | AH43: =(I43-MIN($I$2:$I$170))/(MAX($I$2:$I$170)-MIN($I$2:$I$170))*100 -> 2.8803105 | AI43: =(J43-MIN($J$2:$J$170))/(MAX($J$2:$J$170)-MIN($J$2:$J$170))*100 -> 23.564495 | AJ43: =(K43-MIN($K$2:$K$170))/(MAX($K$2:$K$170)-MIN($K$2:$K$170))*100 -> 4.0662651 | AK43: =(L43-MIN($L$2:$L$170))/(MAX($L$2:$L$170)-MIN($L$2:$L$170))*100 -> 2.9450699 | AL43: =(M43-MIN($M$2:$M$170))/(MAX($M$2:$M$170)-MIN($M$2:$M$170))*100 -> 23.939094 | AM43: =(N43-MIN($N$2:$N$170))/(MAX($N$2:$N$170)-MIN($N$2:$N$170))*100 -> 2.53385 | AN43: =(O43-MIN($O$2:$O$170))/(MAX($O$2:$O$170)-MIN($O$2:$O$170))*100 -> 11.978468 | AO43: =(P43-MIN($P$2:$P$170))/(MAX($P$2:$P$170)-MIN($P$2:$P$170))*100 -> 3.8486527 | AP43: =(Q43-MIN($Q$2:$Q$170))/(MAX($Q$2:$Q$170)-MIN($Q$2:$Q$170))*100 -> 89 | AQ43: =IF(AP43>=50,AP43,50) -> 89 | AR43: =(#REF!-MIN(#REF!))/(MAX(#REF!)-MIN(#REF!))*100 -> #REF! | AS43: =IF(AR43>=50,AR43,50) -> #REF! | AT43: =(U43-MIN($U$2:$U$170))/(MAX($U$2:$U$170)-MIN($U$2:$U$170))*100 -> 10.393167 | AU43: =(V43-MIN($V$2:$V$170))/(MAX($V$2:$V$170)-MIN($V$2:$V$170))*100 -> 5.5018986 | AV43: =(W43-MIN($W$2:$W$170))/(MAX($W$2:$W$170)-MIN($W$2:$W$170))*100 -> 0.47810836 | AW43: =(X43-MIN($X$2:$X$170))/(MAX($X$2:$X$170)-MIN($X$2:$X$170))*100 -> 10.86304 | AX43: =(Y43-MIN($Y$2:$Y$170))/(MAX($Y$2:$Y$170)-MIN($Y$2:$Y$170))*100 -> 5.4720036 | AY43: =(Z43-MIN($Z$2:$Z$170))/(MAX($Z$2:$Z$170)-MIN($Z$2:$Z$170))*100 -> 3.578788 | AZ43: =(AA43-MIN($AA$2:$AA$170))/(MAX($AA$2:$AA$170)-MIN($AA$2:$AA$170))*100 -> 0.55143193 | BA43: =(AB43-MIN($AB$2:$AB$170))/(MAX($AB$2:$AB$170)-MIN($AB$2:$AB$170))*100 -> 0.10437593 | BB43: =(AC43-MIN($AC$2:$AC$170))/(MAX($AC$2:$AC$170)-MIN($AC$2:$AC$170))*100 -> 0.35381398 | BC43: 3.1 | BD43: 129034 | BE43: 2 | BF43: 0.4
A44: CUSCO | B44: CUSCO | C44: WANCHAQ | D44: 080108 | E44: 2052 | F44: 1502.9159 | G44: 0.73241514 | H44: 238 | I44: 14484891 | J44: 60860.887 | K44: 233 | L44: 14403947 | M44: 61820 | N44: 640225.3 | O44: 53382.33 | P44: 2087635.9 | Q44: 0.91 | R44: 37499040 | S44: 758984.1 | T44: =IF((100-IFERROR(S44/R44*100,0))=100,50,(100-IFERROR(S44/R44*100,0))) -> 97.975991 | U44: 13389 | V44: 47716505 | W44: 15707301 | X44: 5621 | Y44: 26912087 | Z44: 14217976 | AA44: 446792 | AB44: 36842111 | AC44: 789576 | AD44: =(E44-MIN($E$2:$E$170))/(MAX($E$2:$E$170)-MIN($E$2:$E$170))*100 -> 14.091003 | AE44: =(F44-MIN($F$2:$F$170))/(MAX($F$2:$F$170)-MIN($F$2:$F$170))*100 -> 13.27031 | AF44: =(G44-MIN($G$2:$G$170))/(MAX($G$2:$G$170)-MIN($G$2:$G$170))*100 -> 33.44666 | AG44: =(H44-MIN($H$2:$H$170))/(MAX($H$2:$H$170)-MIN($H$2:$H$170))*100 -> 11.632454 | AH44: =(I44-MIN($I$2:$I$170))/(MAX($I$2:$I$170)-MIN($I$2:$I$170))*100 -> 10.844911 | AI44: =(J44-MIN($J$2:$J$170))/(MAX($J$2:$J$170)-MIN($J$2:$J$170))*100 -> 30.941827 | AJ44: =(K44-MIN($K$2:$K$170))/(MAX($K$2:$K$170)-MIN($K$2:$K$170))*100 -> 11.696787 | AK44: =(L44-MIN($L$2:$L$170))/(MAX($L$2:$L$170)-MIN($L$2:$L$170))*100 -> 11.122326 | AL44: =(M44-MIN($M$2:$M$170))/(MAX($M$2:$M$170)-MIN($M$2:$M$170))*100 -> 31.42937 | AM44: =(N44-MIN($N$2:$N$170))/(MAX($N$2:$N$170)-MIN($N$2:$N$170))*100 -> 6.8556428 | AN44: =(O44-MIN($O$2:$O$170))/(MAX($O$2:$O$170)-MIN($O$2:$O$170))*100 -> 19.775387 | AO44: =(P44-MIN($P$2:$P$170))/(MAX($P$2:$P$170)-MIN($P$2:$P$170))*100 -> 8.4830489 | AP44: =(Q44-MIN($Q$2:$Q$170))/(MAX($Q$2:$Q$170)-MIN($Q$2:$Q$170))*100 -> 91 | AQ44: =IF(AP44>=50,AP44,50) -> 91 | AR44: =(#REF!-MIN(#REF!))/(MAX(#REF!)-MIN(#REF!))*100 -> #REF! | AS44: =IF(AR44>=50,AR44,50) -> #REF! | AT44: =(U44-MIN($U$2:$U$170))/(MAX($U$2:$U$170)-MIN($U$2:$U$170))*100 -> 13.924461 | AU44: =(V44-MIN($V$2:$V$170))/(MAX($V$2:$V$170)-MIN($V$2:$V$170))*100 -> 8.6710713 | AV44: =(W44-MIN($W$2:$W$170))/(MAX($W$2:$W$170)-MIN($W$2:$W$170))*100 -> 1.5336971 | AW44: =(X44-MIN($X$2:$X$170))/(MAX($X$2:$X$170)-MIN($X$2:$X$170))*100 -> 14.73856 | AX44: =(Y44-MIN($Y$2:$Y$170))/(MAX($Y$2:$Y$170)-MIN($Y$2:$Y$170))*100 -> 8.348155 | AY44: =(Z44-MIN($Z$2:$Z$170))/(MAX($Z$2:$Z$170)-MIN($Z$2:$Z$170))*100 -> 18.868956 | AZ44: =(AA44-MIN($AA$2:$AA$170))/(MAX($AA$2:$AA$170)-MIN($AA$2:$AA$170))*100 -> 18.459643 | BA44: =(AB44-MIN($AB$2:$AB$170))/(MAX($AB$2:$AB$170)-MIN($AB$2:$AB$170))*100 -> 6.6816913 | BB44: =(AC44-MIN($AC$2:$AC$170))/(MAX($AC$2:$AC$170)-MIN($AC$2:$AC$170))*100 -> 12.793223 | BC44: 5.8 | BD44: 277381 | BE44: 6 | BF44: 3
A45: HUÁNUCO | B45: HUÁNUCO | C45: HUANUCO | D45: 100101 | E45: 1984 | F45: 1502.5052 | G45: 0.75731108 | H45: 98 | I45: 4654236.1 | J45: 47492.205 | K45: 91 | L45: 4451801 | M45: 48921 | N45: 758868.55 | O45: 84973.48 | P45: 940892.29 | Q45: 0.8 | R45: 12492491 | S45: 585798.26 | T45: =IF((100-IFERROR(S45/R45*100,0))=100,50,(100-IFERROR(S45/R45*100,0))) -> 95.310797 | U45: 13227 | V45: 52781904 | W45: 5492154.8 | X45: 4208 | Y45: 30380531 | Z45: 3293512 | AA45: 675953 | AB45: 1.2280711e+08 | AC45: 1492986 | AD45: =(E45-MIN($E$2:$E$170))/(MAX($E$2:$E$170)-MIN($E$2:$E$170))*100 -> 13.622909 | AE45: =(F45-MIN($F$2:$F$170))/(MAX($F$2:$F$170)-MIN($F$2:$F$170))*100 -> 13.266678 | AF45: =(G45-MIN($G$2:$G$170))/(MAX($G$2:$G$170)-MIN($G$2:$G$170))*100 -> 35.640438 | AG45: =(H45-MIN($H$2:$H$170))/(MAX($H$2:$H$170)-MIN($H$2:$H$170))*100 -> 4.7898338 | AH45: =(I45-MIN($I$2:$I$170))/(MAX($I$2:$I$170)-MIN($I$2:$I$170))*100 -> 3.4846501 | AI45: =(J45-MIN($J$2:$J$170))/(MAX($J$2:$J$170)-MIN($J$2:$J$170))*100 -> 24.145156 | AJ45: =(K45-MIN($K$2:$K$170))/(MAX($K$2:$K$170)-MIN($K$2:$K$170))*100 -> 4.5682731 | AK45: =(L45-MIN($L$2:$L$170))/(MAX($L$2:$L$170)-MIN($L$2:$L$170))*100 -> 3.4375566 | AL45: =(M45-MIN($M$2:$M$170))/(MAX($M$2:$M$170)-MIN($M$2:$M$170))*100 -> 24.871502 | AM45: =(N45-MIN($N$2:$N$170))/(MAX($N$2:$N$170)-MIN($N$2:$N$170))*100 -> 8.1260952 | AN45: =(O45-MIN($O$2:$O$170))/(MAX($O$2:$O$170)-MIN($O$2:$O$170))*100 -> 31.478271 | AO45: =(P45-MIN($P$2:$P$170))/(MAX($P$2:$P$170)-MIN($P$2:$P$170))*100 -> 3.8232889 | AP45: =(Q45-MIN($Q$2:$Q$170))/(MAX($Q$2:$Q$170)-MIN($Q$2:$Q$170))*100 -> 80 | AQ45: =IF(AP45>=50,AP45,50) -> 80 | AR45: =(#REF!-MIN(#REF!))/(MAX(#REF!)-MIN(#REF!))*100 -> #REF! | AS45: =IF(AR45>=50,AR45,50) -> #REF! | AT45: =(U45-MIN($U$2:$U$170))/(MAX($U$2:$U$170)-MIN($U$2:$U$170))*100 -> 13.755109 | AU45: =(V45-MIN($V$2:$V$170))/(MAX($V$2:$V$170)-MIN($V$2:$V$170))*100 -> 9.5937958 | AV45: =(W45-MIN($W$2:$W$170))/(MAX($W$2:$W$170)-MIN($W$2:$W$170))*100 -> 0.5362559 | AW45: =(X45-MIN($X$2:$X$170))/(MAX($X$2:$X$170)-MIN($X$2:$X$170))*100 -> 11.018377 | AX45: =(Y45-MIN($Y$2:$Y$170))/(MAX($Y$2:$Y$170)-MIN($Y$2:$Y$170))*100 -> 9.4265047 | AY45: =(Z45-MIN($Z$2:$Z$170))/(MAX($Z$2:$Z$170)-MIN($Z$2:$Z$170))*100 -> 4.3707122 | AZ45: =(AA45-MIN($AA$2:$AA$170))/(MAX($AA$2:$AA$170)-MIN($AA$2:$AA$170))*100 -> 27.92886 | BA45: =(AB45-MIN($AB$2:$AB$170))/(MAX($AB$2:$AB$170)-MIN($AB$2:$AB$170))*100 -> 22.272317 | BB45: =(AC45-MIN($AC$2:$AC$170))/(MAX($AC$2:$AC$170)-MIN($AC$2:$AC$170))*100 -> 24.191267 | BC45: 4.5 | BD45: 213876 | BE45: 2 | BF45: 1.5
A46: HUÁNUCO | B46: HUÁNUCO | C46: AMARILIS | D46: 100102 | E46: 561 | F46: 378.3779 | G46: 0.67447041 | H46: 50 | I46: 2372777.2 | J46: 47455.543 | K46: 46 | L46: 1947110 | M46: 42328 | N46: 5397.16 | O46: 39.58 | P46: 468495.39 | Q46: 0.83 | R46: 6530998.8 | S46: 515800.88 | T46: =IF((100-IFERROR(S46/R46*100,0))=100,50,(100-IFERROR(S46/R46*100,0))) -> 92.102266 | U46: 8000 | V46: 22569107 | W46: 2155018.8 | X46: 2387 | Y46: 11105375 | Z46: 1170272 | AA46: 104282 | AB46: 5029121 | AC46: 186463 | AD46: =(E46-MIN($E$2:$E$170))/(MAX($E$2:$E$170)-MIN($E$2:$E$170))*100 -> 3.827356 | AE46: =(F46-MIN($F$2:$F$170))/(MAX($F$2:$F$170)-MIN($F$2:$F$170))*100 -> 3.3246218 | AF46: =(G46-MIN($G$2:$G$170))/(MAX($G$2:$G$170)-MIN($G$2:$G$170))*100 -> 28.340693 | AG46: =(H46-MIN($H$2:$H$170))/(MAX($H$2:$H$170)-MIN($H$2:$H$170))*100 -> 2.4437928 | AH46: =(I46-MIN($I$2:$I$170))/(MAX($I$2:$I$170)-MIN($I$2:$I$170))*100 -> 1.7765103 | AI46: =(J46-MIN($J$2:$J$170))/(MAX($J$2:$J$170)-MIN($J$2:$J$170))*100 -> 24.126517 | AJ46: =(K46-MIN($K$2:$K$170))/(MAX($K$2:$K$170)-MIN($K$2:$K$170))*100 -> 2.3092369 | AK46: =(L46-MIN($L$2:$L$170))/(MAX($L$2:$L$170)-MIN($L$2:$L$170))*100 -> 1.5035041 | AL46: =(M46-MIN($M$2:$M$170))/(MAX($M$2:$M$170)-MIN($M$2:$M$170))*100 -> 21.519612 | AM46: =(N46-MIN($N$2:$N$170))/(MAX($N$2:$N$170)-MIN($N$2:$N$170))*100 -> 0.057793719 | AN46: =(O46-MIN($O$2:$O$170))/(MAX($O$2:$O$170)-MIN($O$2:$O$170))*100 -> 0.014662339 | AO46: =(P46-MIN($P$2:$P$170))/(MAX($P$2:$P$170)-MIN($P$2:$P$170))*100 -> 1.9037176 | AP46: =(Q46-MIN($Q$2:$Q$170))/(MAX($Q$2:$Q$170)-MIN($Q$2:$Q$170))*100 -> 83 | AQ46: =IF(AP46>=50,AP46,50) -> 83 | AR46: =(#REF!-MIN(#REF!))/(MAX(#REF!)-MIN(#REF!))*100 -> #REF! | AS46: =IF(AR46>=50,AR46,50) -> #REF! | AT46: =(U46-MIN($U$2:$U$170))/(MAX($U$2:$U$170)-MIN($U$2:$U$170))*100 -> 8.2909083 | AU46: =(V46-MIN($V$2:$V$170))/(MAX($V$2:$V$170)-MIN($V$2:$V$170))*100 -> 4.0901651 | AV46: =(W46-MIN($W$2:$W$170))/(MAX($W$2:$W$170)-MIN($W$2:$W$170))*100 -> 0.21040676 | AW46: =(X46-MIN($X$2:$X$170))/(MAX($X$2:$X$170)-MIN($X$2:$X$170))*100 -> 6.2240008 | AX46: =(Y46-MIN($Y$2:$Y$170))/(MAX($Y$2:$Y$170)-MIN($Y$2:$Y$170))*100 -> 3.4338005 | AY46: =(Z46-MIN($Z$2:$Z$170))/(MAX($Z$2:$Z$170)-MIN($Z$2:$Z$170))*100 -> 1.5528852 | AZ46: =(AA46-MIN($AA$2:$AA$170))/(MAX($AA$2:$AA$170)-MIN($AA$2:$AA$170))*100 -> 4.3067061 | BA46: =(AB46-MIN($AB$2:$AB$170))/(MAX($AB$2:$AB$170)-MIN($AB$2:$AB$170))*100 -> 0.9120822 | BB46: =(AC46-MIN($AC$2:$AC$170))/(MAX($AC$2:$AC$170)-MIN($AC$2:$AC$170))*100 -> 3.0203901 | BC46: 2 | BD46: 91142 | BE46: 0 | BF46: 0
A47: HUÁNUCO | B47: HUÁNUCO | C47: PILLCO MARCA | D47: 100111 | E47: 235 | F47: 150.64109 | G47: 0.64102591 | H47: 8 | I47: 399971.75 | J47: 49996.469 | K47: 8 | L47: 399972 | M47: 49996 | N47: 18179.48 | O47: 3263.13 | P47: 0 | Q47: 0.83 | R47: 333524.33 | S47: 0 | T47: =IF((100-IFERROR(S47/R47*100,0))=100,50,(100-IFERROR(S47/R47*100,0))) -> 50 | U47: 3392 | V47: 10220822 | W47: 473301.8 | X47: 1137 | Y47: 6479393 | Z47: 221323 | AA47: 13807 | AB47: 598264.64 | AC47: 20022 | AD47: =(E47-MIN($E$2:$E$170))/(MAX($E$2:$E$170)-MIN($E$2:$E$170))*100 -> 1.5832588 | AE47: =(F47-MIN($F$2:$F$170))/(MAX($F$2:$F$170)-MIN($F$2:$F$170))*100 -> 1.3104618 | AF47: =(G47-MIN($G$2:$G$170))/(MAX($G$2:$G$170)-MIN($G$2:$G$170))*100 -> 25.393635 | AG47: =(H47-MIN($H$2:$H$170))/(MAX($H$2:$H$170)-MIN($H$2:$H$170))*100 -> 0.39100684 | AH47: =(I47-MIN($I$2:$I$170))/(MAX($I$2:$I$170)-MIN($I$2:$I$170))*100 -> 0.29946087 | AI47: =(J47-MIN($J$2:$J$170))/(MAX($J$2:$J$170)-MIN($J$2:$J$170))*100 -> 25.41833 | AJ47: =(K47-MIN($K$2:$K$170))/(MAX($K$2:$K$170)-MIN($K$2:$K$170))*100 -> 0.40160643 | AK47: =(L47-MIN($L$2:$L$170))/(MAX($L$2:$L$170)-MIN($L$2:$L$170))*100 -> 0.30884723 | AL47: =(M47-MIN($M$2:$M$170))/(MAX($M$2:$M$170)-MIN($M$2:$M$170))*100 -> 25.418033 | AM47: =(N47-MIN($N$2:$N$170))/(MAX($N$2:$N$170)-MIN($N$2:$N$170))*100 -> 0.194669 | AN47: =(O47-MIN($O$2:$O$170))/(MAX($O$2:$O$170)-MIN($O$2:$O$170))*100 -> 1.2088206 | AO47: =(P47-MIN($P$2:$P$170))/(MAX($P$2:$P$170)-MIN($P$2:$P$170))*100 -> 0 | AP47: =(Q47-MIN($Q$2:$Q$170))/(MAX($Q$2:$Q$170)-MIN($Q$2:$Q$170))*100 -> 83 | AQ47: =IF(AP47>=50,AP47,50) -> 83 | AR47: =(#REF!-MIN(#REF!))/(MAX(#REF!)-MIN(#REF!))*100 -> #REF! | AS47: =IF(AR47>=50,AR47,50) -> #REF! | AT47: =(U47-MIN($U$2:$U$170))/(MAX($U$2:$U$170)-MIN($U$2:$U$170))*100 -> 3.4737976 | AU47: =(V47-MIN($V$2:$V$170))/(MAX($V$2:$V$170)-MIN($V$2:$V$170))*100 -> 1.8407737 | AV47: =(W47-MIN($W$2:$W$170))/(MAX($W$2:$W$170)-MIN($W$2:$W$170))*100 -> 0.046198273 | AW47: =(X47-MIN($X$2:$X$170))/(MAX($X$2:$X$170)-MIN($X$2:$X$170))*100 -> 2.9329682 | AX47: =(Y47-MIN($Y$2:$Y$170))/(MAX($Y$2:$Y$170)-MIN($Y$2:$Y$170))*100 -> 1.9955687 | AY47: =(Z47-MIN($Z$2:$Z$170))/(MAX($Z$2:$Z$170)-MIN($Z$2:$Z$170))*100 -> 0.29350131 | AZ47: =(AA47-MIN($AA$2:$AA$170))/(MAX($AA$2:$AA$170)-MIN($AA$2:$AA$170))*100 -> 0.56816703 | BA47: =(AB47-MIN($AB$2:$AB$170))/(MAX($AB$2:$AB$170)-MIN($AB$2:$AB$170))*100 -> 0.10850137 | BB47: =(AC47-MIN($AC$2:$AC$170))/(MAX($AC$2:$AC$170)-MIN($AC$2:$AC$170))*100 -> 0.3233829 | BC47: 0.6 | BD47: 26287 | BE47: 0 | BF47: 0
A48: ICA | B48: ICA | C48: ICA | D48: 110101 | E48: 2669 | F48: 1989.9488 | G48: 0.74557841 | H48: 215 | I48: 12449270 | J48: 57903.582 | K48: 213 | L48: 12424888 | M48: 58333 | N48: 939385.3 | O48: 106433.96 | P48: 3325832.8 | Q48: 0.9 | R48: 33810531 | S48: 299365.93 | T48: =IF((100-IFERROR(S48/R48*100,0))=100,50,(100-IFERROR(S48/R48*100,0))) -> 99.114578 | U48: 19811 | V48: 1.5056391e+08 | W48: 19362894 | X48: 8409 | Y48: 94452734 | Z48: 15927085 | AA48: 1061899 | AB48: 2.1294557e+08 | AC48: 2793793 | AD48: =(E48-MIN($E$2:$E$170))/(MAX($E$2:$E$170)-MIN($E$2:$E$170))*100 -> 18.338267 | AE48: =(F48-MIN($F$2:$F$170))/(MAX($F$2:$F$170)-MIN($F$2:$F$170))*100 -> 17.577748 | AF48: =(G48-MIN($G$2:$G$170))/(MAX($G$2:$G$170)-MIN($G$2:$G$170))*100 -> 34.60658 | AG48: =(H48-MIN($H$2:$H$170))/(MAX($H$2:$H$170)-MIN($H$2:$H$170))*100 -> 10.508309 | AH48: =(I48-MIN($I$2:$I$170))/(MAX($I$2:$I$170)-MIN($I$2:$I$170))*100 -> 9.3208316 | AI48: =(J48-MIN($J$2:$J$170))/(MAX($J$2:$J$170)-MIN($J$2:$J$170))*100 -> 29.438326 | AJ48: =(K48-MIN($K$2:$K$170))/(MAX($K$2:$K$170)-MIN($K$2:$K$170))*100 -> 10.692771 | AK48: =(L48-MIN($L$2:$L$170))/(MAX($L$2:$L$170)-MIN($L$2:$L$170))*100 -> 9.5941521 | AL48: =(M48-MIN($M$2:$M$170))/(MAX($M$2:$M$170)-MIN($M$2:$M$170))*100 -> 29.656575 | AM48: =(N48-MIN($N$2:$N$170))/(MAX($N$2:$N$170)-MIN($N$2:$N$170))*100 -> 10.0591 | AN48: =(O48-MIN($O$2:$O$170))/(MAX($O$2:$O$170)-MIN($O$2:$O$170))*100 -> 39.428267 | AO48: =(P48-MIN($P$2:$P$170))/(MAX($P$2:$P$170)-MIN($P$2:$P$170))*100 -> 13.514427 | AP48: =(Q48-MIN($Q$2:$Q$170))/(MAX($Q$2:$Q$170)-MIN($Q$2:$Q$170))*100 -> 90 | AQ48: =IF(AP48>=50,AP48,50) -> 90 | AR48: =(#REF!-MIN(#REF!))/(MAX(#REF!)-MIN(#REF!))*100 -> #REF! | AS48: =IF(AR48>=50,AR48,50) -> #REF! | AT48: =(U48-MIN($U$2:$U$170))/(MAX($U$2:$U$170)-MIN($U$2:$U$170))*100 -> 20.637891 | AU48: =(V48-MIN($V$2:$V$170))/(MAX($V$2:$V$170)-MIN($V$2:$V$170))*100 -> 27.405985 | AV48: =(W48-MIN($W$2:$W$170))/(MAX($W$2:$W$170)-MIN($W$2:$W$170))*100 -> 1.8906414 | AW48: =(X48-MIN($X$2:$X$170))/(MAX($X$2:$X$170)-MIN($X$2:$X$170))*100 -> 22.078879 | AX48: =(Y48-MIN($Y$2:$Y$170))/(MAX($Y$2:$Y$170)-MIN($Y$2:$Y$170))*100 -> 29.346746 | AY48: =(Z48-MIN($Z$2:$Z$170))/(MAX($Z$2:$Z$170)-MIN($Z$2:$Z$170))*100 -> 21.137175 | AZ48: =(AA48-MIN($AA$2:$AA$170))/(MAX($AA$2:$AA$170)-MIN($AA$2:$AA$170))*100 -> 43.876626 | BA48: =(AB48-MIN($AB$2:$AB$170))/(MAX($AB$2:$AB$170)-MIN($AB$2:$AB$170))*100 -> 38.619844 | BB48: =(AC48-MIN($AC$2:$AC$170))/(MAX($AC$2:$AC$170)-MIN($AC$2:$AC$170))*100 -> 45.269522 | BC48: 7 | BD48: 325334 | BE48: 2 | BF48: 2
A49: ICA | B49: ICA | C49: LA TINGUIÑA | D49: 110102 | E49: 213 | F49: 128.45995 | G49: 0.60309835 | H49: 21 | I49: 1545589.8 | J49: 73599.513 | K49: 20 | L49: 1529511 | M49: 76476 | N49: 17454.8 | O49: 2770.41 | P49: 106849.13 | Q49: 0.76 | R49: 4152268.6 | S49: 207263.8 | T49: =IF((100-IFERROR(S49/R49*100,0))=100,50,(100-IFERROR(S49/R49*100,0))) -> 95.00842 | U49: 2591 | V49: 12842176 | W49: 1730768.5 | X49: 1178 | Y49: 8600841 | Z49: 1132095 | AA49: 47487 | AB49: 2454067.1 | AC49: 92534 | AD49: =(E49-MIN($E$2:$E$170))/(MAX($E$2:$E$170)-MIN($E$2:$E$170))*100 -> 1.4318166 | AE49: =(F49-MIN($F$2:$F$170))/(MAX($F$2:$F$170)-MIN($F$2:$F$170))*100 -> 1.1142864 | AF49: =(G49-MIN($G$2:$G$170))/(MAX($G$2:$G$170)-MIN($G$2:$G$170))*100 -> 22.051538 | AG49: =(H49-MIN($H$2:$H$170))/(MAX($H$2:$H$170)-MIN($H$2:$H$170))*100 -> 1.026393 | AH49: =(I49-MIN($I$2:$I$170))/(MAX($I$2:$I$170)-MIN($I$2:$I$170))*100 -> 1.1571909 | AI49: =(J49-MIN($J$2:$J$170))/(MAX($J$2:$J$170)-MIN($J$2:$J$170))*100 -> 37.418177 | AJ49: =(K49-MIN($K$2:$K$170))/(MAX($K$2:$K$170)-MIN($K$2:$K$170))*100 -> 1.0040161 | AK49: =(L49-MIN($L$2:$L$170))/(MAX($L$2:$L$170)-MIN($L$2:$L$170))*100 -> 1.1810458 | AL49: =(M49-MIN($M$2:$M$170))/(MAX($M$2:$M$170)-MIN($M$2:$M$170))*100 -> 38.8805 | AM49: =(N49-MIN($N$2:$N$170))/(MAX($N$2:$N$170)-MIN($N$2:$N$170))*100 -> 0.18690901 | AN49: =(O49-MIN($O$2:$O$170))/(MAX($O$2:$O$170)-MIN($O$2:$O$170))*100 -> 1.0262933 | AO49: =(P49-MIN($P$2:$P$170))/(MAX($P$2:$P$170)-MIN($P$2:$P$170))*100 -> 0.43417838 | AP49: =(Q49-MIN($Q$2:$Q$170))/(MAX($Q$2:$Q$170)-MIN($Q$2:$Q$170))*100 -> 76 | AQ49: =IF(AP49>=50,AP49,50) -> 76 | AR49: =(#REF!-MIN(#REF!))/(MAX(#REF!)-MIN(#REF!))*100 -> #REF! | AS49: =IF(AR49>=50,AR49,50) -> #REF! | AT49: =(U49-MIN($U$2:$U$170))/(MAX($U$2:$U$170)-MIN($U$2:$U$170))*100 -> 2.6364482 | AU49: =(V49-MIN($V$2:$V$170))/(MAX($V$2:$V$170)-MIN($V$2:$V$170))*100 -> 2.3182854 | AV49: =(W49-MIN($W$2:$W$170))/(MAX($W$2:$W$170)-MIN($W$2:$W$170))*100 -> 0.16898153 | AW49: =(X49-MIN($X$2:$X$170))/(MAX($X$2:$X$170)-MIN($X$2:$X$170))*100 -> 3.0409141 | AX49: =(Y49-MIN($Y$2:$Y$170))/(MAX($Y$2:$Y$170)-MIN($Y$2:$Y$170))*100 -> 2.6551333 | AY49: =(Z49-MIN($Z$2:$Z$170))/(MAX($Z$2:$Z$170)-MIN($Z$2:$Z$170))*100 -> 1.5022191 | AZ49: =(AA49-MIN($AA$2:$AA$170))/(MAX($AA$2:$AA$170)-MIN($AA$2:$AA$170))*100 -> 1.9598663 | BA49: =(AB49-MIN($AB$2:$AB$170))/(MAX($AB$2:$AB$170)-MIN($AB$2:$AB$170))*100 -> 0.44507001 | BB49: =(AC49-MIN($AC$2:$AC$170))/(MAX($AC$2:$AC$170)-MIN($AC$2:$AC$170))*100 -> 1.4983662 | BC49: 1.1 | BD49: 47475 | BE49: 0 | BF49: 0
A50: ICA | B50: ICA | C50: LOS AQUIJES | D50: 110103 | E50: 39 | F50: 23.875338 | G50: 0.61218815 | H50: 12 | I50: 712439.34 | J50: 59369.945 | K50: 12 | L50: 712439 | M50: 59370 | N50: 11201.8 | O50: 3339.76 | P50: 18255.77 | Q50: 0.71 | R50: 1436012.2 | S50: 22801.79 | T50: =IF((100-IFERROR(S50/R50*100,0))=100,50,(100-IFERROR(S50/R50*100,0))) -> 98.412145 | U50: 907 | V50: 7341327.6 | W50: 369274.76 | X50: 434 | Y50: 5672078 | Z50: 369275 | AA50: 938 | AB50: 32831.7 | AC50: 1308 | AD50: =(E50-MIN($E$2:$E$170))/(MAX($E$2:$E$170)-MIN($E$2:$E$170))*100 -> 0.23404695 | AE50: =(F50-MIN($F$2:$F$170))/(MAX($F$2:$F$170)-MIN($F$2:$F$170))*100 -> 0.1893146 | AF50: =(G50-MIN($G$2:$G$170))/(MAX($G$2:$G$170)-MIN($G$2:$G$170))*100 -> 22.852512 | AG50: =(H50-MIN($H$2:$H$170))/(MAX($H$2:$H$170)-MIN($H$2:$H$170))*100 -> 0.58651026 | AH50: =(I50-MIN($I$2:$I$170))/(MAX($I$2:$I$170)-MIN($I$2:$I$170))*100 -> 0.53340694 | AI50: =(J50-MIN($J$2:$J$170))/(MAX($J$2:$J$170)-MIN($J$2:$J$170))*100 -> 30.183829 | AJ50: =(K50-MIN($K$2:$K$170))/(MAX($K$2:$K$170)-MIN($K$2:$K$170))*100 -> 0.60240964 | AK50: =(L50-MIN($L$2:$L$170))/(MAX($L$2:$L$170)-MIN($L$2:$L$170))*100 -> 0.55012553 | AL50: =(M50-MIN($M$2:$M$170))/(MAX($M$2:$M$170)-MIN($M$2:$M$170))*100 -> 30.183787 | AM50: =(N50-MIN($N$2:$N$170))/(MAX($N$2:$N$170)-MIN($N$2:$N$170))*100 -> 0.1199508 | AN50: =(O50-MIN($O$2:$O$170))/(MAX($O$2:$O$170)-MIN($O$2:$O$170))*100 -> 1.237208 | AO50: =(P50-MIN($P$2:$P$170))/(MAX($P$2:$P$170)-MIN($P$2:$P$170))*100 -> 0.074181799 | AP50: =(Q50-MIN($Q$2:$Q$170))/(MAX($Q$2:$Q$170)-MIN($Q$2:$Q$170))*100 -> 71 | AQ50: =IF(AP50>=50,AP50,50) -> 71 | AR50: =(#REF!-MIN(#REF!))/(MAX(#REF!)-MIN(#REF!))*100 -> #REF! | AS50: =IF(AR50>=50,AR50,50) -> #REF! | AT50: =(U50-MIN($U$2:$U$170))/(MAX($U$2:$U$170)-MIN($U$2:$U$170))*100 -> 0.87602839 | AU50: =(V50-MIN($V$2:$V$170))/(MAX($V$2:$V$170)-MIN($V$2:$V$170))*100 -> 1.3162386 | AV50: =(W50-MIN($W$2:$W$170))/(MAX($W$2:$W$170)-MIN($W$2:$W$170))*100 -> 0.036040723 | AW50: =(X50-MIN($X$2:$X$170))/(MAX($X$2:$X$170)-MIN($X$2:$X$170))*100 -> 1.0820915 | AX50: =(Y50-MIN($Y$2:$Y$170))/(MAX($Y$2:$Y$170)-MIN($Y$2:$Y$170))*100 -> 1.744572 | AY50: =(Z50-MIN($Z$2:$Z$170))/(MAX($Z$2:$Z$170)-MIN($Z$2:$Z$170))*100 -> 0.48985366 | AZ50: =(AA50-MIN($AA$2:$AA$170))/(MAX($AA$2:$AA$170)-MIN($AA$2:$AA$170))*100 -> 0.036404011 | BA50: =(AB50-MIN($AB$2:$AB$170))/(MAX($AB$2:$AB$170)-MIN($AB$2:$AB$170))*100 -> 0.0059543624 | BB50: =(AC50-MIN($AC$2:$AC$170))/(MAX($AC$2:$AC$170)-MIN($AC$2:$AC$170))*100 -> 0.020141552 | BC50: 0.2 | BD50: 8880 | BE50: 0 | BF50: 0
A51: ICA | B51: ICA | C51: PARCONA | D51: 110106 | E51: 224 | F51: 123.37311 | G51: 0.55077283 | H51: 30 | I51: 1628766.4 | J51: 54292.212 | K51: 30 | L51: 1628766 | M51: 54292 | N51: 139305.99 | O51: 24946.86 | P51: 277456.03 | Q51: 0.96 | R51: 5084965.4 | S51: 38227.84 | T51: =IF((100-IFERROR(S51/R51*100,0))=100,50,(100-IFERROR(S51/R51*100,0))) -> 99.248218 | U51: 3648 | V51: 19283293 | W51: 1099424.7 | X51: 1617 | Y51: 11574617 | Z51: 660562 | AA51: 88836 | AB51: 5020122 | AC51: 180665 | AD51: =(E51-MIN($E$2:$E$170))/(MAX($E$2:$E$170)-MIN($E$2:$E$170))*100 -> 1.5075377 | AE51: =(F51-MIN($F$2:$F$170))/(MAX($F$2:$F$170)-MIN($F$2:$F$170))*100 -> 1.0692972 | AF51: =(G51-MIN($G$2:$G$170))/(MAX($G$2:$G$170)-MIN($G$2:$G$170))*100 -> 17.440725 | AG51: =(H51-MIN($H$2:$H$170))/(MAX($H$2:$H$170)-MIN($H$2:$H$170))*100 -> 1.4662757 | AH51: =(I51-MIN($I$2:$I$170))/(MAX($I$2:$I$170)-MIN($I$2:$I$170))*100 -> 1.2194656 | AI51: =(J51-MIN($J$2:$J$170))/(MAX($J$2:$J$170)-MIN($J$2:$J$170))*100 -> 27.602297 | AJ51: =(K51-MIN($K$2:$K$170))/(MAX($K$2:$K$170)-MIN($K$2:$K$170))*100 -> 1.5060241 | AK51: =(L51-MIN($L$2:$L$170))/(MAX($L$2:$L$170)-MIN($L$2:$L$170))*100 -> 1.2576877 | AL51: =(M51-MIN($M$2:$M$170))/(MAX($M$2:$M$170)-MIN($M$2:$M$170))*100 -> 27.602125 | AM51: =(N51-MIN($N$2:$N$170))/(MAX($N$2:$N$170)-MIN($N$2:$N$170))*100 -> 1.4917125 | AN51: =(O51-MIN($O$2:$O$170))/(MAX($O$2:$O$170)-MIN($O$2:$O$170))*100 -> 9.2415188 | AO51: =(P51-MIN($P$2:$P$170))/(MAX($P$2:$P$170)-MIN($P$2:$P$170))*100 -> 1.1274346 | AP51: =(Q51-MIN($Q$2:$Q$170))/(MAX($Q$2:$Q$170)-MIN($Q$2:$Q$170))*100 -> 96 | AQ51: =IF(AP51>=50,AP51,50) -> 96 | AR51: =(#REF!-MIN(#REF!))/(MAX(#REF!)-MIN(#REF!))*100 -> #REF! | AS51: =IF(AR51>=50,AR51,50) -> #REF! | AT51: =(U51-MIN($U$2:$U$170))/(MAX($U$2:$U$170)-MIN($U$2:$U$170))*100 -> 3.7414148 | AU51: =(V51-MIN($V$2:$V$170))/(MAX($V$2:$V$170)-MIN($V$2:$V$170))*100 -> 3.4916138 | AV51: =(W51-MIN($W$2:$W$170))/(MAX($W$2:$W$170)-MIN($W$2:$W$170))*100 -> 0.10733501 | AW51: =(X51-MIN($X$2:$X$170))/(MAX($X$2:$X$170)-MIN($X$2:$X$170))*100 -> 4.1967248 | AX51: =(Y51-MIN($Y$2:$Y$170))/(MAX($Y$2:$Y$170)-MIN($Y$2:$Y$170))*100 -> 3.5796892 | AY51: =(Z51-MIN($Z$2:$Z$170))/(MAX($Z$2:$Z$170)-MIN($Z$2:$Z$170))*100 -> 0.87643096 | AZ51: =(AA51-MIN($AA$2:$AA$170))/(MAX($AA$2:$AA$170)-MIN($AA$2:$AA$170))*100 -> 3.6684582 | BA51: =(AB51-MIN($AB$2:$AB$170))/(MAX($AB$2:$AB$170)-MIN($AB$2:$AB$170))*100 -> 0.91045014 | BB51: =(AC51-MIN($AC$2:$AC$170))/(MAX($AC$2:$AC$170)-MIN($AC$2:$AC$170))*100 -> 2.9264394 | BC51: 1.6 | BD51: 66478 | BE51: 0 | BF51: 0
