Workbook

Sheet Resumen
B2: Portafolio de Modelos & Analítica | G2: Actualizado: | H2: 46195
B3: Banca Negocio · NBC Empresas — Advanced Analytics & AI
B4: Jefatura de Analytics · Karen Sofía Barrozo
B6: TOTAL PROYECTOS | D6: EN DESARROLLO | F6: EN PILOTO | H6: EN PRODUCCIÓN
B7: =COUNTA('Backlog Proyectos'!C5:C200) -> 4 | D7: =COUNTIF('Backlog Proyectos'!G5:G200,"En desarrollo") -> 3 | F7: =COUNTIF('Backlog Proyectos'!G5:G200,"Piloto") -> 1 | H7: =COUNTIF('Backlog Proyectos'!G5:G200,"Producción / Monitoreo") -> 0
B11: Distribución por Estado | E11: Distribución por Prioridad
B12: Estado | C12: N° Proyectos | E12: Prioridad | F12: N° Proyectos
B13: Backlog | C13: =COUNTIF('Backlog Proyectos'!G5:G200,B13) -> 0 | E13: Alta | F13: =COUNTIF('Backlog Proyectos'!F5:F200,E13) -> 3
B14: En desarrollo | C14: =COUNTIF('Backlog Proyectos'!G5:G200,B14) -> 3 | E14: Media | F14: =COUNTIF('Backlog Proyectos'!F5:F200,E14) -> 1
B15: Piloto | C15: =COUNTIF('Backlog Proyectos'!G5:G200,B15) -> 1 | E15: Baja | F15: =COUNTIF('Backlog Proyectos'!F5:F200,E15) -> 0
B16: Producción / Monitoreo | C16: =COUNTIF('Backlog Proyectos'!G5:G200,B16) -> 0
B17: Pausado | C17: =COUNTIF('Backlog Proyectos'!G5:G200,B17) -> 0 | E17: Impacto Económico Esperado del Portafolio (S/ MM)
B18: Completado | C18: =COUNTIF('Backlog Proyectos'!G5:G200,B18) -> 0 | E18: =SUM('Backlog Proyectos'!N5:N200) -> 0
B19: TOTAL | C19: =SUM(C13:C18) -> 4
B20: Próximos Hitos
B21: Proyecto | C21: Próximo Paso / Hito | D21: Fecha Objetivo | E21: Responsable
B22: ='Backlog Proyectos'!C5 -> Asistente de IA Desembolso (Titán) | C22: ='Backlog Proyectos'!L5 -> Despliegue en Copilot Studio vía Cloudflare Tunnel y medir precisión con GF declarado. | D22: ='Backlog Proyectos'!K5 -> 46218 | E22: ='Backlog Proyectos'!H5 -> Sofía
B23: ='Backlog Proyectos'!C6 -> Zonas Potenciales | C23: ='Backlog Proyectos'!L6 -> Actualizar base y medir el impacto económico del proyecto. | D23: ='Backlog Proyectos'!K6 -> 46233 | E23: ='Backlog Proyectos'!H6 -> Fernando
B24: ='Backlog Proyectos'!C7 -> Modelo de Fuga (NBC Empresas) | C24: ='Backlog Proyectos'!L7 -> Actualizar base de despliegue y cerrar contrato de columnas. | D24: ='Backlog Proyectos'!K7 -> 46249 | E24: ='Backlog Proyectos'!H7 -> Sofía
B25: ='Backlog Proyectos'!C8 -> Modelo de Izipay (Propensión) | C25: ='Backlog Proyectos'!L8 -> Backtest sobre gestión, medir impacto de flujo transaccional, añadir variables (cash-in: planillas, pago serv.) y descriptivo del target. | D25: ='Backlog Proyectos'!K8 -> 46234 | E25: ='Backlog Proyectos'!H8 -> Sofía

Sheet Backlog Proyectos
B2: Backlog de Proyectos & Modelos
B3: Vista de gestión — editable. Usa las listas desplegables en Categoría, Prioridad y Estado.
B4: ID | C4: Proyecto / Modelo | D4: Categoría | E4: Objetivo / Descripción | F4: Prioridad | G4: Estado | H4: Responsable | I4: Aprobador | J4: Inicio | K4: Hito / Fecha objetivo | L4: Próximo Paso | M4: % Avance | N4: Impacto Esp. (S/ MM) | O4: Riesgos / Bloqueos
B5: 1 | C5: Asistente de IA Desembolso (Titán) | D5: Agente IA | E5: Agente conversacional (FastAPI) que apoya la decisión de desembolso y compra de deuda; alertas de variación de deuda, campos SBS/atraso. Despliegue en Microsoft Copilot Studio. | F5: Alta | G5: En desarrollo | H5: Sofía | I5: Kevin Berrios | J5: 45962 | K5: 46218 | L5: Despliegue en Copilot Studio vía Cloudflare Tunnel y medir precisión con GF declarado. | M5: 0.7 | O5: Diferencia de precisión 65.7% (GF declarado) vs 0.4% (margen_asignado autónomo).
B6: 2 | C6: Zonas Potenciales | D6: Analítica / Geo | E6: Identificación y priorización de zonas comerciales potenciales (Gamarra/Arequipa) y rutas comerciales. Geolocalización SUNAT + Haversine. | F6: Media | G6: Piloto | H6: Fernando | I6: Patsy Colonio | J6: 45992 | K6: 46233 | L6: Actualizar base y medir el impacto económico del proyecto. | M6: 0.5 | O6: Pendiente refresco de base de direcciones fiscales.
B7: 3 | C7: Modelo de Fuga (NBC Empresas) | D7: Modelo ML | E7: Predicción de fuga / compra de deuda para Banca Negocio. Pipeline SQL en Athena con target y features parametrizados (251+ variables) y diccionario de datos. | F7: Alta | G7: En desarrollo | H7: Sofía | I7: Kevin Berrios | J7: 45931 | K7: 46249 | L7: Actualizar base de despliegue y cerrar contrato de columnas. | M7: 0.65 | O7: Hallazgo: IBK ya era banco dominante (SOW prom. 77%) antes de la fuga → problema de retención.
B8: 4 | C8: Modelo de Izipay (Propensión) | D8: Modelo ML | E8: Refactor del pipeline de propensión Izipay: plantilla SQL_BASE unificada con build_train()/build_score(); backtest y recalibración por grupos. | F8: Alta | G8: En desarrollo | H8: Sofía | I8: Patsy Colonio | J8: 45992 | K8: 46234 | L8: Backtest sobre gestión, medir impacto de flujo transaccional, añadir variables (cash-in: planillas, pago serv.) y descriptivo del target. | M8: 0.55 | O8: Decisión abierta: contrato de columnas canónico vs feature list del modelo serializado.
B9: 5
B10: 6
B11: 7
B12: 8
B13: 9
B14: 10
B15: 11
B16: 12

Sheet Fuentes de Datos
B2: Fuentes de Datos & Certificación
B3: Inventario de insumos de datos y su estado de certificación.
B4: Fuente / Tabla | C4: Esquema (Athena) | D4: Tipo | E4: Estado | F4: Responsable | G4: Proyecto(s) que la usan | H4: Últ. actualización | I4: Observaciones
B5: Data Desembolsos general | C5: disc_comercial | D5: Insumo | E5: Certificado | F5: Sofía | G5: Asistente IA Desembolso / Fuga
B6: Funnel BN | C6: disc_comercial | D6: Insumo | E6: Certificado | F6: Sofía | G6: Mejor Canal / Fuga
B7: Gescom TLV | C7: disc_comercial | D7: Insumo | E7: Certificado | F7: Sofía | G7: TLV B / Canales
B8: Data Izipay | C8: e_perm_aws | D8: Insumo | E8: En certificación | F8: Sofía | G8: Modelo de Izipay | I8: Añadir variables cash-in (planillas, pago serv.).
B9: BASE_BPE_ADQ_ACT | C9: e_perm_aws | D9: Insumo | E9: Despriorizado | F9: — | G9: — | I9: Despriorizado por el momento.

Sheet Pilotos
B2: Seguimiento de Pilotos & Experimentos
B3: Pilotos con grupo control, métrica de éxito y decisión.
B4: Piloto | C4: Proyecto asociado | D4: Hipótesis | E4: Diseño (Piloto / Control) | F4: Métrica de éxito | G4: Periodo | H4: Resultado | I4: Estado | J4: Decisión / Siguientes pasos
B5: Piloto / Control Cartera | C5: Cartera priorización | D5: La priorización por modelo incrementa el monto colocado vs gestión estándar. | E5: Terciles IAM: 14 Piloto vs 14 Control | F5: Monto colocado (S/) | G5: Ene-26 | H5: Piloto S/23.45M vs Control S/21.56M (+S/4.85M) | I5: Completado | J5: Escalar priorización; baseline de referencia Ene-26.
B6: Zonas Potenciales | C6: Zonas Potenciales | D6: Las zonas priorizadas generan mayor conversión/colocación. | E6: Estratificado por canal × score | F6: Impacto económico (S/) | G6: En curso | H6: Por medir | I6: Piloto | J6: Actualizar base y medir impacto.
